Workbook

Sheet 2023 Tier 1
A1: Firm Name | B1: Retail Revenue | C1: Rest. Revenue | D1: Multifamily Revenue | E1: Industrial Revenue | F1: Data Center Revenue | G1: Hospitality Revenue | H1: Total Relevant Revenue | I1: LI Employees | J1: Data Source | K1: C1 Name | L1: C1 Title | M1: C1 Email | N1: C1 Phone | O1: C1 Office Address | P1: C2 Name | Q1: C2 Title | R1: C2 Email | S1: C2 Phone | T1: C2 Office Address | U1: C3 Name | V1: C3 Title | W1: C3 Email | X1: C3 Phone | Y1: C3 Office Address | Z1: C4 Name | AA1: C4 Title | AB1: C4 Email | AC1: C4 Phone | AD1: C4 Office Address | AE1: C5 Name | AF1: C5 Title | AG1: C5 Email | AH1: C5 Phone | AI1: C5 Office Address
A2: NORR | B2: 43068568 | C2: 11903850 | D2: 28972291 | E2: 8954881 | G2: 4226719 | H2: 97126309 | I2: 875 | J2: BDC 2023 | K2: Jonathan Hughes | L2: Chief Operating Officer | M2: jonathan.hughes@norr.com | N2: 416 944 7837 | O2: 175 Bloor Street East, Toronto, Ontario, M4W 3R8, CA | P2: Ricardo Avila | Q2: Senior Principal, Retail | U2: Anthony Ricciuti | V2: Executive Vice President, Retail | Z2: Andrea Davis | AA2: Principal, Retail | AE2: How can | AF2: Vice President, Operations, US
A3: GPD Group | B3: 28064000 | C3: 14364000 | H3: 42428000 | I3: 705 | J3: BDC 2023 | K3: Jeff Evans | L3: Senior Vice President, Operations | P3: Becky McAdams | Q3: Vice President, Operations | U3: Trever Powers | V3: Vice President, Operations | Z3: Jake Bendik | AA3: Director, Retail/Commercial | AE3: Steve Turner | AF3: National Leader, Strategy and Growth, Multi Site Programs
A4: HFA | I4: 670 | J4: ICSC CB | K4: Ryan Ray | L4: Chief Operating Officer | P4: Aksel Solberg | Q4: Design Development Studio Lead | U4: James Owens | V4: Vice President | Z4: Bo Ebbrecht | AA4: Vice President | AE4: Marc Jennings | AF4: Vice President
A5: H2M Architects + Engineers | I5: 629 | J5: ICSC CB | K5: Joseph Mottola | L5: Chief Operating Officer | P5: Ray Givargis | Q5: Studio Director | U5: Phil Schade | V5: Senior Vice President, Market Director, Energy
A6: WATG | D6: 5653143 | G6: 77924699 | H6: 83577842 | I6: 577 | J6: BDC 2023
A7: HED | D7: 9426600 | E7: 4600000 | F7: 20200000 | H7: 34226600 | I7: 575 | J7: BDC 2023 | K7: Michael Cooper | L7: President | P7: Anna McDougall | Q7: Principal, Operations Practice Leader | U7: Jerome (Otis) Odell | V7: Principal, Business Leader, Housing and Mixed Use
A8: KTGY | B8: 3736599 | D8: 16117830 | G8: 6742437 | H8: 26596866 | I8: 514 | J8: BDC 2023 | K8: David Senden | L8: Principal | P8: Keith Labus | Q8: Principal | U8: Adam Hale | V8: Director, Production | Z8: Bindiya Agarwal | AA8: Director, Production | AE8: Brandon Wernli | AF8: Executive Director, Production
A9: Cushing Terrell | B9: 26457330 | D9: 6241505 | E9: 2391131 | F9: 2705244 | H9: 37795210 | I9: 508 | J9: BDC 2023 | K9: Martin Byrnes | L9: Chief Operating Officer | P9: Nicole Dovel-Moore | Q9: Associate Principal | U9: Joshua Hersel | V9: Director, Multi-Family Design | Z9: Brad Sperry | AA9: Principal, Design Director | AE9: Rob Arthur | AF9: Principal, Design Director
A10: Little | I10: 500 | J10: ICSC CB | K10: Charles Todd | L10: Chief Operating Officer | P10: Sarah Curtis | Q10: Principal | U10: Michael Magee | V10: Principal | Z10: Heather Nifong | AA10: Principal | AE10: John Quinn | AF10: Principal
A11: MG2 - WHAT NOW THAT IT IS CED?? | B11: 38313224 | D11: 4845824 | E11: 3022289 | H11: 46181337 | I11: 498 | J11: BDC 2023
A12: BL Companies | I12: 494 | J12: ICSC CB | K12: Derek Kohl | L12: VP of Operations | P12: Bill Fries | Q12: Director, Project Development | U12: Barbara Joslin | V12: Director, Project Development | Z12: Amy Samuelson | AA12: Executive Director of Architecture and Building Engineering | AE12: Ian McPhillips | AF12: Director, Energy
A13: LS3P Associates | B13: 5964397 | C13: 2586784 | D13: 12355944 | E13: 7373084 | G13: 2798008 | H13: 31078217 | I13: 488 | J13: BDC 2023 | K13: George Temple | L13: Chief Operating Officer | P13: Neil Dawson | Q13: Living Practice Leader | U13: Chris Owings | V13: Senior Practice Professional, Urban Environments | Z13: David Burt | AA13: Firmwide Hospitality Sector Leader / Vice President | AE13: Roy Selvidge | AF13: Firmwide Federal & Industrial Sector Leader
A14: Larson Design Group | I14: 472 | J14: ICSC CB | K14: David Schaarsmith | L14: Chief Operating Officer | P14: Ronald Kretz | Q14: Built Environment Operations Manager and Vice President | U14: Andrew Dorin | V14: Market Lead & Vice President
A15: AO | B15: 35332000 | C15: 1752000 | D15: 52485000 | E15: 8187000 | F15: 1944000 | G15: 6903000 | H15: 106603000 | I15: 446 | J15: BDC 2023 | P15: Rob Budetti | Q15: Managing Partner | U15: Jeff Rabbitt | V15: Partner | Z15: Richard Clark | AA15: Partner | AE15: RC Alley | AF15: Managing Partner
A16: Moody Nolan | B16: 6334173 | D16: 13233668 | H16: 19567841 | I16: 375 | J16: BDC 2023 | K16: Allen Schaffer | L16: Partner, Chief Operating Office, Chief Sustainability Officer | P16: Todd Dove | Q16: Partner, Retail Practice Leader | U16: Yanitza Brongers-Marrero | V16: Partner, Housing Practice Leader | Z16: Jay Boone | AA16: Partner, Director of General Architecture | AE16: Julie Cook | AF16: Partner, Director of Project Delivery
A17: Progressive Companies | I17: 374 | J17: ICSC CB | K17: Wes Jones | L17: Managing Principal | P17: Ryan Doherty | Q17: Principal, Mixed-use Practice Leader | U17: Doug Wurl | V17: Principal, Director of Program Delivery | Z17: Bill Culhane | AA17: Principal, Director of Project Delivery | AE17: Rand Harder | AF17: Senior Design Architect
A18: Hord Coplan Macht | D18: 26297448 | H18: 26297448 | I18: 360 | J18: BDC 2023 | K18: Joe Schneider | L18: Managing Principal | P18: John Harris | Q18: Managing Principal | U18: Liz Peterson | V18: Principal
A19: WDG | D19: 23937000 | H19: 23937000 | I19: 327 | J19: BDC 2023 | K19: Robyn Jacobson | L19: Managing Principal | P19: Siti Abdul-Rahman | Q19: Managing Principal | U19: Will Duncan | V19: Managing Principal | Z19: Doug James | AA19: Principal | AE19: Eric Schlegel | AF19: Principal
A20: Cooper Carry | B20: 9394769 | C20: 4625642 | D20: 23705448 | F20: 1656006 | G20: 19400953 | H20: 58782818 | I20: 316 | J20: BDC 2023 | K20: Kyle Reis | L20: Principal, President and CEO | P20: John Ward | Q20: Principal | U20: Angelo Carusi | V20: Principal, Atlanta Office Managing Director | Z20: Alex Lopatynsky | AA20: Principal, New York Office Managing Director | AE20: Kathy Logan | AF20: Principal
A21: Galloway & Company, Inc | I21: 313 | J21: ICSC CB | K21: Darren Bruns | L21: Chief Operating Officer | P21: Kristoffer Kenton | Q21: Director of Architecture, Principal | U21: Chris Carlson | V21: Regional Architectural Team Manager, Principal | Z21: Gary Rhodes | AA21: Regional Architectural Team Manager, Principal | AE21: Blake Olson | AF21: Architectural Project Manager, Principal
A22: Greenberg Farrow | B22: 37688000 | C22: 14560000 | H22: 52248000 | I22: 302 | J22: BDC 2023 | K22: Rodeny E. Abney, Jr | L22: CFO, Senior Vice President | P22: Ali Yadegari | Q22: Managing Director of Roll-Out Architecture | U22: Krista Karlson | V22: Managing Director of Charlotte | Z22: Kelly Hosack | AA22: Managing Director of Charleston | AE22: Mike Haas | AF22: Managing Director of Structural Engineering
A23: Cuningham | B23: 15220694 | C23: 5556771 | D23: 6149658 | H23: 26927123 | I23: 294 | J23: BDC 2023 | K23: Dan Olic | L23: Principal, Chief Operating Officer | P23: Charles Stoffel | Q23: Principal, Director of Technical Design & Delivery | U23: Gregory Houck | V23: Principal | Z23: Jeremy Agraz | AA23: Associate Principal, Executive Director - Marketing + Strategy | AE23: Jeffrey Mandyck | AF23: Director of Strategy
A24: BSB Design | D24: 24639893 | H24: 24639893 | I24: 286 | J24: BDC 2023 | K24: Chris Jorgensen | L24: Vice President of Operations | P24: Deena A. Roumeliotis | Q24: Associate, Director of Production | U24: Michael Tripodi | V24: Associate, Director of Production | Z24: Paul Penman | AA24: Associate, Director of Production | AE24: Chris Blackburn | AF24: Associate, Director of Production
A25: Solomon Cordwell Buenz (SCB) | D25: 64982137 | G25: 11891646 | H25: 76873783 | I25: 257 | J25: BDC 2023 | K25: Renee Sprogis-Marohn | L25: Chief Operating Officer
A26: Mithun | D26: 14496274 | H26: 14496274 | I26: 249 | J26: BDC 2023 | K26: Dave Goldberg | L26: President | P26: Jason Steiner | Q26: Partner
A27: Vocon | B27: 7884889 | D27: 8348706 | H27: 16233595 | I27: 245 | J27: BDC 2023 | K27: Laura Rees | L27: Chief Operating Officer
A28: Cuhaci Peterson | I28: 235 | J28: ICSC CB
A29: Benchmark Group | I29: 234 | J29: ICSC CB
A30: LRK | D30: 16700000 | H30: 16700000 | I30: 231 | J30: BDC 2023 | K30: Tony Pellicciotti | L30: Managing Principal
A31: RATIO Design | B31: 3122293 | C31: 3112262 | D31: 10357542 | G31: 7535753 | H31: 24127850 | I31: 227 | J31: BDC 2023 | K31: Bill Browne | L31: Principal, CEO | P31: Chris Meier | Q31: Principal / Dir. of Ops & Indianaplois Studio Leader | U31: Hal Bowen | V31: Principal / Raleigh Studio Leader | Z31: Clay Markham | AA31: Principal | AE31: Eric Doner | AF31: Associate Principal
A32: Dahlin Architecture | Planning | Interiors | D32: 22500000 | H32: 22500000 | I32: 224 | J32: BDC 2023 | K32: Emily A. Bonato | L32: Chief Operating Officer | P32: Lauren Jessup-Mosu | Q32: Managing Director - Regional | U32: Sean Whitacre | V32: Senior Principal / Senior Architect | Z32: Lauri Moffet-Fehlberg | AA32: Senior Vice President - Architecture | AE32: Andrew "Jack" Gallagher | AF32: Managing Principal - Austin Office
A33: Baskervill | G33: 14381252 | H33: 14381252 | I33: 223 | J33: BDC 2023 | K33: Bob Clark | L33: CEO | P33: Brad Richards | Q33: Principal, Executive Vice President | U33: Jay Woodburn | V33: Principal | Z33: Terri Callaway | AA33: Principal | AE33: Fred Hopkins | AF33: Associate, Studio Director
A34: JCJ Architecture | G34: 12039538 | H34: 12039538 | I34: 218 | J34: BDC 2023 | K34: Scott Celella | L34: Chief Operating Officer | P34: Robert Gdowski | Q34: Principal, Director of Hospitality Design | U34: Paul Hamel | V34: Director of Project Management | Z34: Jeanne Muscolino | AA34: Principal, Hospitality Market Leader | AE34: Doug Roberts | AF34: Principal
A35: Elkus Manfredi Architects | D35: 8092756 | G35: 3109129 | H35: 11201885 | I35: 210 | J35: BDC 2023

Sheet 2023 Tier 2
A1: Firm Name | B1: Retail Revenue | C1: Rest. Revenue | D1: Multifamily Revenue | E1: Industrial Revenue | F1: Data Center Revenue | G1: Hospitality Revenue | H1: Total Relevant Revenue | I1: LI Employees | J1: Data Source
A2: LEO A DALY | D2: 5358661 | E2: 12533614 | G2: 6707417 | H2: 24599692 | I2: 662 | J2: BDC 2023
A3: Barge Design Solutions | E3: 14719106 | H3: 14719106 | I3: 590 | J3: BDC 2023
A4: Little Diversified Architectural Consulting | B4: 20500780 | H4: 20500780 | I4: 501 | J4: BDC 2023
A5: Larson Design Group | B5: 17034210 | E5: 3536384 | H5: 20570594 | I5: 472 | J5: BDC 2023
A6: Ayres Associates | I6: 451 | J6: ICSC CB
A7: Moseley Architects | D7: 7212951 | H7: 7212951 | I7: 346 | J7: BDC 2023
A8: McMillan Pazdan Smith | C8: 1489679 | D8: 4330414 | E8: 7286299 | H8: 13106392 | I8: 331 | J8: BDC 2023
A9: BRR | I9: 325 | J9: ICSC CB
A10: Diamond Schmitt Architects | D10: 9127020 | H10: 9127020 | I10: 296 | J10: BDC 2023
A11: LHB | D11: 3793785 | E11: 3156753 | H11: 6950538 | I11: 269 | J11: BDC 2023
A12: TPG Architecture | B12: 10474000 | H12: 10474000 | I12: 258 | J12: BDC 2023
A13: Quinn Evans | D13: 8798319 | H13: 8798319 | I13: 249 | J13: BDC 2023
A14: BHDP Architecture | E14: 7015353 | H14: 7015353 | I14: 233 | J14: BDC 2023
A15: Handel Architects | D15: 42523884 | H15: 42523884 | I15: 194 | J15: BDC 2023
A16: Lord Aeck Sargent Planning & Design | D16: 10019663 | H16: 10019663 | I16: 188 | J16: BDC 2023
A17: Dwell Design Studio | D17: 43081125 | H17: 43081125 | I17: 186 | J17: BDC 2023
A18: Tait & Associates | I18: 184 | J18: ICSC CB
A19: RDC-S111 | B19: 25546137 | H19: 25546137 | I19: 180 | J19: BDC 2023
A20: Cromwell Architects Engineers | E20: 7744669 | H20: 7744669 | I20: 166 | J20: BDC 2023
A21: FSB Architects + Engineers | E21: 3530805 | G21: 2478377 | H21: 6009182 | I21: 164 | J21: BDC 2023
A22: Niles Bolton Associates | D22: 34215698 | H22: 34215698 | I22: 159 | J22: BDC 2023
A23: Dattner Architects | D23: 11698012 | H23: 11698012 | I23: 151 | J23: BDC 2023
A24: BAR Architects & Interiors | D24: 7825225 | H24: 7825225 | I24: 150 | J24: BDC 2023
A25: AHL | D25: 7475496 | H25: 7475496 | I25: 150 | J25: BDC 2023
A26: Aria Group Architects | B26: 15444024 | C26: 10034876 | H26: 25478900 | I26: 149 | J26: BDC 2023
A27: Cyntergy AEC | I27: 148 | J27: ICSC CB
A28: Orcutt | Winslow | B28: 5454072 | G28: 2870564 | H28: 8324636 | I28: 142 | J28: BDC 2023
A29: LK Architecture | B29: 15400000 | C29: 2200000 | G29: 3100000 | H29: 20700000 | I29: 141 | J29: BDC 2023
A30: HBG Design | G30: 20074000 | H30: 20074000 | I30: 137 | J30: BDC 2023
A31: Onyx Creative | B31: 16800000 | H31: 16800000 | I31: 131 | J31: BDC 2023
A32: SWBR | D32: 7648521 | H32: 7648521 | I32: 127 | J32: BDC 2023
A33: Chipman Design Architecture | B33: 22300000 | C33: 16300000 | H33: 38600000 | I33: 126 | J33: BDC 2023
A34: BDG Architects | I34: 124 | J34: ICSC CB
A35: FitzGerald | D35: 7138000 | H35: 7138000 | I35: 120 | J35: BDC 2023
A36: GGLO | D36: 19260795 | H36: 19260795 | I36: 116 | J36: BDC 2023
A37: Bergmeyer | B37: 11205939 | C37: 2316366 | D37: 2901318 | H37: 16423623 | I37: 116 | J37: BDC 2023
A38: Smallwood | D38: 11036238 | G38: 8257494 | H38: 19293732 | I38: 114 | J38: BDC 2023
A39: Fogarty Finger | D39: 6420000 | H39: 6420000 | I39: 113 | J39: BDC 2023
A40: GFF | B40: 3905177 | D40: 17003201 | H40: 20908378 | I40: 108 | J40: BDC 2023
A41: DAG Architects | D41: 6730409 | H41: 6730409 | I41: 100 | J41: BDC 2023
A42: FXCollaborative | D42: 7479909 | H42: 7479909 | I42: 95 | J42: BDC 2023
A43: CetraRuddy Architecture | D43: 9594620 | H43: 9594620 | I43: 93 | J43: BDC 2023
A44: Hill West Architects | D44: 16480000 | H44: 16480000 | I44: 85 | J44: BDC 2023
A45: KSS Architects | E45: 6106941 | H45: 6106941 | I45: 84 | J45: BDC 2023
A46: ArcVision Inc | I46: 84 | J46: ICSC CB
A47: Rule Joy Trammell Rubio | D47: 25078000 | H47: 25078000 | I47: 83 | J47: BDC 2023
A48: Goettsch Partners | D48: 9960000 | G48: 2590000 | H48: 12550000 | I48: 75 | J48: BDC 2023
A49: Carrier Johnson + Culture | D49: 12402554 | H49: 12402554 | I49: 74 | J49: BDC 2023
A50: Oculus | B50: 3438388 | C50: 1731678 | H50: 5170066 | I50: 73 | J50: BDC 2023
A51: Thriven Design | D51: 6640849 | H51: 6640849 | I51: 70 | J51: BDC 2023
A52: MJM Architects | I52: 67 | J52: ICSC CB
A53: bKL Architecture | D53: 12700000 | H53: 12700000 | I53: 65 | J53: BDC 2023
A54: NSPJ Architects | D54: 9456309 | H54: 9456309 | I54: 64 | J54: BDC 2023
A55: Tricarico Architecture and Design | B55: 11638000 | H55: 11638000 | I55: 63 | J55: BDC 2023
A56: Method Architecture | E56: 8682491 | H56: 8682491 | I56: 63 | J56: BDC 2023
A57: JHP Architecture / Urban Design | D57: 23575495 | H57: 23575495 | I57: 62 | J57: BDC 2023
A58: Weber Thompson | D58: 8614895 | H58: 8614895 | I58: 56 | J58: BDC 2023
A59: CTA Architects | D59: 7465335 | H59: 7465335 | I59: 56 | J59: BDC 2023
A60: //3877 | B60: 3224000 | C60: 3108000 | G60: 2735000 | H60: 9067000 | I60: 47 | J60: BDC 2023
A61: Randall-Paulson Architects | E61: 11959373 | H61: 11959373 | I61: 47 | J61: BDC 2023
A62: Curtis + Ginsberg Architects | D62: 7151365 | H62: 7151365 | I62: 47 | J62: BDC 2023
A63: FK Architecture | D63: 15425000 | H63: 15425000 | I63: 45 | J63: BDC 2023
A64: Reztark Design Studio | B64: 4508686 | D64: 3473170 | H64: 7981856 | I64: 45 | J64: BDC 2023
A65: Macgregor Associates Architects | E65: 34502771 | H65: 34502771 | I65: 41 | J65: BDC 2023
A66: GSB | G66: 7230000 | H66: 7230000 | I66: 40 | J66: BDC 2023
A67: Bignell Watkins Hasser Architects | I67: 37 | J67: ICSC CB
A68: Architectural Design Guild | I68: 30 | J68: ICSC CB
A69: Nunzio Marc DeSantis Architects | G69: 6450000 | H69: 6450000 | I69: 29 | J69: BDC 2023
A70: Kinetic Design Inc. | I70: 26 | J70: ICSC CB
A71: The Martin Architectural Group | I71: 23 | J71: ICSC CB
A72: CREATE Architecture Planning Design | I72: 17 | J72: ICSC CB
A73: Bowling Schork Design Co. | I73: 8 | J73: ICSC CB

Sheet 2023 Tier 3
A1: Firm Name | B1: Retail Revenue | C1: Rest. Revenue | D1: Multifamily Revenue | E1: Industrial Revenue | F1: Data Center Revenue | G1: Hospitality Revenue | H1: Total Relevant Revenue | I1: LI Employees | J1: Data Source
A2: HDR | F2: 100780000 | G2: 2700000 | H2: 103480000 | I2: 14915 | J2: BDC 2023
A3: Perkins&Will | B3: 6039334 | D3: 15509875 | G3: 10311923 | H3: 31861132 | I3: 2756 | J3: BDC 2023
A4: HKS | D4: 37000000 | F4: 17000000 | G4: 72000000 | H4: 126000000 | I4: 2340 | J4: BDC 2023
A5: Skidmore, Owings & Merrill | D5: 17578000 | G5: 7070000 | H5: 24648000 | I5: 1914 | J5: BDC 2023
A6: Page Southerland Page | D6: 17556240 | E6: 7745400 | F6: 27108900 | G6: 5163600 | H6: 57574140 | I6: 1902 | J6: BDC 2023
A7: Barton Malow | E7: 16001999 | H7: 16001999 | I7: 1902 | J7: BDC 2023
A8: DLR Group | B8: 21300000 | G8: 24440000 | H8: 45740000 | I8: 1820 | J8: BDC 2023
A9: Ryan Companies US | D9: 6490000 | E9: 18270000 | H9: 24760000 | I9: 1765 | J9: BDC 2023
A10: Gresham Smith | D10: 5730332 | E10: 54916599 | H10: 60646931 | I10: 1362 | J10: BDC 2023
A11: Kohn Pedersen Fox | B11: 5041570 | D11: 15846873 | G11: 5226972 | H11: 26115415 | I11: 1308 | J11: BDC 2023
A12: Corgan | F12: 122647818 | H12: 122647818 | I12: 1197 | J12: BDC 2023
A13: Perkins Eastman | G13: 17596156 | H13: 17596156 | I13: 1046 | J13: BDC 2023
A14: Whitman, Requardt & Associates | F14: 5456796 | H14: 5456796 | I14: 726 | J14: BDC 2023
A15: Goodwyn Mills Cawood | B15: 3470373 | E15: 3796954 | H15: 7267327 | I15: 572 | J15: BDC 2023

Sheet Firm Engagement
A1: FIRM | B1: Notes | J1: plant | K1: water bottle | N1: Engaged = 1
A2: NORR | C2: Andrea Davis | D2: Anthony Ricciuit | N2: 1
A3: GPD Group | C3: Becky McAdams | D3: Steve Turner | E3: Jake Bendik | F3: Trever Powers | G3: Jeff Evans | N3: 1
A4: HFA | C4: Bo Ebbrecht | D4: Aksel | E4: Nicole Bell | N4: 1
A5: H2M Architects + Engineers | C5: Jim Powers | D5: Raymond Givargis | N5: 1
A6: ADA Architects | C6: Brian Quinn | D6: James Kassay | E6: Lindsay Scott | N6: 1
A7: WATG | C7: Richard Luis | D7: Monica Cuervo | N7: 1
A8: HED | C8: Joe Furwa | N8: 1
A9: KTGY | C9: Brandon Wernli | D9: David Senden | N9: 1
A10: Cushing Terrell
A11: Little
A12: MG2 - WHAT NOW THAT IT IS CED??
A13: HP Engineering
A14: LS3P Associates
A15: Larson Design Group | C15: Andrew Dorin (changed firms) | N15: 1
A16: AO | C16: Jeff Rabbitt | D16: Johnny Hembree | M16: not interested' | N16: 1
A17: Moody Nolan | C17: Kathryn Prigmore | D17: Todd Dove | E17: Allen Schaffer | N17: 1
A18: Progressive Companies | C18: Wes Jones | D18: Ryan Doherty | N18: 1
A19: Hord Coplan Macht | C19: Tim Linko | D19: Gary Hubler | N19: 1
A20: WDG
A21: Cooper Carry | C21: Daniel Sweeney | D21: T. Jack Bagby | E21: Manny Dominguez | F21: Dots Colley | N21: 1
A22: Galloway & Company, Inc | C22: Chris Carlson | D22: Catherine Gaboian (Caty) | E22: Jenny Romano | F22: Andrew Dorin | N22: 1
A23: Greenberg Farrow | C23: Kelly Hosack | D23: Faith Hoople | N23: 1
A24: Cuningham
A25: MJM Architects | C25: Gretchen Fisher | D25: Derron Sluser | N25: 1
A26: BSB Design
A27: Silver Studio Architects (Amy's old firm) | C27: Ellen Garland | N27: 1
A28: Solomon Cordwell Buenz (SCB)
A29: Mithun
A30: Vocon
A31: Cuhaci Peterson | C31: NON TARGET | N31: 1
A32: Benchmark Group | C32: Jason Adams | D32: Jason Dodson | N32: 1
A33: LRK
A34: RATIO Design
A35: Dahlin Architecture | Planning | Interiors
A36: Baskervill | C36: Bob Clark | D36: Eric Haley | E36: Alan Davis | F36: Bob Clark | G36: Sheena Mayfield | N36: 1
A37: JCJ Architecture
A38: Elkus Manfredi Architects
A39: Cyntergy | C39: Gordy Guest (CEO) | D39: Kent Bray | E39: Seth Hildebrant | F39: Stephen Burgin | G39: Michael Hicks | H39: Linda Waytula | N39: 1
A40: LEO A DALY | C40: Cindy A. McCleary | D40: Ivan O. | N40: 1
A41: Barge Design Solutions
A42: Little Diversified Architectural Consulting
A43: Larson Design Group | N43: 1
A44: Ayres Associates
A45: Moseley Architects
A46: McMillan Pazdan Smith
A47: BRR | C47: Ryan Rosché | D47: Jill Nordin Lyons, AIA, LEED AP | K47: Jordan's Priorities
A48: Diamond Schmitt Architects | K48: Get Pilot (follow up meetings)
A49: LHB | K49: New Target Outreach (A/E [1 target client per week] + Design Tech)
A50: TPG Architecture | K50: Conference Outreach
A51: Quinn Evans | K51: Newsletter
A52: BHDP Architecture | K52: Linkedin
A53: Handel Architects | K53: CRM
A54: Lord Aeck Sargent Planning & Design
A55: Dwell Design Studio
A56: Tait & Associates | K56: Jason Lau (?)
A57: RDC-S111 | K57: Design Tech Marketing Strategy
A58: Cromwell Architects Engineers
A59: FSB Architects + Engineers
A60: Niles Bolton Associates
A61: Dattner Architects
A62: BAR Architects & Interiors
A63: AHL
A64: Aria Group Architects
A65: Orcutt | Winslow
A66: LK Architecture
A67: HBG Design
A68: Onyx Creative | C68: Don Alexander | D68: Richard Knapp | N68: 1
A69: SWBR
A70: Chipman Design Architecture
A71: BDG Architects
A72: FitzGerald
A73: GGLO
A74: Bergmeyer
A75: Smallwood
A76: Fogarty Finger
A77: GFF
A78: DAG Architects
A79: FXCollaborative
A80: CetraRuddy Architecture
... A124: Goodwyn Mills Cawood
A125: Atwell | C125: Justin Crable | D125: Kurt Belek | E125: Tracey Dubuque | F125: Brian Searcy | N125: 1
A126: OTJ Architects
A127: Bohler | C127: Daniel Danvers | D127: Andrew Mortiarty | N127: 1
A128: OTJ Architects
A129: Gensler
A130: Sargent & Lundy | C130: Abigail Buchta | D130: Mike Sronse | E130: Al Wilson | F130: Nick Wiesmen | G130: Joe Peters | H130: Matt Thibedau | N130: 1
M131: Total Firms Engaged = | N131: =SUM(N2:N130) -> 28

Sheet Centerbuild 2024
A1: Company | B1: Score | C1: Status | D1: CIV | E1: ARC | F1: STR | G1: MP | H1: ELE | I1: FP | J1: Column6 | K1: Column5 | L1: Column4 | M1: Column3 | N1: Column2 | O1: Column1 | P1: Mkt Fit (1-3) | Q1: Size (S, M, L) | R1: Column7 | S1: TZone | T1: Column8 | U1: Low-cost office? | V1: Column9 | W1: Using Competitor?
A2: HFA | B2: =Table1[[#This Row],[Column6]]+Table1[[#This Row],[Column5]]+Table1[[#This Row],[Column4]]+Table1[[#This Row],[Column3]]+Table1[[#This Row],[Column2]]+Table1[[#This Row],[Column1]]+2*(Table1[[#This Row],[Mkt Fit (1-3)]])+Table1[[#This Row],[Column7]]+Table1[[#This Row],[Column8]]+Table1[[#This Row],[Column9]] -> 23.5 | C2: Contact | D2: ✓ | E2: ✓ | F2: ✓ | G2: ✓ | H2: ✓ | I2: ✓ | J2: =IF(Table1[[#This Row],[CIV]]="⮽",0,1)*1.5 -> 1.5 | K2: =IF(Table1[[#This Row],[ARC]]="⮽",0,1)*3 -> 3 | L2: =IF(Table1[[#This Row],[STR]]="⮽",0,1)*2 -> 2 | M2: =IF(Table1[[#This Row],[MP]]="⮽",0,1) -> 1 | N2: =IF(Table1[[#This Row],[ELE]]="⮽",0,1) -> 1 | O2: =IF(Table1[[#This Row],[FP]]="⮽",0,1) -> 1 | P2: 3 | Q2: M | R2: =IF(Table1[[#This Row],[Size (S, M, L)]]="S",2,IF(Table1[[#This Row],[Size (S, M, L)]]="L",1,4)) -> 4 | S2: EST | T2: =IF(Table1[[#This Row],[TZone]]="EST",4,IF(Table1[[#This Row],[TZone]]="CST",3,IF(Table1[[#This Row],[TZone]]="MST",2,1))) -> 4 | U2: No | V2: =IF(Table1[[#This Row],[Low-cost office?]]="Yes",-4,0) -> 0
A3: Larson Design Group | B3: =Table1[[#This Row],[Column6]]+Table1[[#This Row],[Column5]]+Table1[[#This Row],[Column4]]+Table1[[#This Row],[Column3]]+Table1[[#This Row],[Column2]]+Table1[[#This Row],[Column1]]+2*(Table1[[#This Row],[Mkt Fit (1-3)]])+Table1[[#This Row],[Column7]]+Table1[[#This Row],[Column8]]+Table1[[#This Row],[Column9]] -> 23.5 | C3: Connection | D3: ✓ | E3: ✓ | F3: ✓ | G3: ✓ | H3: ✓ | I3: ✓ | J3: =IF(Table1[[#This Row],[CIV]]="⮽",0,1)*1.5 -> 1.5 | K3: =IF(Table1[[#This Row],[ARC]]="⮽",0,1)*3 -> 3 | L3: =IF(Table1[[#This Row],[STR]]="⮽",0,1)*2 -> 2 | M3: =IF(Table1[[#This Row],[MP]]="⮽",0,1) -> 1 | N3: =IF(Table1[[#This Row],[ELE]]="⮽",0,1) -> 1 | O3: =IF(Table1[[#This Row],[FP]]="⮽",0,1) -> 1 | P3: 3 | Q3: M | R3: =IF(Table1[[#This Row],[Size (S, M, L)]]="S",2,IF(Table1[[#This Row],[Size (S, M, L)]]="L",1,4)) -> 4 | S3: EST | T3: =IF(Table1[[#This Row],[TZone]]="EST",4,IF(Table1[[#This Row],[TZone]]="CST",3,IF(Table1[[#This Row],[TZone]]="MST",2,1))) -> 4 | U3: No | V3: =IF(Table1[[#This Row],[Low-cost office?]]="Yes",-4,0) -> 0
A4: Benchmark Group | B4: =Table1[[#This Row],[Column6]]+Table1[[#This Row],[Column5]]+Table1[[#This Row],[Column4]]+Table1[[#This Row],[Column3]]+Table1[[#This Row],[Column2]]+Table1[[#This Row],[Column1]]+2*(Table1[[#This Row],[Mkt Fit (1-3)]])+Table1[[#This Row],[Column7]]+Table1[[#This Row],[Column8]]+Table1[[#This Row],[Column9]] -> 22.5 | C4: Contact | D4: ✓ | E4: ✓ | F4: ✓ | G4: ✓ | H4: ✓ | I4: ✓ | J4: =IF(Table1[[#This Row],[CIV]]="⮽",0,1)*1.5 -> 1.5 | K4: =IF(Table1[[#This Row],[ARC]]="⮽",0,1)*3 -> 3 | L4: =IF(Table1[[#This Row],[STR]]="⮽",0,1)*2 -> 2 | M4: =IF(Table1[[#This Row],[MP]]="⮽",0,1) -> 1 | N4: =IF(Table1[[#This Row],[ELE]]="⮽",0,1) -> 1 | O4: =IF(Table1[[#This Row],[FP]]="⮽",0,1) -> 1 | P4: 3 | Q4: M | R4: =IF(Table1[[#This Row],[Size (S, M, L)]]="S",2,IF(Table1[[#This Row],[Size (S, M, L)]]="L",1,4)) -> 4 | S4: CST | T4: =IF(Table1[[#This Row],[TZone]]="EST",4,IF(Table1[[#This Row],[TZone]]="CST",3,IF(Table1[[#This Row],[TZone]]="MST",2,1))) -> 3 | U4: No | V4: =IF(Table1[[#This Row],[Low-cost office?]]="Yes",-4,0) -> 0
A5: Core States Group | B5: =Table1[[#This Row],[Column6]]+Table1[[#This Row],[Column5]]+Table1[[#This Row],[Column4]]+Table1[[#This Row],[Column3]]+Table1[[#This Row],[Column2]]+Table1[[#This Row],[Column1]]+2*(Table1[[#This Row],[Mkt Fit (1-3)]])+Table1[[#This Row],[Column7]]+Table1[[#This Row],[Column8]]+Table1[[#This Row],[Column9]] -> 22.5 | C5: Client | D5: ✓ | E5: ✓ | F5: ✓ | G5: ✓ | H5: ✓ | I5: ✓ | J5: =IF(Table1[[#This Row],[CIV]]="⮽",0,1)*1.5 -> 1.5 | K5: =IF(Table1[[#This Row],[ARC]]="⮽",0,1)*3 -> 3 | L5: =IF(Table1[[#This Row],[STR]]="⮽",0,1)*2 -> 2 | M5: =IF(Table1[[#This Row],[MP]]="⮽",0,1) -> 1 | N5: =IF(Table1[[#This Row],[ELE]]="⮽",0,1) -> 1 | O5: =IF(Table1[[#This Row],[FP]]="⮽",0,1) -> 1 | P5: 3 | Q5: M | R5: =IF(Table1[[#This Row],[Size (S, M, L)]]="S",2,IF(Table1[[#This Row],[Size (S, M, L)]]="L",1,4)) -> 4 | S5: CST | T5: =IF(Table1[[#This Row],[TZone]]="EST",4,IF(Table1[[#This Row],[TZone]]="CST",3,IF(Table1[[#This Row],[TZone]]="MST",2,1))) -> 3 | U5: No | V5: =IF(Table1[[#This Row],[Low-cost office?]]="Yes",-4,0) -> 0
A6: GreenbergFarrow | B6: =Table1[[#This Row],[Column6]]+Table1[[#This Row],[Column5]]+Table1[[#This Row],[Column4]]+Table1[[#This Row],[Column3]]+Table1[[#This Row],[Column2]]+Table1[[#This Row],[Column1]]+2*(Table1[[#This Row],[Mkt Fit (1-3)]])+Table1[[#This Row],[Column7]]+Table1[[#This Row],[Column8]]+Table1[[#This Row],[Column9]] -> 22.5 | C6: Target | D6: ✓ | E6: ✓ | F6: ✓ | G6: ✓ | H6: ✓ | I6: ⮽ | J6: =IF(Table1[[#This Row],[CIV]]="⮽",0,1)*1.5 -> 1.5 | K6: =IF(Table1[[#This Row],[ARC]]="⮽",0,1)*3 -> 3 | L6: =IF(Table1[[#This Row],[STR]]="⮽",0,1)*2 -> 2 | M6: =IF(Table1[[#This Row],[MP]]="⮽",0,1) -> 1 | N6: =IF(Table1[[#This Row],[ELE]]="⮽",0,1) -> 1 | O6: =IF(Table1[[#This Row],[FP]]="⮽",0,1) -> 0 | P6: 3 | Q6: M | R6: =IF(Table1[[#This Row],[Size (S, M, L)]]="S",2,IF(Table1[[#This Row],[Size (S, M, L)]]="L",1,4)) -> 4 | S6: EST | T6: =IF(Table1[[#This Row],[TZone]]="EST",4,IF(Table1[[#This Row],[TZone]]="CST",3,IF(Table1[[#This Row],[TZone]]="MST",2,1))) -> 4 | U6: No | V6: =IF(Table1[[#This Row],[Low-cost office?]]="Yes",-4,0) -> 0
A7: BL Companies | B7: =Table1[[#This Row],[Column6]]+Table1[[#This Row],[Column5]]+Table1[[#This Row],[Column4]]+Table1[[#This Row],[Column3]]+Table1[[#This Row],[Column2]]+Table1[[#This Row],[Column1]]+2*(Table1[[#This Row],[Mkt Fit (1-3)]])+Table1[[#This Row],[Column7]]+Table1[[#This Row],[Column8]]+Table1[[#This Row],[Column9]] -> 21.5 | C7: Contact | D7: ✓ | E7: ✓ | F7: ✓ | G7: ✓ | H7: ✓ | I7: ✓ | J7: =IF(Table1[[#This Row],[CIV]]="⮽",0,1)*1.5 -> 1.5 | K7: =IF(Table1[[#This Row],[ARC]]="⮽",0,1)*3 -> 3 | L7: =IF(Table1[[#This Row],[STR]]="⮽",0,1)*2 -> 2 | M7: =IF(Table1[[#This Row],[MP]]="⮽",0,1) -> 1 | N7: =IF(Table1[[#This Row],[ELE]]="⮽",0,1) -> 1 | O7: =IF(Table1[[#This Row],[FP]]="⮽",0,1) -> 1 | P7: 2 | Q7: M | R7: =IF(Table1[[#This Row],[Size (S, M, L)]]="S",2,IF(Table1[[#This Row],[Size (S, M, L)]]="L",1,4)) -> 4 | S7: EST | T7: =IF(Table1[[#This Row],[TZone]]="EST",4,IF(Table1[[#This Row],[TZone]]="CST",3,IF(Table1[[#This Row],[TZone]]="MST",2,1))) -> 4 | U7: No | V7: =IF(Table1[[#This Row],[Low-cost office?]]="Yes",-4,0) -> 0
A8: CESO | B8: =Table1[[#This Row],[Column6]]+Table1[[#This Row],[Column5]]+Table1[[#This Row],[Column4]]+Table1[[#This Row],[Column3]]+Table1[[#This Row],[Column2]]+Table1[[#This Row],[Column1]]+2*(Table1[[#This Row],[Mkt Fit (1-3)]])+Table1[[#This Row],[Column7]]+Table1[[#This Row],[Column8]]+Table1[[#This Row],[Column9]] -> 21.5 | C8: Client | D8: ✓ | E8: ✓ | F8: ✓ | G8: ✓ | H8: ✓ | I8: ⮽ | J8: =IF(Table1[[#This Row],[CIV]]="⮽",0,1)*1.5 -> 1.5 | K8: =IF(Table1[[#This Row],[ARC]]="⮽",0,1)*3 -> 3 | L8: =IF(Table1[[#This Row],[STR]]="⮽",0,1)*2 -> 2 | M8: =IF(Table1[[#This Row],[MP]]="⮽",0,1) -> 1 | N8: =IF(Table1[[#This Row],[ELE]]="⮽",0,1) -> 1 | O8: =IF(Table1[[#This Row],[FP]]="⮽",0,1) -> 0 | P8: 3 | Q8: M | R8: =IF(Table1[[#This Row],[Size (S, M, L)]]="S",2,IF(Table1[[#This Row],[Size (S, M, L)]]="L",1,4)) -> 4 | S8: CST | T8: =IF(Table1[[#This Row],[TZone]]="EST",4,IF(Table1[[#This Row],[TZone]]="CST",3,IF(Table1[[#This Row],[TZone]]="MST",2,1))) -> 3 | U8: No | V8: =IF(Table1[[#This Row],[Low-cost office?]]="Yes",-4,0) -> 0
A9: H2M Architects + Engineers | B9: =Table1[[#This Row],[Column6]]+Table1[[#This Row],[Column5]]+Table1[[#This Row],[Column4]]+Table1[[#This Row],[Column3]]+Table1[[#This Row],[Column2]]+Table1[[#This Row],[Column1]]+2*(Table1[[#This Row],[Mkt Fit (1-3)]])+Table1[[#This Row],[Column7]]+Table1[[#This Row],[Column8]]+Table1[[#This Row],[Column9]] -> 21.5 | C9: Target | D9: ✓ | E9: ✓ | F9: ✓ | G9: ✓ | H9: ✓ | I9: ✓ | J9: =IF(Table1[[#This Row],[CIV]]="⮽",0,1)*1.5 -> 1.5 | K9: =IF(Table1[[#This Row],[ARC]]="⮽",0,1)*3 -> 3 | L9: =IF(Table1[[#This Row],[STR]]="⮽",0,1)*2 -> 2 | M9: =IF(Table1[[#This Row],[MP]]="⮽",0,1) -> 1 | N9: =IF(Table1[[#This Row],[ELE]]="⮽",0,1) -> 1 | O9: =IF(Table1[[#This Row],[FP]]="⮽",0,1) -> 1 | P9: 2 | Q9: M | R9: =IF(Table1[[#This Row],[Size (S, M, L)]]="S",2,IF(Table1[[#This Row],[Size (S, M, L)]]="L",1,4)) -> 4 | S9: EST | T9: =IF(Table1[[#This Row],[TZone]]="EST",4,IF(Table1[[#This Row],[TZone]]="CST",3,IF(Table1[[#This Row],[TZone]]="MST",2,1))) -> 4 | U9: No | V9: =IF(Table1[[#This Row],[Low-cost office?]]="Yes",-4,0) -> 0
A10: Little | B10: =Table1[[#This Row],[Column6]]+Table1[[#This Row],[Column5]]+Table1[[#This Row],[Column4]]+Table1[[#This Row],[Column3]]+Table1[[#This Row],[Column2]]+Table1[[#This Row],[Column1]]+2*(Table1[[#This Row],[Mkt Fit (1-3)]])+Table1[[#This Row],[Column7]]+Table1[[#This Row],[Column8]]+Table1[[#This Row],[Column9]] -> 21 | C10: Contact | D10: ⮽ | E10: ✓ | F10: ✓ | G10: ✓ | H10: ✓ | I10: ⮽ | J10: =IF(Table1[[#This Row],[CIV]]="⮽",0,1)*1.5 -> 0 | K10: =IF(Table1[[#This Row],[ARC]]="⮽",0,1)*3 -> 3 | L10: =IF(Table1[[#This Row],[STR]]="⮽",0,1)*2 -> 2 | M10: =IF(Table1[[#This Row],[MP]]="⮽",0,1) -> 1 | N10: =IF(Table1[[#This Row],[ELE]]="⮽",0,1) -> 1 | O10: =IF(Table1[[#This Row],[FP]]="⮽",0,1) -> 0 | P10: 3 | Q10: M | R10: =IF(Table1[[#This Row],[Size (S, M, L)]]="S",2,IF(Table1[[#This Row],[Size (S, M, L)]]="L",1,4)) -> 4 | S10: EST | T10: =IF(Table1[[#This Row],[TZone]]="EST",4,IF(Table1[[#This Row],[TZone]]="CST",3,IF(Table1[[#This Row],[TZone]]="MST",2,1))) -> 4 | U10: No | V10: =IF(Table1[[#This Row],[Low-cost office?]]="Yes",-4,0) -> 0
A11: Cyntergy AEC | B11: =Table1[[#This Row],[Column6]]+Table1[[#This Row],[Column5]]+Table1[[#This Row],[Column4]]+Table1[[#This Row],[Column3]]+Table1[[#This Row],[Column2]]+Table1[[#This Row],[Column1]]+2*(Table1[[#This Row],[Mkt Fit (1-3)]])+Table1[[#This Row],[Column7]]+Table1[[#This Row],[Column8]]+Table1[[#This Row],[Column9]] -> 20.5 | C11: Target | D11: ✓ | E11: ✓ | F11: ✓ | G11: ✓ | H11: ✓ | I11: ✓ | J11: =IF(Table1[[#This Row],[CIV]]="⮽",0,1)*1.5 -> 1.5 | K11: =IF(Table1[[#This Row],[ARC]]="⮽",0,1)*3 -> 3 | L11: =IF(Table1[[#This Row],[STR]]="⮽",0,1)*2 -> 2 | M11: =IF(Table1[[#This Row],[MP]]="⮽",0,1) -> 1 | N11: =IF(Table1[[#This Row],[ELE]]="⮽",0,1) -> 1 | O11: =IF(Table1[[#This Row],[FP]]="⮽",0,1) -> 1 | P11: 3 | Q11: S | R11: =IF(Table1[[#This Row],[Size (S, M, L)]]="S",2,IF(Table1[[#This Row],[Size (S, M, L)]]="L",1,4)) -> 2 | S11: CST | T11: =IF(Table1[[#This Row],[TZone]]="EST",4,IF(Table1[[#This Row],[TZone]]="CST",3,IF(Table1[[#This Row],[TZone]]="MST",2,1))) -> 3 | U11: No | V11: =IF(Table1[[#This Row],[Low-cost office?]]="Yes",-4,0) -> 0
A12: Galloway & Company, Inc | B12: =Table1[[#This Row],[Column6]]+Table1[[#This Row],[Column5]]+Table1[[#This Row],[Column4]]+Table1[[#This Row],[Column3]]+Table1[[#This Row],[Column2]]+Table1[[#This Row],[Column1]]+2*(Table1[[#This Row],[Mkt Fit (1-3)]])+Table1[[#This Row],[Column7]]+Table1[[#This Row],[Column8]]+Table1[[#This Row],[Column9]] -> 20.5 | C12: Target | D12: ✓ | E12: ✓ | F12: ✓ | G12: ✓ | H12: ✓ | I12: ⮽ | J12: =IF(Table1[[#This Row],[CIV]]="⮽",0,1)*1.5 -> 1.5 | K12: =IF(Table1[[#This Row],[ARC]]="⮽",0,1)*3 -> 3 | L12: =IF(Table1[[#This Row],[STR]]="⮽",0,1)*2 -> 2 | M12: =IF(Table1[[#This Row],[MP]]="⮽",0,1) -> 1 | N12: =IF(Table1[[#This Row],[ELE]]="⮽",0,1) -> 1 | O12: =IF(Table1[[#This Row],[FP]]="⮽",0,1) -> 0 | P12: 3 | Q12: M | R12: =IF(Table1[[#This Row],[Size (S, M, L)]]="S",2,IF(Table1[[#This Row],[Size (S, M, L)]]="L",1,4)) -> 4 | S12: MST | T12: =IF(Table1[[#This Row],[TZone]]="EST",4,IF(Table1[[#This Row],[TZone]]="CST",3,IF(Table1[[#This Row],[TZone]]="MST",2,1))) -> 2 | U12: No | V12: =IF(Table1[[#This Row],[Low-cost office?]]="Yes",-4,0) -> 0
A13: Progressive Companies | B13: =Table1[[#This Row],[Column6]]+Table1[[#This Row],[Column5]]+Table1[[#This Row],[Column4]]+Table1[[#This Row],[Column3]]+Table1[[#This Row],[Column2]]+Table1[[#This Row],[Column1]]+2*(Table1[[#This Row],[Mkt Fit (1-3)]])+Table1[[#This Row],[Column7]]+Table1[[#This Row],[Column8]]+Table1[[#This Row],[Column9]] -> 20.5 | C13: Connection | D13: ✓ | E13: ✓ | F13: ✓ | G13: ✓ | H13: ✓ | I13: ⮽ | J13: =IF(Table1[[#This Row],[CIV]]="⮽",0,1)*1.5 -> 1.5 | K13: =IF(Table1[[#This Row],[ARC]]="⮽",0,1)*3 -> 3 | L13: =IF(Table1[[#This Row],[STR]]="⮽",0,1)*2 -> 2 | M13: =IF(Table1[[#This Row],[MP]]="⮽",0,1) -> 1 | N13: =IF(Table1[[#This Row],[ELE]]="⮽",0,1) -> 1 | O13: =IF(Table1[[#This Row],[FP]]="⮽",0,1) -> 0 | P13: 2 | Q13: M | R13: =IF(Table1[[#This Row],[Size (S, M, L)]]="S",2,IF(Table1[[#This Row],[Size (S, M, L)]]="L",1,4)) -> 4 | S13: EST | T13: =IF(Table1[[#This Row],[TZone]]="EST",4,IF(Table1[[#This Row],[TZone]]="CST",3,IF(Table1[[#This Row],[TZone]]="MST",2,1))) -> 4 | U13: No | V13: =IF(Table1[[#This Row],[Low-cost office?]]="Yes",-4,0) -> 0
... A45: DLR Group | B45: =Table1[[#This Row],[Column6]]+Table1[[#This Row],[Column5]]+Table1[[#This Row],[Column4]]+Table1[[#This Row],[Column3]]+Table1[[#This Row],[Column2]]+Table1[[#This Row],[Column1]]+2*(Table1[[#This Row],[Mkt Fit (1-3)]])+Table1[[#This Row],[Column7]]+Table1[[#This Row],[Column8]]+Table1[[#This Row],[Column9]] -> 14.5 | C45: Target | D45: ✓ | E45: ✓ | F45: ✓ | G45: ✓ | H45: ✓ | I45: ⮽ | J45: =IF(Table1[[#This Row],[CIV]]="⮽",0,1)*1.5 -> 1.5 | K45: =IF(Table1[[#This Row],[ARC]]="⮽",0,1)*3 -> 3 | L45: =IF(Table1[[#This Row],[STR]]="⮽",0,1)*2 -> 2 | M45: =IF(Table1[[#This Row],[MP]]="⮽",0,1) -> 1 | N45: =IF(Table1[[#This Row],[ELE]]="⮽",0,1) -> 1 | O45: =IF(Table1[[#This Row],[FP]]="⮽",0,1) -> 0 | P45: 1 | Q45: L | R45: =IF(Table1[[#This Row],[Size (S, M, L)]]="S",2,IF(Table1[[#This Row],[Size (S, M, L)]]="L",1,4)) -> 1 | S45: CST | T45: =IF(Table1[[#This Row],[TZone]]="EST",4,IF(Table1[[#This Row],[TZone]]="CST",3,IF(Table1[[#This Row],[TZone]]="MST",2,1))) -> 3 | U45: No | V45: =IF(Table1[[#This Row],[Low-cost office?]]="Yes",-4,0) -> 0
A46: Ensemble | B46: =Table1[[#This Row],[Column6]]+Table1[[#This Row],[Column5]]+Table1[[#This Row],[Column4]]+Table1[[#This Row],[Column3]]+Table1[[#This Row],[Column2]]+Table1[[#This Row],[Column1]]+2*(Table1[[#This Row],[Mkt Fit (1-3)]])+Table1[[#This Row],[Column7]]+Table1[[#This Row],[Column8]]+Table1[[#This Row],[Column9]] -> 14.5 | C46: Competitor | J46: =IF(Table1[[#This Row],[CIV]]="⮽",0,1)*1.5 -> 1.5 | K46: =IF(Table1[[#This Row],[ARC]]="⮽",0,1)*3 -> 3 | L46: =IF(Table1[[#This Row],[STR]]="⮽",0,1)*2 -> 2 | M46: =IF(Table1[[#This Row],[MP]]="⮽",0,1) -> 1 | N46: =IF(Table1[[#This Row],[ELE]]="⮽",0,1) -> 1 | O46: =IF(Table1[[#This Row],[FP]]="⮽",0,1) -> 1 | R46: =IF(Table1[[#This Row],[Size (S, M, L)]]="S",2,IF(Table1[[#This Row],[Size (S, M, L)]]="L",1,4)) -> 4 | T46: =IF(Table1[[#This Row],[TZone]]="EST",4,IF(Table1[[#This Row],[TZone]]="CST",3,IF(Table1[[#This Row],[TZone]]="MST",2,1))) -> 1 | V46: =IF(Table1[[#This Row],[Low-cost office?]]="Yes",-4,0) -> 0
A47: Kimley-Horn | B47: =Table1[[#This Row],[Column6]]+Table1[[#This Row],[Column5]]+Table1[[#This Row],[Column4]]+Table1[[#This Row],[Column3]]+Table1[[#This Row],[Column2]]+Table1[[#This Row],[Column1]]+2*(Table1[[#This Row],[Mkt Fit (1-3)]])+Table1[[#This Row],[Column7]]+Table1[[#This Row],[Column8]]+Table1[[#This Row],[Column9]] -> 14.5 | C47: Contact | D47: ✓ | E47: ⮽ | F47: ✓ | G47: ✓ | H47: ✓ | I47: ⮽ | J47: =IF(Table1[[#This Row],[CIV]]="⮽",0,1)*1.5 -> 1.5 | K47: =IF(Table1[[#This Row],[ARC]]="⮽",0,1)*3 -> 0 | L47: =IF(Table1[[#This Row],[STR]]="⮽",0,1)*2 -> 2 | M47: =IF(Table1[[#This Row],[MP]]="⮽",0,1) -> 1 | N47: =IF(Table1[[#This Row],[ELE]]="⮽",0,1) -> 1 | O47: =IF(Table1[[#This Row],[FP]]="⮽",0,1) -> 0 | P47: 2 | Q47: L | R47: =IF(Table1[[#This Row],[Size (S, M, L)]]="S",2,IF(Table1[[#This Row],[Size (S, M, L)]]="L",1,4)) -> 1 | S47: EST | T47: =IF(Table1[[#This Row],[TZone]]="EST",4,IF(Table1[[#This Row],[TZone]]="CST",3,IF(Table1[[#This Row],[TZone]]="MST",2,1))) -> 4 | U47: No | V47: =IF(Table1[[#This Row],[Low-cost office?]]="Yes",-4,0) -> 0
A48: RaSmith | B48: =Table1[[#This Row],[Column6]]+Table1[[#This Row],[Column5]]+Table1[[#This Row],[Column4]]+Table1[[#This Row],[Column3]]+Table1[[#This Row],[Column2]]+Table1[[#This Row],[Column1]]+2*(Table1[[#This Row],[Mkt Fit (1-3)]])+Table1[[#This Row],[Column7]]+Table1[[#This Row],[Column8]]+Table1[[#This Row],[Column9]] -> 14.5 | C48: Connection | D48: ✓ | E48: ⮽ | F48: ✓ | G48: ⮽ | H48: ⮽ | I48: ⮽ | J48: =IF(Table1[[#This Row],[CIV]]="⮽",0,1)*1.5 -> 1.5 | K48: =IF(Table1[[#This Row],[ARC]]="⮽",0,1)*3 -> 0 | L48: =IF(Table1[[#This Row],[STR]]="⮽",0,1)*2 -> 2 | M48: =IF(Table1[[#This Row],[MP]]="⮽",0,1) -> 0 | N48: =IF(Table1[[#This Row],[ELE]]="⮽",0,1) -> 0 | O48: =IF(Table1[[#This Row],[FP]]="⮽",0,1) -> 0 | P48: 2 | Q48: M | R48: =IF(Table1[[#This Row],[Size (S, M, L)]]="S",2,IF(Table1[[#This Row],[Size (S, M, L)]]="L",1,4)) -> 4 | S48: CST | T48: =IF(Table1[[#This Row],[TZone]]="EST",4,IF(Table1[[#This Row],[TZone]]="CST",3,IF(Table1[[#This Row],[TZone]]="MST",2,1))) -> 3 | U48: No | V48: =IF(Table1[[#This Row],[Low-cost office?]]="Yes",-4,0) -> 0
A49: VAA | B49: =Table1[[#This Row],[Column6]]+Table1[[#This Row],[Column5]]+Table1[[#This Row],[Column4]]+Table1[[#This Row],[Column3]]+Table1[[#This Row],[Column2]]+Table1[[#This Row],[Column1]]+2*(Table1[[#This Row],[Mkt Fit (1-3)]])+Table1[[#This Row],[Column7]]+Table1[[#This Row],[Column8]]+Table1[[#This Row],[Column9]] -> 14.5 | C49: Target | D49: ✓ | E49: ⮽ | F49: ✓ | G49: ✓ | H49: ✓ | I49: ⮽ | J49: =IF(Table1[[#This Row],[CIV]]="⮽",0,1)*1.5 -> 1.5 | K49: =IF(Table1[[#This Row],[ARC]]="⮽",0,1)*3 -> 0 | L49: =IF(Table1[[#This Row],[STR]]="⮽",0,1)*2 -> 2 | M49: =IF(Table1[[#This Row],[MP]]="⮽",0,1) -> 1 | N49: =IF(Table1[[#This Row],[ELE]]="⮽",0,1) -> 1 | O49: =IF(Table1[[#This Row],[FP]]="⮽",0,1) -> 0 | P49: 1 | Q49: M | R49: =IF(Table1[[#This Row],[Size (S, M, L)]]="S",2,IF(Table1[[#This Row],[Size (S, M, L)]]="L",1,4)) -> 4 | S49: CST | T49: =IF(Table1[[#This Row],[TZone]]="EST",4,IF(Table1[[#This Row],[TZone]]="CST",3,IF(Table1[[#This Row],[TZone]]="MST",2,1))) -> 3 | U49: No | V49: =IF(Table1[[#This Row],[Low-cost office?]]="Yes",-4,0) -> 0
A50: Woolpert Inc. | B50: =Table1[[#This Row],[Column6]]+Table1[[#This Row],[Column5]]+Table1[[#This Row],[Column4]]+Table1[[#This Row],[Column3]]+Table1[[#This Row],[Column2]]+Table1[[#This Row],[Column1]]+2*(Table1[[#This Row],[Mkt Fit (1-3)]])+Table1[[#This Row],[Column7]]+Table1[[#This Row],[Column8]]+Table1[[#This Row],[Column9]] -> 14.5 | C50: Target | D50: ✓ | E50: ✓ | F50: ✓ | G50: ✓ | H50: ✓ | I50: ⮽ | J50: =IF(Table1[[#This Row],[CIV]]="⮽",0,1)*1.5 -> 1.5 | K50: =IF(Table1[[#This Row],[ARC]]="⮽",0,1)*3 -> 3 | L50: =IF(Table1[[#This Row],[STR]]="⮽",0,1)*2 -> 2 | M50: =IF(Table1[[#This Row],[MP]]="⮽",0,1) -> 1 | N50: =IF(Table1[[#This Row],[ELE]]="⮽",0,1) -> 1 | O50: =IF(Table1[[#This Row],[FP]]="⮽",0,1) -> 0 | P50: 1 | Q50: L | R50: =IF(Table1[[#This Row],[Size (S, M, L)]]="S",2,IF(Table1[[#This Row],[Size (S, M, L)]]="L",1,4)) -> 1 | S50: CST | T50: =IF(Table1[[#This Row],[TZone]]="EST",4,IF(Table1[[#This Row],[TZone]]="CST",3,IF(Table1[[#This Row],[TZone]]="MST",2,1))) -> 3 | U50: No | V50: =IF(Table1[[#This Row],[Low-cost office?]]="Yes",-4,0) -> 0
A51: Heights Venture Architecture + Design | B51: =Table1[[#This Row],[Column6]]+Table1[[#This Row],[Column5]]+Table1[[#This Row],[Column4]]+Table1[[#This Row],[Column3]]+Table1[[#This Row],[Column2]]+Table1[[#This Row],[Column1]]+2*(Table1[[#This Row],[Mkt Fit (1-3)]])+Table1[[#This Row],[Column7]]+Table1[[#This Row],[Column8]]+Table1[[#This Row],[Column9]] -> 14 | C51: Contact | D51: ⮽ | E51: ✓ | F51: ⮽ | G51: ⮽ | H51: ⮽ | I51: ⮽ | J51: =IF(Table1[[#This Row],[CIV]]="⮽",0,1)*1.5 -> 0 | K51: =IF(Table1[[#This Row],[ARC]]="⮽",0,1)*3 -> 3 | L51: =IF(Table1[[#This Row],[STR]]="⮽",0,1)*2 -> 0 | M51: =IF(Table1[[#This Row],[MP]]="⮽",0,1) -> 0 | N51: =IF(Table1[[#This Row],[ELE]]="⮽",0,1) -> 0 | O51: =IF(Table1[[#This Row],[FP]]="⮽",0,1) -> 0 | P51: 3 | Q51: S | R51: =IF(Table1[[#This Row],[Size (S, M, L)]]="S",2,IF(Table1[[#This Row],[Size (S, M, L)]]="L",1,4)) -> 2 | S51: CST | T51: =IF(Table1[[#This Row],[TZone]]="EST",4,IF(Table1[[#This Row],[TZone]]="CST",3,IF(Table1[[#This Row],[TZone]]="MST",2,1))) -> 3 | U51: No | V51: =IF(Table1[[#This Row],[Low-cost office?]]="Yes",-4,0) -> 0
A52: Henderson Engineers, Inc | B52: =Table1[[#This Row],[Column6]]+Table1[[#This Row],[Column5]]+Table1[[#This Row],[Column4]]+Table1[[#This Row],[Column3]]+Table1[[#This Row],[Column2]]+Table1[[#This Row],[Column1]]+2*(Table1[[#This Row],[Mkt Fit (1-3)]])+Table1[[#This Row],[Column7]]+Table1[[#This Row],[Column8]]+Table1[[#This Row],[Column9]] -> 14 | C52: Target | D52: ⮽ | E52: ⮽ | F52: ⮽ | G52: ✓ | H52: ✓ | I52: ✓ | J52: =IF(Table1[[#This Row],[CIV]]="⮽",0,1)*1.5 -> 0 | K52: =IF(Table1[[#This Row],[ARC]]="⮽",0,1)*3 -> 0 | L52: =IF(Table1[[#This Row],[STR]]="⮽",0,1)*2 -> 0 | M52: =IF(Table1[[#This Row],[MP]]="⮽",0,1) -> 1 | N52: =IF(Table1[[#This Row],[ELE]]="⮽",0,1) -> 1 | O52: =IF(Table1[[#This Row],[FP]]="⮽",0,1) -> 1 | P52: 2 | Q52: M | R52: =IF(Table1[[#This Row],[Size (S, M, L)]]="S",2,IF(Table1[[#This Row],[Size (S, M, L)]]="L",1,4)) -> 4 | S52: CST | T52: =IF(Table1[[#This Row],[TZone]]="EST",4,IF(Table1[[#This Row],[TZone]]="CST",3,IF(Table1[[#This Row],[TZone]]="MST",2,1))) -> 3 | U52: No | V52: =IF(Table1[[#This Row],[Low-cost office?]]="Yes",-4,0) -> 0
A53: MCG Architecture | B53: =Table1[[#This Row],[Column6]]+Table1[[#This Row],[Column5]]+Table1[[#This Row],[Column4]]+Table1[[#This Row],[Column3]]+Table1[[#This Row],[Column2]]+Table1[[#This Row],[Column1]]+2*(Table1[[#This Row],[Mkt Fit (1-3)]])+Table1[[#This Row],[Column7]]+Table1[[#This Row],[Column8]]+Table1[[#This Row],[Column9]] -> 14 | C53: Target | D53: ⮽ | E53: ✓ | F53: ⮽ | G53: ⮽ | H53: ⮽ | I53: ⮽ | J53: =IF(Table1[[#This Row],[CIV]]="⮽",0,1)*1.5 -> 0 | K53: =IF(Table1[[#This Row],[ARC]]="⮽",0,1)*3 -> 3 | L53: =IF(Table1[[#This Row],[STR]]="⮽",0,1)*2 -> 0 | M53: =IF(Table1[[#This Row],[MP]]="⮽",0,1) -> 0 | N53: =IF(Table1[[#This Row],[ELE]]="⮽",0,1) -> 0 | O53: =IF(Table1[[#This Row],[FP]]="⮽",0,1) -> 0 | P53: 3 | Q53: S | R53: =IF(Table1[[#This Row],[Size (S, M, L)]]="S",2,IF(Table1[[#This Row],[Size (S, M, L)]]="L",1,4)) -> 2 | S53: CST | T53: =IF(Table1[[#This Row],[TZone]]="EST",4,IF(Table1[[#This Row],[TZone]]="CST",3,IF(Table1[[#This Row],[TZone]]="MST",2,1))) -> 3 | U53: No | V53: =IF(Table1[[#This Row],[Low-cost office?]]="Yes",-4,0) -> 0
A54: Nudell Architects | B54: =Table1[[#This Row],[Column6]]+Table1[[#This Row],[Column5]]+Table1[[#This Row],[Column4]]+Table1[[#This Row],[Column3]]+Table1[[#This Row],[Column2]]+Table1[[#This Row],[Column1]]+2*(Table1[[#This Row],[Mkt Fit (1-3)]])+Table1[[#This Row],[Column7]]+Table1[[#This Row],[Column8]]+Table1[[#This Row],[Column9]] -> 14 | C54: Target | D54: ⮽ | E54: ✓ | F54: ⮽ | G54: ⮽ | H54: ⮽ | I54: ⮽ | J54: =IF(Table1[[#This Row],[CIV]]="⮽",0,1)*1.5 -> 0 | K54: =IF(Table1[[#This Row],[ARC]]="⮽",0,1)*3 -> 3 | L54: =IF(Table1[[#This Row],[STR]]="⮽",0,1)*2 -> 0 | M54: =IF(Table1[[#This Row],[MP]]="⮽",0,1) -> 0 | N54: =IF(Table1[[#This Row],[ELE]]="⮽",0,1) -> 0 | O54: =IF(Table1[[#This Row],[FP]]="⮽",0,1) -> 0 | P54: 3 | Q54: S | R54: =IF(Table1[[#This Row],[Size (S, M, L)]]="S",2,IF(Table1[[#This Row],[Size (S, M, L)]]="L",1,4)) -> 2 | S54: CST | T54: =IF(Table1[[#This Row],[TZone]]="EST",4,IF(Table1[[#This Row],[TZone]]="CST",3,IF(Table1[[#This Row],[TZone]]="MST",2,1))) -> 3 | U54: No | V54: =IF(Table1[[#This Row],[Low-cost office?]]="Yes",-4,0) -> 0
A55: NWS Architects Inc. | B55: =Table1[[#This Row],[Column6]]+Table1[[#This Row],[Column5]]+Table1[[#This Row],[Column4]]+Table1[[#This Row],[Column3]]+Table1[[#This Row],[Column2]]+Table1[[#This Row],[Column1]]+2*(Table1[[#This Row],[Mkt Fit (1-3)]])+Table1[[#This Row],[Column7]]+Table1[[#This Row],[Column8]]+Table1[[#This Row],[Column9]] -> 14 | C55: Target | D55: ⮽ | E55: ✓ | F55: ⮽ | G55: ⮽ | H55: ⮽ | I55: ⮽ | J55: =IF(Table1[[#This Row],[CIV]]="⮽",0,1)*1.5 -> 0 | K55: =IF(Table1[[#This Row],[ARC]]="⮽",0,1)*3 -> 3 | L55: =IF(Table1[[#This Row],[STR]]="⮽",0,1)*2 -> 0 | M55: =IF(Table1[[#This Row],[MP]]="⮽",0,1) -> 0 | N55: =IF(Table1[[#This Row],[ELE]]="⮽",0,1) -> 0 | O55: =IF(Table1[[#This Row],[FP]]="⮽",0,1) -> 0 | P55: 3 | Q55: S | R55: =IF(Table1[[#This Row],[Size (S, M, L)]]="S",2,IF(Table1[[#This Row],[Size (S, M, L)]]="L",1,4)) -> 2 | S55: CST | T55: =IF(Table1[[#This Row],[TZone]]="EST",4,IF(Table1[[#This Row],[TZone]]="CST",3,IF(Table1[[#This Row],[TZone]]="MST",2,1))) -> 3 | U55: No | V55: =IF(Table1[[#This Row],[Low-cost office?]]="Yes",-4,0) -> 0
A56: Rogue Architects, LLC | B56: =Table1[[#This Row],[Column6]]+Table1[[#This Row],[Column5]]+Table1[[#This Row],[Column4]]+Table1[[#This Row],[Column3]]+Table1[[#This Row],[Column2]]+Table1[[#This Row],[Column1]]+2*(Table1[[#This Row],[Mkt Fit (1-3)]])+Table1[[#This Row],[Column7]]+Table1[[#This Row],[Column8]]+Table1[[#This Row],[Column9]] -> 14 | C56: Connection | D56: ⮽ | E56: ✓ | F56: ⮽ | G56: ⮽ | H56: ⮽ | I56: ⮽ | J56: =IF(Table1[[#This Row],[CIV]]="⮽",0,1)*1.5 -> 0 | K56: =IF(Table1[[#This Row],[ARC]]="⮽",0,1)*3 -> 3 | L56: =IF(Table1[[#This Row],[STR]]="⮽",0,1)*2 -> 0 | M56: =IF(Table1[[#This Row],[MP]]="⮽",0,1) -> 0 | N56: =IF(Table1[[#This Row],[ELE]]="⮽",0,1) -> 0 | O56: =IF(Table1[[#This Row],[FP]]="⮽",0,1) -> 0 | P56: 3 | Q56: S | R56: =IF(Table1[[#This Row],[Size (S, M, L)]]="S",2,IF(Table1[[#This Row],[Size (S, M, L)]]="L",1,4)) -> 2 | S56: CST | T56: =IF(Table1[[#This Row],[TZone]]="EST",4,IF(Table1[[#This Row],[TZone]]="CST",3,IF(Table1[[#This Row],[TZone]]="MST",2,1))) -> 3 | U56: No | V56: =IF(Table1[[#This Row],[Low-cost office?]]="Yes",-4,0) -> 0
A57: SGA Design Group | B57: =Table1[[#This Row],[Column6]]+Table1[[#This Row],[Column5]]+Table1[[#This Row],[Column4]]+Table1[[#This Row],[Column3]]+Table1[[#This Row],[Column2]]+Table1[[#This Row],[Column1]]+2*(Table1[[#This Row],[Mkt Fit (1-3)]])+Table1[[#This Row],[Column7]]+Table1[[#This Row],[Column8]]+Table1[[#This Row],[Column9]] -> 14 | C57: Client | D57: ⮽ | E57: ✓ | F57: ⮽ | G57: ⮽ | H57: ⮽ | I57: ⮽ | J57: =IF(Table1[[#This Row],[CIV]]="⮽",0,1)*1.5 -> 0 | K57: =IF(Table1[[#This Row],[ARC]]="⮽",0,1)*3 -> 3 | L57: =IF(Table1[[#This Row],[STR]]="⮽",0,1)*2 -> 0 | M57: =IF(Table1[[#This Row],[MP]]="⮽",0,1) -> 0 | N57: =IF(Table1[[#This Row],[ELE]]="⮽",0,1) -> 0 | O57: =IF(Table1[[#This Row],[FP]]="⮽",0,1) -> 0 | P57: 3 | Q57: S | R57: =IF(Table1[[#This Row],[Size (S, M, L)]]="S",2,IF(Table1[[#This Row],[Size (S, M, L)]]="L",1,4)) -> 2 | S57: CST | T57: =IF(Table1[[#This Row],[TZone]]="EST",4,IF(Table1[[#This Row],[TZone]]="CST",3,IF(Table1[[#This Row],[TZone]]="MST",2,1))) -> 3 | U57: No | V57: =IF(Table1[[#This Row],[Low-cost office?]]="Yes",-4,0) -> 0
A58: The McIntosh Group | B58: =Table1[[#This Row],[Column6]]+Table1[[#This Row],[Column5]]+Table1[[#This Row],[Column4]]+Table1[[#This Row],[Column3]]+Table1[[#This Row],[Column2]]+Table1[[#This Row],[Column1]]+2*(Table1[[#This Row],[Mkt Fit (1-3)]])+Table1[[#This Row],[Column7]]+Table1[[#This Row],[Column8]]+Table1[[#This Row],[Column9]] -> 14 | C58: Connection | D58: ⮽ | E58: ✓ | F58: ⮽ | G58: ⮽ | H58: ⮽ | I58: ⮽ | J58: =IF(Table1[[#This Row],[CIV]]="⮽",0,1)*1.5 -> 0 | K58: =IF(Table1[[#This Row],[ARC]]="⮽",0,1)*3 -> 3 | L58: =IF(Table1[[#This Row],[STR]]="⮽",0,1)*2 -> 0 | M58: =IF(Table1[[#This Row],[MP]]="⮽",0,1) -> 0 | N58: =IF(Table1[[#This Row],[ELE]]="⮽",0,1) -> 0 | O58: =IF(Table1[[#This Row],[FP]]="⮽",0,1) -> 0 | P58: 3 | Q58: S | R58: =IF(Table1[[#This Row],[Size (S, M, L)]]="S",2,IF(Table1[[#This Row],[Size (S, M, L)]]="L",1,4)) -> 2 | S58: CST | T58: =IF(Table1[[#This Row],[TZone]]="EST",4,IF(Table1[[#This Row],[TZone]]="CST",3,IF(Table1[[#This Row],[TZone]]="MST",2,1))) -> 3 | U58: No | V58: =IF(Table1[[#This Row],[Low-cost office?]]="Yes",-4,0) -> 0
... A170: Civil & Environmental Consultants | B170: =Table1[[#This Row],[Column6]]+Table1[[#This Row],[Column5]]+Table1[[#This Row],[Column4]]+Table1[[#This Row],[Column3]]+Table1[[#This Row],[Column2]]+Table1[[#This Row],[Column1]]+2*(Table1[[#This Row],[Mkt Fit (1-3)]])+Table1[[#This Row],[Column7]]+Table1[[#This Row],[Column8]]+Table1[[#This Row],[Column9]] -> 3.5 | C170: Target | D170: ✓ | E170: ⮽ | F170: ⮽ | G170: ⮽ | H170: ⮽ | I170: ⮽ | J170: =IF(Table1[[#This Row],[CIV]]="⮽",0,1)*1.5 -> 1.5 | K170: =IF(Table1[[#This Row],[ARC]]="⮽",0,1)*3 -> 0 | L170: =IF(Table1[[#This Row],[STR]]="⮽",0,1)*2 -> 0 | M170: =IF(Table1[[#This Row],[MP]]="⮽",0,1) -> 0 | N170: =IF(Table1[[#This Row],[ELE]]="⮽",0,1) -> 0 | O170: =IF(Table1[[#This Row],[FP]]="⮽",0,1) -> 0 | P170: 1 | Q170: L | R170: =IF(Table1[[#This Row],[Size (S, M, L)]]="S",2,IF(Table1[[#This Row],[Size (S, M, L)]]="L",1,4)) -> 1 | S170: CST | T170: =IF(Table1[[#This Row],[TZone]]="EST",4,IF(Table1[[#This Row],[TZone]]="CST",3,IF(Table1[[#This Row],[TZone]]="MST",2,1))) -> 3 | U170: Yes | V170: =IF(Table1[[#This Row],[Low-cost office?]]="Yes",-4,0) -> -4

Sheet Centerbuild 2025
A1: Company | B1: Score | C1: Status | D1: CIV | E1: ARC | F1: STR | G1: MP | H1: ELE | I1: FP | J1: Column6 | K1: Column5 | L1: Column4 | M1: Column3 | N1: Column2 | O1: Column1 | P1: Mkt Fit (1-3) | Q1: Size (S, M, L) | R1: Column7 | S1: TZone | T1: Column8 | U1: Low-cost office? | V1: Column9 | W1: Using Competitor? | X1: Attended in 2024
A2: HFA | B2: =Table1[[#This Row],[Column6]]+Table1[[#This Row],[Column5]]+Table1[[#This Row],[Column4]]+Table1[[#This Row],[Column3]]+Table1[[#This Row],[Column2]]+Table1[[#This Row],[Column1]]+2*(Table1[[#This Row],[Mkt Fit (1-3)]])+Table1[[#This Row],[Column7]]+Table1[[#This Row],[Column8]]+Table1[[#This Row],[Column9]] -> 23.5 | C2: Contact | D2: ✓ | E2: ✓ | F2: ✓ | G2: ✓ | H2: ✓ | I2: ✓ | J2: =IF(Table1[[#This Row],[CIV]]="⮽",0,1)*1.5 -> 1.5 | K2: =IF(Table1[[#This Row],[ARC]]="⮽",0,1)*3 -> 3 | L2: =IF(Table1[[#This Row],[STR]]="⮽",0,1)*2 -> 2 | M2: =IF(Table1[[#This Row],[MP]]="⮽",0,1) -> 1 | N2: =IF(Table1[[#This Row],[ELE]]="⮽",0,1) -> 1 | O2: =IF(Table1[[#This Row],[FP]]="⮽",0,1) -> 1 | P2: 3 | Q2: M | R2: =IF(Table1[[#This Row],[Size (S, M, L)]]="S",2,IF(Table1[[#This Row],[Size (S, M, L)]]="L",1,4)) -> 4 | S2: EST | T2: =IF(Table1[[#This Row],[TZone]]="EST",4,IF(Table1[[#This Row],[TZone]]="CST",3,IF(Table1[[#This Row],[TZone]]="MST",2,1))) -> 4 | U2: No | V2: =IF(Table1[[#This Row],[Low-cost office?]]="Yes",-4,0) -> 0 | X2: Yes
A3: Benchmark Group | B3: =Table1[[#This Row],[Column6]]+Table1[[#This Row],[Column5]]+Table1[[#This Row],[Column4]]+Table1[[#This Row],[Column3]]+Table1[[#This Row],[Column2]]+Table1[[#This Row],[Column1]]+2*(Table1[[#This Row],[Mkt Fit (1-3)]])+Table1[[#This Row],[Column7]]+Table1[[#This Row],[Column8]]+Table1[[#This Row],[Column9]] -> 23.5 | C3: Contact | D3: ✓ | E3: ✓ | F3: ✓ | G3: ✓ | H3: ✓ | I3: ✓ | J3: =IF(Table1[[#This Row],[CIV]]="⮽",0,1)*1.5 -> 1.5 | K3: =IF(Table1[[#This Row],[ARC]]="⮽",0,1)*3 -> 3 | L3: =IF(Table1[[#This Row],[STR]]="⮽",0,1)*2 -> 2 | M3: =IF(Table1[[#This Row],[MP]]="⮽",0,1) -> 1 | N3: =IF(Table1[[#This Row],[ELE]]="⮽",0,1) -> 1 | O3: =IF(Table1[[#This Row],[FP]]="⮽",0,1) -> 1 | P3: 3 | Q3: M | R3: =IF(Table1[[#This Row],[Size (S, M, L)]]="S",2,IF(Table1[[#This Row],[Size (S, M, L)]]="L",1,4)) -> 4 | S3: CST | T3: =IF(Table1[[#This Row],[TZone]]="EST",4,IF(Table1[[#This Row],[TZone]]="CST",3,IF(Table1[[#This Row],[TZone]]="MST",2,1))) -> 4 | U3: No | V3: =IF(Table1[[#This Row],[Low-cost office?]]="Yes",-4,0) -> 0 | X3: Yes
A4: Core States Group | B4: =Table1[[#This Row],[Column6]]+Table1[[#This Row],[Column5]]+Table1[[#This Row],[Column4]]+Table1[[#This Row],[Column3]]+Table1[[#This Row],[Column2]]+Table1[[#This Row],[Column1]]+2*(Table1[[#This Row],[Mkt Fit (1-3)]])+Table1[[#This Row],[Column7]]+Table1[[#This Row],[Column8]]+Table1[[#This Row],[Column9]] -> 22.5 | C4: Client | D4: ✓ | E4: ✓ | F4: ✓ | G4: ✓ | H4: ✓ | I4: ✓ | J4: =IF(Table1[[#This Row],[CIV]]="⮽",0,1)*1.5 -> 1.5 | K4: =IF(Table1[[#This Row],[ARC]]="⮽",0,1)*3 -> 3 | L4: =IF(Table1[[#This Row],[STR]]="⮽",0,1)*2 -> 2 | M4: =IF(Table1[[#This Row],[MP]]="⮽",0,1) -> 1 | N4: =IF(Table1[[#This Row],[ELE]]="⮽",0,1) -> 1 | O4: =IF(Table1[[#This Row],[FP]]="⮽",0,1) -> 1 | P4: 3 | Q4: M | R4: =IF(Table1[[#This Row],[Size (S, M, L)]]="S",2,IF(Table1[[#This Row],[Size (S, M, L)]]="L",1,4)) -> 4 | S4: CST | T4: =IF(Table1[[#This Row],[TZone]]="EST",4,IF(Table1[[#This Row],[TZone]]="CST",3,IF(Table1[[#This Row],[TZone]]="MST",2,1))) -> 3 | U4: No | V4: =IF(Table1[[#This Row],[Low-cost office?]]="Yes",-4,0) -> 0 | X4: Yes
A5: GreenbergFarrow | B5: =Table1[[#This Row],[Column6]]+Table1[[#This Row],[Column5]]+Table1[[#This Row],[Column4]]+Table1[[#This Row],[Column3]]+Table1[[#This Row],[Column2]]+Table1[[#This Row],[Column1]]+2*(Table1[[#This Row],[Mkt Fit (1-3)]])+Table1[[#This Row],[Column7]]+Table1[[#This Row],[Column8]]+Table1[[#This Row],[Column9]] -> 22.5 | C5: Target | D5: ✓ | E5: ✓ | F5: ✓ | G5: ✓ | H5: ✓ | I5: ⮽ | J5: =IF(Table1[[#This Row],[CIV]]="⮽",0,1)*1.5 -> 1.5 | K5: =IF(Table1[[#This Row],[ARC]]="⮽",0,1)*3 -> 3 | L5: =IF(Table1[[#This Row],[STR]]="⮽",0,1)*2 -> 2 | M5: =IF(Table1[[#This Row],[MP]]="⮽",0,1) -> 1 | N5: =IF(Table1[[#This Row],[ELE]]="⮽",0,1) -> 1 | O5: =IF(Table1[[#This Row],[FP]]="⮽",0,1) -> 1 | P5: 3 | Q5: M | R5: =IF(Table1[[#This Row],[Size (S, M, L)]]="S",2,IF(Table1[[#This Row],[Size (S, M, L)]]="L",1,4)) -> 4 | S5: EST | T5: =IF(Table1[[#This Row],[TZone]]="EST",4,IF(Table1[[#This Row],[TZone]]="CST",3,IF(Table1[[#This Row],[TZone]]="MST",2,1))) -> 3 | U5: No | V5: =IF(Table1[[#This Row],[Low-cost office?]]="Yes",-4,0) -> 0 | X5: Yes
A6: CASCO | B6: =Table1[[#This Row],[Column6]]+Table1[[#This Row],[Column5]]+Table1[[#This Row],[Column4]]+Table1[[#This Row],[Column3]]+Table1[[#This Row],[Column2]]+Table1[[#This Row],[Column1]]+2*(Table1[[#This Row],[Mkt Fit (1-3)]])+Table1[[#This Row],[Column7]]+Table1[[#This Row],[Column8]]+Table1[[#This Row],[Column9]] -> 22.5 | C6: Target | D6: ✓ | E6: ✓ | F6: ✓ | G6: ✓ | H6: ✓ | I6: ✓ | J6: =IF(Table1[[#This Row],[CIV]]="⮽",0,1)*1.5 -> 1.5 | K6: =IF(Table1[[#This Row],[ARC]]="⮽",0,1)*3 -> 3 | L6: =IF(Table1[[#This Row],[STR]]="⮽",0,1)*2 -> 2 | M6: =IF(Table1[[#This Row],[MP]]="⮽",0,1) -> 1 | N6: =IF(Table1[[#This Row],[ELE]]="⮽",0,1) -> 1 | O6: =IF(Table1[[#This Row],[FP]]="⮽",0,1) -> 0 | P6: 3 | Q6: M | R6: =IF(Table1[[#This Row],[Size (S, M, L)]]="S",2,IF(Table1[[#This Row],[Size (S, M, L)]]="L",1,4)) -> 4 | S6: CST | T6: =IF(Table1[[#This Row],[TZone]]="EST",4,IF(Table1[[#This Row],[TZone]]="CST",3,IF(Table1[[#This Row],[TZone]]="MST",2,1))) -> 4 | U6: No | V6: =IF(Table1[[#This Row],[Low-cost office?]]="Yes",-4,0) -> 0 | X6: No
A7: The Dimension Group | B7: =Table1[[#This Row],[Column6]]+Table1[[#This Row],[Column5]]+Table1[[#This Row],[Column4]]+Table1[[#This Row],[Column3]]+Table1[[#This Row],[Column2]]+Table1[[#This Row],[Column1]]+2*(Table1[[#This Row],[Mkt Fit (1-3)]])+Table1[[#This Row],[Column7]]+Table1[[#This Row],[Column8]]+Table1[[#This Row],[Column9]] -> 21.5 | C7: Target | D7: ✓ | E7: ✓ | F7: ✓ | G7: ✓ | H7: ✓ | I7: ✓ | J7: =IF(Table1[[#This Row],[CIV]]="⮽",0,1)*1.5 -> 1.5 | K7: =IF(Table1[[#This Row],[ARC]]="⮽",0,1)*3 -> 3 | L7: =IF(Table1[[#This Row],[STR]]="⮽",0,1)*2 -> 2 | M7: =IF(Table1[[#This Row],[MP]]="⮽",0,1) -> 1 | N7: =IF(Table1[[#This Row],[ELE]]="⮽",0,1) -> 1 | O7: =IF(Table1[[#This Row],[FP]]="⮽",0,1) -> 1 | P7: 3 | Q7: M | R7: =IF(Table1[[#This Row],[Size (S, M, L)]]="S",2,IF(Table1[[#This Row],[Size (S, M, L)]]="L",1,4)) -> 4 | S7: CST | T7: =IF(Table1[[#This Row],[TZone]]="EST",4,IF(Table1[[#This Row],[TZone]]="CST",3,IF(Table1[[#This Row],[TZone]]="MST",2,1))) -> 4 | U7: No | V7: =IF(Table1[[#This Row],[Low-cost office?]]="Yes",-4,0) -> 0 | X7: No
A8: Sargenti Architects | B8: =Table1[[#This Row],[Column6]]+Table1[[#This Row],[Column5]]+Table1[[#This Row],[Column4]]+Table1[[#This Row],[Column3]]+Table1[[#This Row],[Column2]]+Table1[[#This Row],[Column1]]+2*(Table1[[#This Row],[Mkt Fit (1-3)]])+Table1[[#This Row],[Column7]]+Table1[[#This Row],[Column8]]+Table1[[#This Row],[Column9]] -> 21.5 | C8: Target | D8: ⮽ | E8: ✓ | F8: ✓ | G8: ✓ | H8: ✓ | I8: ✓ | J8: =IF(Table1[[#This Row],[CIV]]="⮽",0,1)*1.5 -> 1.5 | K8: =IF(Table1[[#This Row],[ARC]]="⮽",0,1)*3 -> 3 | L8: =IF(Table1[[#This Row],[STR]]="⮽",0,1)*2 -> 2 | M8: =IF(Table1[[#This Row],[MP]]="⮽",0,1) -> 1 | N8: =IF(Table1[[#This Row],[ELE]]="⮽",0,1) -> 1 | O8: =IF(Table1[[#This Row],[FP]]="⮽",0,1) -> 0 | P8: 3 | Q8: M | R8: =IF(Table1[[#This Row],[Size (S, M, L)]]="S",2,IF(Table1[[#This Row],[Size (S, M, L)]]="L",1,4)) -> 4 | S8: EST | T8: =IF(Table1[[#This Row],[TZone]]="EST",4,IF(Table1[[#This Row],[TZone]]="CST",3,IF(Table1[[#This Row],[TZone]]="MST",2,1))) -> 3 | U8: No | V8: =IF(Table1[[#This Row],[Low-cost office?]]="Yes",-4,0) -> 0 | X8: No
A9: BL Companies | B9: =Table1[[#This Row],[Column6]]+Table1[[#This Row],[Column5]]+Table1[[#This Row],[Column4]]+Table1[[#This Row],[Column3]]+Table1[[#This Row],[Column2]]+Table1[[#This Row],[Column1]]+2*(Table1[[#This Row],[Mkt Fit (1-3)]])+Table1[[#This Row],[Column7]]+Table1[[#This Row],[Column8]]+Table1[[#This Row],[Column9]] -> 21.5 | C9: Contact | D9: ✓ | E9: ✓ | F9: ✓ | G9: ✓ | H9: ✓ | I9: ✓ | J9: =IF(Table1[[#This Row],[CIV]]="⮽",0,1)*1.5 -> 1.5 | K9: =IF(Table1[[#This Row],[ARC]]="⮽",0,1)*3 -> 3 | L9: =IF(Table1[[#This Row],[STR]]="⮽",0,1)*2 -> 2 | M9: =IF(Table1[[#This Row],[MP]]="⮽",0,1) -> 1 | N9: =IF(Table1[[#This Row],[ELE]]="⮽",0,1) -> 1 | O9: =IF(Table1[[#This Row],[FP]]="⮽",0,1) -> 1 | P9: 2 | Q9: M | R9: =IF(Table1[[#This Row],[Size (S, M, L)]]="S",2,IF(Table1[[#This Row],[Size (S, M, L)]]="L",1,4)) -> 4 | S9: EST | T9: =IF(Table1[[#This Row],[TZone]]="EST",4,IF(Table1[[#This Row],[TZone]]="CST",3,IF(Table1[[#This Row],[TZone]]="MST",2,1))) -> 4 | U9: No | V9: =IF(Table1[[#This Row],[Low-cost office?]]="Yes",-4,0) -> 0 | X9: Yes
A10: CESO, Inc. | B10: =Table1[[#This Row],[Column6]]+Table1[[#This Row],[Column5]]+Table1[[#This Row],[Column4]]+Table1[[#This Row],[Column3]]+Table1[[#This Row],[Column2]]+Table1[[#This Row],[Column1]]+2*(Table1[[#This Row],[Mkt Fit (1-3)]])+Table1[[#This Row],[Column7]]+Table1[[#This Row],[Column8]]+Table1[[#This Row],[Column9]] -> 21 | C10: Client | D10: ✓ | E10: ✓ | F10: ✓ | G10: ✓ | H10: ✓ | I10: ⮽ | J10: =IF(Table1[[#This Row],[CIV]]="⮽",0,1)*1.5 -> 0 | K10: =IF(Table1[[#This Row],[ARC]]="⮽",0,1)*3 -> 3 | L10: =IF(Table1[[#This Row],[STR]]="⮽",0,1)*2 -> 2 | M10: =IF(Table1[[#This Row],[MP]]="⮽",0,1) -> 1 | N10: =IF(Table1[[#This Row],[ELE]]="⮽",0,1) -> 1 | O10: =IF(Table1[[#This Row],[FP]]="⮽",0,1) -> 0 | P10: 3 | Q10: M | R10: =IF(Table1[[#This Row],[Size (S, M, L)]]="S",2,IF(Table1[[#This Row],[Size (S, M, L)]]="L",1,4)) -> 4 | S10: CST | T10: =IF(Table1[[#This Row],[TZone]]="EST",4,IF(Table1[[#This Row],[TZone]]="CST",3,IF(Table1[[#This Row],[TZone]]="MST",2,1))) -> 4 | U10: No | V10: =IF(Table1[[#This Row],[Low-cost office?]]="Yes",-4,0) -> 0 | X10: Yes
A11: H2M Architects + Engineers | B11: =Table1[[#This Row],[Column6]]+Table1[[#This Row],[Column5]]+Table1[[#This Row],[Column4]]+Table1[[#This Row],[Column3]]+Table1[[#This Row],[Column2]]+Table1[[#This Row],[Column1]]+2*(Table1[[#This Row],[Mkt Fit (1-3)]])+Table1[[#This Row],[Column7]]+Table1[[#This Row],[Column8]]+Table1[[#This Row],[Column9]] -> 20.5 | C11: Target | D11: ✓ | E11: ✓ | F11: ✓ | G11: ✓ | H11: ✓ | I11: ✓ | J11: =IF(Table1[[#This Row],[CIV]]="⮽",0,1)*1.5 -> 1.5 | K11: =IF(Table1[[#This Row],[ARC]]="⮽",0,1)*3 -> 3 | L11: =IF(Table1[[#This Row],[STR]]="⮽",0,1)*2 -> 2 | M11: =IF(Table1[[#This Row],[MP]]="⮽",0,1) -> 1 | N11: =IF(Table1[[#This Row],[ELE]]="⮽",0,1) -> 1 | O11: =IF(Table1[[#This Row],[FP]]="⮽",0,1) -> 1 | P11: 2 | Q11: M | R11: =IF(Table1[[#This Row],[Size (S, M, L)]]="S",2,IF(Table1[[#This Row],[Size (S, M, L)]]="L",1,4)) -> 2 | S11: EST | T11: =IF(Table1[[#This Row],[TZone]]="EST",4,IF(Table1[[#This Row],[TZone]]="CST",3,IF(Table1[[#This Row],[TZone]]="MST",2,1))) -> 3 | U11: No | V11: =IF(Table1[[#This Row],[Low-cost office?]]="Yes",-4,0) -> 0 | X11: Yes
A12: Little | B12: =Table1[[#This Row],[Column6]]+Table1[[#This Row],[Column5]]+Table1[[#This Row],[Column4]]+Table1[[#This Row],[Column3]]+Table1[[#This Row],[Column2]]+Table1[[#This Row],[Column1]]+2*(Table1[[#This Row],[Mkt Fit (1-3)]])+Table1[[#This Row],[Column7]]+Table1[[#This Row],[Column8]]+Table1[[#This Row],[Column9]] -> 20.5 | C12: Contact | D12: ⮽ | E12: ✓ | F12: ✓ | G12: ✓ | H12: ✓ | I12: ⮽ | J12: =IF(Table1[[#This Row],[CIV]]="⮽",0,1)*1.5 -> 1.5 | K12: =IF(Table1[[#This Row],[ARC]]="⮽",0,1)*3 -> 3 | L12: =IF(Table1[[#This Row],[STR]]="⮽",0,1)*2 -> 2 | M12: =IF(Table1[[#This Row],[MP]]="⮽",0,1) -> 1 | N12: =IF(Table1[[#This Row],[ELE]]="⮽",0,1) -> 1 | O12: =IF(Table1[[#This Row],[FP]]="⮽",0,1) -> 0 | P12: 3 | Q12: M | R12: =IF(Table1[[#This Row],[Size (S, M, L)]]="S",2,IF(Table1[[#This Row],[Size (S, M, L)]]="L",1,4)) -> 4 | S12: EST | T12: =IF(Table1[[#This Row],[TZone]]="EST",4,IF(Table1[[#This Row],[TZone]]="CST",3,IF(Table1[[#This Row],[TZone]]="MST",2,1))) -> 2 | U12: No | V12: =IF(Table1[[#This Row],[Low-cost office?]]="Yes",-4,0) -> 0 | X12: Yes
A13: Cyntergy AEC | B13: =Table1[[#This Row],[Column6]]+Table1[[#This Row],[Column5]]+Table1[[#This Row],[Column4]]+Table1[[#This Row],[Column3]]+Table1[[#This Row],[Column2]]+Table1[[#This Row],[Column1]]+2*(Table1[[#This Row],[Mkt Fit (1-3)]])+Table1[[#This Row],[Column7]]+Table1[[#This Row],[Column8]]+Table1[[#This Row],[Column9]] -> 20.5 | C13: Target | D13: ✓ | E13: ✓ | F13: ✓ | G13: ✓ | H13: ✓ | I13: ✓ | J13: =IF(Table1[[#This Row],[CIV]]="⮽",0,1)*1.5 -> 1.5 | K13: =IF(Table1[[#This Row],[ARC]]="⮽",0,1)*3 -> 3 | L13: =IF(Table1[[#This Row],[STR]]="⮽",0,1)*2 -> 2 | M13: =IF(Table1[[#This Row],[MP]]="⮽",0,1) -> 1 | N13: =IF(Table1[[#This Row],[ELE]]="⮽",0,1) -> 1 | O13: =IF(Table1[[#This Row],[FP]]="⮽",0,1) -> 0 | P13: 3 | Q13: S | R13: =IF(Table1[[#This Row],[Size (S, M, L)]]="S",2,IF(Table1[[#This Row],[Size (S, M, L)]]="L",1,4)) -> 4 | S13: CST | T13: =IF(Table1[[#This Row],[TZone]]="EST",4,IF(Table1[[#This Row],[TZone]]="CST",3,IF(Table1[[#This Row],[TZone]]="MST",2,1))) -> 4 | U13: No | V13: =IF(Table1[[#This Row],[Low-cost office?]]="Yes",-4,0) -> 0 | X13: Yes
... A166: Ensemble | B166: =Table1[[#This Row],[Column6]]+Table1[[#This Row],[Column5]]+Table1[[#This Row],[Column4]]+Table1[[#This Row],[Column3]]+Table1[[#This Row],[Column2]]+Table1[[#This Row],[Column1]]+2*(Table1[[#This Row],[Mkt Fit (1-3)]])+Table1[[#This Row],[Column7]]+Table1[[#This Row],[Column8]]+Table1[[#This Row],[Column9]] -> 6 | C166: Competitor!!!! | D166: ⮽ | E166: ⮽ | F166: ⮽ | G166: ⮽ | H166: ⮽ | I166: ⮽ | J166: =IF(Table1[[#This Row],[CIV]]="⮽",0,1)*1.5 -> 0 | K166: =IF(Table1[[#This Row],[ARC]]="⮽",0,1)*3 -> 0 | L166: =IF(Table1[[#This Row],[STR]]="⮽",0,1)*2 -> 0 | M166: =IF(Table1[[#This Row],[MP]]="⮽",0,1) -> 0 | N166: =IF(Table1[[#This Row],[ELE]]="⮽",0,1) -> 0 | O166: =IF(Table1[[#This Row],[FP]]="⮽",0,1) -> 0 | P166: 1 | Q166: S | R166: =IF(Table1[[#This Row],[Size (S, M, L)]]="S",2,IF(Table1[[#This Row],[Size (S, M, L)]]="L",1,4)) -> 2 | S166: CST | T166: =IF(Table1[[#This Row],[TZone]]="EST",4,IF(Table1[[#This Row],[TZone]]="CST",3,IF(Table1[[#This Row],[TZone]]="MST",2,1))) -> 2 | U166: Yes | V166: =IF(Table1[[#This Row],[Low-cost office?]]="Yes",-4,0) -> 0 | X166: Yes

Sheet Hospitality

Sheet 2025 Existing Client List
A1: 2025 Clients | B1: Primary Responsiblity Manager | C1: Target Contacts | E1: Do we have a regular sync meeting? | F1: Programs | G1: Target Contact Status (05 June 2025) | H1: Notes
C2: Name | D2: Title | E2: Yes or No | H2: Notes | J2: Target Contact Status Summary
A3: Atlantic AE | B3: Berkay / Ceren | C3: Paul Gierlach | D3: Client Director | F3: Encore Logistics Building | G3: Active Projects/Program | H3: Follow up for CD set... and second building. | J3: =COUNTIF(G3:G93,"=Active Projects/Program") -> 41 | K3: Active Projects/Program
C4: Krysten Gromly | D4: Project architect | G4: Active Projects/Program | J4: =COUNTIF(G3:G93,"=Waiting for Next Project") -> 24 | K4: Waiting for Next Project
A5: FM Group | B5: John / Mertcan | C5: Tabitha Davis | D5: Operations Manager | G5: Active Projects/Program | J5: =COUNTIF(G3:G93,"=Pursuing Pilot") -> 12 | K5: Pursuing Pilot
C6: Austin Burmer | D6: Senior Project Manager | G6: Waiting for Next Project | J6: =COUNTIF(G3:G93,"=Pursuing Introduction") -> 4 | K6: Pursuing Introduction
C7: Jamie Olivia | D7: Project Coordinator | G7: Waiting for Next Project | J7: =COUNTIF(G3:G94,"=-") -> 7 | K7: Unknown
C8: Miya Bebee | G8: Waiting for Next Project
A9: MG2 | B9: Bahadir / Cagla | C9: Nick Caputo | D9: Principal | F9: Rocky Mountain Chocolate Factory | G9: Waiting for Next Project | J9: 22 | K9: Number of Clients
C10: Dan Boyle | D10: Project Manager | F10: Home Depot | G10: Pursuing Pilot | H10: reports to Kevin?
C11: Kevin Richardson | D11: Senior Project Manager | F11: Home Depot | G11: Pursuing Pilot | H11: Reports Doug Brookbank
C12: Meghana Joshi | D12: Managing Principal | G12: Pursuing Introduction | H12: who is this? when did we last talk to them
C13: Sarah Simchuck | D13: Principal / Senior Associate | G13: Pursuing Introduction | H13: who is this? when did we last talk to them
C14: Victor Malerba | D14: Principal | G14: Pursuing Introduction
C15: Doug Brookbank | D15: Principal | F15: Academy Sports | G15: Pursuing Pilot | H15: Proposal sent in May
A16: Adrenaline | B16: John | C16: Frank Beardsworth | D16: Chief Delivery Officer | F16: PNC | G16: Active Projects/Program
B17: Gozde | C17: Samantha Carreiro | D17: Manager | F17: PNC | G17: Active Projects/Program
B18: Jordan / Hande | C18: Bill Anderson | F18: PNC | G18: Active Projects/Program
B19: Jordan | C19: Eric Anderson | F19: PNC | G19: Active Projects/Program
A20: CPH | B20: Berkay | C20: Joshua Sleeter | D20: Senior Project Manager | F20: Walmart | G20: Active Projects/Program | I20: Paid when paid...
C21: Pam Friday | G21: Waiting for Next Project | H21: worth a call... what is she doing now?
B22: Jason | C22: Todd Hendrix | D22: COO | G22: Waiting for Next Project | H22: mentioned engineering, civil (Jose Ortiz - head of structural)
C23: Audrey Rivera | D23: Project Coordinator | G23: -
C24: Ilker Uzun | G24: -
A25: Novilla RNG | B25: Jason / Derya | C25: Kevin Clark | D25: Director of Engineering | G25: Active Projects/Program
C26: Cory Eberly | D26: Sr. Project Designer | G26: Active Projects/Program
A27: BL Companies | B27: Jason | C27: Barbara Joslin | D27: Director Project Development, Principal | G27: Waiting for Next Project
C28: Bill Fries | D28: Director Project Development, Principal | G28: Pursuing Pilot
C29: Daniel Wenzel | D29: Senior Project Manager | G29: Pursuing Pilot
C30: Maite Ray-Rivera | D30: Project Manager | G30: Waiting for Next Project
C31: Christine Peterson | D31: Project Manager | G31: Waiting for Next Project
A32: Core States - Leadership | B32: Jason / John | C32: Bryan Grabon | D32: Director of Construction Programs | G32: -
C33: Austin Stone | D33: Director of Design Efficiency + Analytics | G33: -
C34: Jason Arasim | D34: Regional Managing Director - Pensylvania | F34: OneStream | G34: Active Projects/Program
A35: Core States - Restuarants | B35: Jason | C35: Ruben Alonso | D35: Operations Director | G35: Active Projects/Program
B36: Yigit | C36: Kelley Teska | D36: Project Manager | F36: BWW, Arby's, Zaxby's | G36: Active Projects/Program
B37: Alana Lee | C37: Keri Budzyn | D37: Organizational Effectiveness Manager | G37: Active Projects/Program
B38: Jordan? | C38: Mike Yao | D38: Program Manager | F38: CFA | G38: Waiting for Next Project
A39: Core States - Energy | B39: Berkay | C39: Clay Gallagher | D39: Project Manager | F39: EVGo | G39: Active Projects/Program
C40: Omar Tun | D40: Senior Project Designer | F40: EVGo | G40: Active Projects/Program
C41: Mark Bernet | D41: Project Manager | F41: EVGo | G41: Active Projects/Program
A42: Core States - Retail | B42: Yigit (???) | C42: Daniel Blohowiak | D42: Senior Project Architect | F42: Family Express | G42: Waiting for Next Project
B43: Berkay | C43: Brody Peterson | D43: Senior Project Manager | F43: Dollar Tree, Pep Boys, Lowes | G43: Active Projects/Program
B44: Jason | C44: Brad Hamilton | D44: Director of Architecture
B45: Berkay | C45: Angie Feulner | D45: Senior Project Architect | F45: Total Wine & More | G45: Active Projects/Program
C46: Keyanna Yerry | F46: Circle K, Travel Center, Dash-in | G46: Active Projects/Program
A47: Core States - Finance | B47: Bahadir / Cagla | C47: Peter Hahn | D47: Project Manager | G47: Active Projects/Program
C48: Virginia Alvarez | D48: Project Manager | F48: Wells Fargo | G48: Waiting for Next Project
C49: James Lalli | D49: Director of Architecture, Financial | G49: Waiting for Next Project
A50: Core States - Engineering | B50: Jason | C50: John Ferguson | D50: Sr. Director of Engineering | G50: Waiting for Next Project
C51: David Leiffer | D51: Director of Mechanical Engineering | G51: Waiting for Next Project
C52: Brad Myers | D52: Senior Project Manager - Electrical | F52: Oil Changers | G52: Active Projects/Program
C53: Carel Stevenson | D53: Structural Engineer | F53: Family Express, Oil Changers, CFA | G53: Active Projects/Program
A54: DXU | B54: Berkay | C54: Kaylee Kaufman | D54: Sr Project Manager | F54: Panera | G54: Active Projects/Program
C55: Austin Register | F55: Glowbar, Pickler | G55: Waiting for Next Project
C56: Alex Karshis | F56: Glowbar, Pickler | G56: Waiting for Next Project
C57: Anthony Volpe | D57: Managing Principal | F57: Big Blue | G57: Waiting for Next Project | H57: May 23rd. did we have a project closure meeting?
C58: Sean Jackson | D58: Project Manager | F58: Solidcore | H58: (17 contacts in GoHighLevel, who else should we be regularly contacting?)
A59: CESO - Industrial | B59: John | C59: Jake Bush | D59: Vice President | F59: All | G59: Active Projects/Program
B60: John / Bahadir | C60: Chris Westbrook | D60: Senior Program Director | F60: R+L Carriers | G60: Pursuing Pilot | H60: Bahadir prepared proposals for R+L Carriers
B61: Jason / Bahadir | C61: Mike Bless | D61: Team Lead (Architecture) | F61: R+L Carriers | G61: Pursuing Pilot | H61: Bahadir prepared proposals for R+L Carriers
C62: Elizabeth Cole | D62: Senior Project Manager | G62: - | H62: Who has worked with Elizabeth Cole in the past?
B63: Jason | C63: Jordan Flischman | D63: Engineering Manager | F63: RSR Civil STF | G63: Active Projects/Program
B64: Jason | C64: Robert Malone | D64: Program Director | F64: AMZN SSD | G64: Active Projects/Program
B65: Yigit | C65: Cory Risola | D65: Project Manager | F65: AMZN SSD | G65: Active Projects/Program
C66: Ricky Williams | D66: Team Lead | F66: AMZN SSD | G66: Active Projects/Program
C67: Amy Sanker | D67: Project Architect | F67: AMZN SSD | G67: Active Projects/Program
A68: CESO - Commercial | B68: John / Jason | C68: Nick Hershberger | D68: Vice President | F68: All | G68: Active Projects/Program
C69: Laura Smith | D69: Retail Market Leader | F69: Albertsons ADA | G69: Active Projects/Program
B70: John / Jason | C70: Bob Morrison | D70: Retail Market Leader | F70: Sams Club | G70: Pursuing Pilot
B71: Jason | C71: Jason Longbrake | D71: Restaurant and Grocery Market Leader | F71: Cracker Barrel ADA, CAVA | G71: Active Projects/Program
B72: Jason | C72: J.D. Damrath | D72: Fueling/C-Store Market Leader | F72: C-store and Car wash | G72: Pursuing Pilot
B73: Jason | C73: Bryan Hall | D73: Civil Business Unit Manager | G73: Active Projects/Program
B74: John | C74: Brady Harding | D74: Director of Architecture | G74: -
C75: Ashley Lyons | D75: Architecture Manager | G75: -
B76: Berkay | C76: Lindsay Meranda | D76: Senior Designer | F76: CAVA | G76: Active Projects/Program
B77: Jason | C77: David Teyber | D77: Project Manager | F77: Albertsons ADA, Cracker Barrel ADA | G77: Active Projects/Program
B78: Berkay | C78: Katie Papin | D78: Senior Project Manager | F78: Sprouts | G78: Active Projects/Program
B79: Berkay | C79: Stephanie Lawson | D79: Senior Designer | F79: Sprouts | G79: Active Projects/Program
A80: Colliers | B80: Yigit / Jason | C80: Justin Mihalik | D80: Principal | F80: Wendy's, Light Bridge Academy | G80: Waiting for Next Project | H80: We have no projects from CED this year... why?
C81: Jodi James | D81: Business Development | G81: Pursuing Pilot
C82: Sarah Valluzzi | D82: Project Manager | G82: Waiting for Next Project
C83: Sean O'Rouke | D83: Architecture Discipline Leader | G83: Waiting for Next Project
C84: Casey Whiteman | D84: Principal/Manager Site Development | F84: Data Centers / Distribution Centers | G84: Pursuing Introduction
A85: SGA Design Group | B85: Bahadir / Cagla | C85: Hal Staples | D85: Principal | G85: Active Projects/Program
C86: Chris Young | G86: Pursuing Pilot | H86: Might be worth trying again... its been two months.
C87: Ben Belle | G87: Pursuing Pilot
C88: Wash Givings | D88: Program Manager | G88: Active Projects/Program
A90: TWM Inc. | B90: Berkay | C90: Scott Carter | D90: Project Manager | F90: SWARCO Renovation & Expansion Project | G90: Waiting for Next Project
A91: Hitachi Energy | B91: Berkay | C91: Emilia Gosiewska | D91: Application Manager | G91: Active Projects/Program
A92: APS | B92: John | C92: ??? | G92: Waiting for Next Project
A93: Dedem Mekatronik | B93: John | C93: ??? | G93: Waiting for Next Project
B95: Sum = | C95: 83
A101: 2025 Clients | B101: Jan | C101: Feb | D101: Mar | F101: Apr | G101: May | H101: Jun | I101: Jul | J101: Aug | K101: Sep | L101: Oct | M101: Nov | N101: Dec | O101: Total | P101: Projection
A102: FM Group | B102: 16180 | C102: 11745 | D102: 3660 | F102: 14400 | G102: 0 | H102: 0 | I102: 0 | J102: 0 | K102: 0 | L102: 0 | M102: 0 | N102: 0 | O102: 45985 | P102: ='[1]Live Projection 2025'!H22 -> 191250
A103: MG2 | B103: 0 | C103: 0 | D103: 2280 | F103: 2700 | G103: 0 | H103: 0 | I103: 0 | J103: 0 | K103: 0 | L103: 0 | M103: 0 | N103: 0 | O103: 4980 | P103: ='[1]Live Projection 2025'!H29 -> 63750
A104: Adrenaline | B104: 0 | C104: 57489 | D104: 218260 | F104: 276086 | G104: 0 | H104: 0 | I104: 0 | J104: 0 | K104: 0 | L104: 0 | M104: 0 | N104: 0 | O104: 551835 | P104: ='[1]Live Projection 2025'!H28 -> 722500
A105: CPH | B105: 9100 | C105: 9100 | D105: 0 | F105: 9100 | G105: 0 | H105: 0 | I105: 0 | J105: 0 | K105: 0 | L105: 0 | M105: 0 | N105: 0 | O105: 27300 | P105: ='[1]Live Projection 2025'!H26 -> 106250
A106: Novilla RNG | B106: 5135 | C106: 2240 | D106: 3550 | F106: 0 | G106: 0 | H106: 0 | I106: 0 | J106: 0 | K106: 0 | L106: 0 | M106: 0 | N106: 0 | O106: 10925 | P106: ='[1]Live Projection 2025'!H25 -> 127500
A107: BL Companies | B107: 0 | C107: 12320 | D107: 1540 | F107: 840 | G107: 0 | H107: 0 | I107: 0 | J107: 0 | K107: 0 | L107: 0 | M107: 0 | N107: 0 | O107: 14700
...

Sheet Action Items Per Team Member
A1: Action Items
A2: Updated: | B2: 46000
B4: Tasks / Questions for....
A5: Item | B5: John | C5: Jason | D5: Jordan | E5: Hande
A6: 1
A7: 2 | B7: Follow up with Austin Stone at Core States about bucket of hours for detail improvement. | C7: Follow up with Bill Fries about EV charging and help at BL Companies
A8: 3 | B8: Connect with Bryan Grabon about missing POs and making the paperwork easier to work with CSG Engineering teams. | C8: Meet with Daniel Wetzel and Maite in America. Talk Dollar Tire and more.
A9: 4 | C9: Call Christine at BL Companies for project closure meeting... and ask whats next.
A10: 5 | C10: Connect again for John Ferguson and ask about mechanical team members we met in April.
A11: 6 | C11: Connect again with David Lieffer about mechanical scopes.
A12: 7 | C12: Connect with Brad Myers to review electrical projects coming down the line.
A13: 8 | C13: Connect with Casey Whiteman again about providing support to his teams for Civil related work.
A14: 9 | C14: How do we connect with Mike Yao to ask about CFA projects?
A15: 10 | C15: Call Daniel Blohowiak and reconnect on Family Express. See what else might be cooking.
B19: Tasks / Questions for....
A20: Item | B20: Yigit | C20: Cagla | D20: Berkay | E20: Gozde | F20: Mertcan
A21: 1
A22: 2
A23: 3
A24: 4
A25: 5
A26: 6
A27: 7
A28: 8
A29: 9
A30: 10

Sheet 2026 Existing Clients
A1: 2026 Target Contacts Name | B1: Company | C1: Title | D1: Primary Responsiblity Manager | E1: Do we have a regular sync meeting? | F1: Programs / Notes | G1: Jason | H1: Jordan | I1: John | J1: Yigit | K1: Cagla | L1: Berkay | M1: Gozde | N1: Mertcan | O1: Amy | P1: Jason/Derya | Q1: Jason/Basak | R1: Jason/Cagla | S1: January | T1: February | U1: March | V1: April | W1: May | X1: June | Y1: July | Z1: August | AA1: September | AB1: October | AC1: November | AD1: December
A2: Samantha Carreiro | B2: Adrenaline | C2: Manager | D2: Gozde | E2: Weekly | F2: Schematic Floorplans | G2: =IF(D2="Jason",1,0) -> 0 | H2: =IF($D2="Jordan",1,0) -> 0 | I2: =IF($D2="John",1,0) -> 0 | J2: =IF($D2="Yigit",1,0) -> 0 | K2: =IF($D2="Cagla",1,0) -> 0 | L2: =IF($D2="Berkay",1,0) -> 0 | M2: =IF($D2="Gozde",1,0) -> 1 | N2: =IF($D2="Mertcan",1,0) -> 0 | O2: =IF($D2="Amy",1,0) -> 0 | P2: =IF($D2="Jason / Derya",1,0) -> 0 | Q2: =IF($D2="Jason / Basak",1,0) -> 0 | R2: =IF($D2="Jason / Cagla",1,0) -> 0 | S2: TRUE | T2: TRUE | U2: TRUE
A3: Kim Beardsworth | B3: Adrenaline | C3: Program Manager | D3: Gozde | F3: Centier Bank Westfield | G3: =IF(D3="Jason",1,0) -> 0 | H3: =IF($D3="Jordan",1,0) -> 0 | I3: =IF($D3="John",1,0) -> 0 | J3: =IF($D3="Yigit",1,0) -> 0 | K3: =IF($D3="Cagla",1,0) -> 0 | L3: =IF($D3="Berkay",1,0) -> 0 | M3: =IF($D3="Gozde",1,0) -> 1 | N3: =IF($D3="Mertcan",1,0) -> 0 | O3: =IF($D3="Amy",1,0) -> 0 | P3: =IF($D3="Jason / Derya",1,0) -> 0 | Q3: =IF($D3="Jason / Basak",1,0) -> 0 | R3: =IF($D3="Jason / Cagla",1,0) -> 0 | S3: TRUE | T3: TRUE | U3: TRUE
A4: Frank Beardsworth | B4: Adrenaline | C4: Chief Delivery Officer | D4: John | G4: =IF(D4="Jason",1,0) -> 0 | H4: =IF($D4="Jordan",1,0) -> 0 | I4: =IF($D4="John",1,0) -> 1 | J4: =IF($D4="Yigit",1,0) -> 0 | K4: =IF($D4="Cagla",1,0) -> 0 | L4: =IF($D4="Berkay",1,0) -> 0 | M4: =IF($D4="Gozde",1,0) -> 0 | N4: =IF($D4="Mertcan",1,0) -> 0 | O4: =IF($D4="Amy",1,0) -> 0 | P4: =IF($D4="Jason / Derya",1,0) -> 0 | Q4: =IF($D4="Jason / Basak",1,0) -> 0 | R4: =IF($D4="Jason / Cagla",1,0) -> 0 | S4: FALSE | T4: TRUE | U4: TRUE
A5: Tabitha Davis | B5: APEX | C5: Operations Manager | D5: Mertcan | E5: Weekly | F5: QAQC, SCAN to BIM | G5: =IF(D5="Jason",1,0) -> 0 | H5: =IF($D5="Jordan",1,0) -> 0 | I5: =IF($D5="John",1,0) -> 0 | J5: =IF($D5="Yigit",1,0) -> 0 | K5: =IF($D5="Cagla",1,0) -> 0 | L5: =IF($D5="Berkay",1,0) -> 0 | M5: =IF($D5="Gozde",1,0) -> 0 | N5: =IF($D5="Mertcan",1,0) -> 1 | O5: =IF($D5="Amy",1,0) -> 0 | P5: =IF($D5="Jason / Derya",1,0) -> 0 | Q5: =IF($D5="Jason / Basak",1,0) -> 0 | R5: =IF($D5="Jason / Cagla",1,0) -> 0 | S5: TRUE | T5: TRUE | U5: TRUE
A6: Franco Gamero | B6: Atlantic AE | C6: Senior Project Manager | D6: Berkay | F6: AMZN SSD | G6: =IF(D6="Jason",1,0) -> 0 | H6: =IF($D6="Jordan",1,0) -> 0 | I6: =IF($D6="John",1,0) -> 0 | J6: =IF($D6="Yigit",1,0) -> 0 | K6: =IF($D6="Cagla",1,0) -> 0 | L6: =IF($D6="Berkay",1,0) -> 1 | M6: =IF($D6="Gozde",1,0) -> 0 | N6: =IF($D6="Mertcan",1,0) -> 0 | O6: =IF($D6="Amy",1,0) -> 0 | P6: =IF($D6="Jason / Derya",1,0) -> 0 | Q6: =IF($D6="Jason / Basak",1,0) -> 0 | R6: =IF($D6="Jason / Cagla",1,0) -> 0 | S6: FALSE | T6: TRUE | U6: TRUE
A7: Paul Gierlach | B7: Atlantic AE | C7: Client Director | D7: Jason | F7: AMZN SSD | G7: =IF(D7="Jason",1,0) -> 1 | H7: =IF($D7="Jordan",1,0) -> 0 | I7: =IF($D7="John",1,0) -> 0 | J7: =IF($D7="Yigit",1,0) -> 0 | K7: =IF($D7="Cagla",1,0) -> 0 | L7: =IF($D7="Berkay",1,0) -> 0 | M7: =IF($D7="Gozde",1,0) -> 0 | N7: =IF($D7="Mertcan",1,0) -> 0 | O7: =IF($D7="Amy",1,0) -> 0 | P7: =IF($D7="Jason / Derya",1,0) -> 0 | Q7: =IF($D7="Jason / Basak",1,0) -> 0 | R7: =IF($D7="Jason / Cagla",1,0) -> 0 | S7: TRUE | T7: TRUE | U7: TRUE
A8: Patrick Gaither | B8: Atlantic AE | C8: Project Manager | D8: Jason | F8: AMZN SSD | G8: =IF(D8="Jason",1,0) -> 1 | H8: =IF($D8="Jordan",1,0) -> 0 | I8: =IF($D8="John",1,0) -> 0 | J8: =IF($D8="Yigit",1,0) -> 0 | K8: =IF($D8="Cagla",1,0) -> 0 | L8: =IF($D8="Berkay",1,0) -> 0 | M8: =IF($D8="Gozde",1,0) -> 0 | N8: =IF($D8="Mertcan",1,0) -> 0 | O8: =IF($D8="Amy",1,0) -> 0 | P8: =IF($D8="Jason / Derya",1,0) -> 0 | Q8: =IF($D8="Jason / Basak",1,0) -> 0 | R8: =IF($D8="Jason / Cagla",1,0) -> 0 | S8: TRUE | T8: TRUE | U8: TRUE
A9: Bill Fries | B9: BL Companies | C9: Director Project Development, Principal | D9: Jason | F9: Civil | G9: =IF(D9="Jason",1,0) -> 1 | H9: =IF($D9="Jordan",1,0) -> 0 | I9: =IF($D9="John",1,0) -> 0 | J9: =IF($D9="Yigit",1,0) -> 0 | K9: =IF($D9="Cagla",1,0) -> 0 | L9: =IF($D9="Berkay",1,0) -> 0 | M9: =IF($D9="Gozde",1,0) -> 0 | N9: =IF($D9="Mertcan",1,0) -> 0 | O9: =IF($D9="Amy",1,0) -> 0 | P9: =IF($D9="Jason / Derya",1,0) -> 0 | Q9: =IF($D9="Jason / Basak",1,0) -> 0 | R9: =IF($D9="Jason / Cagla",1,0) -> 0 | S9: FALSE | T9: FALSE | U9: FALSE
A10: Maite Ray-Rivera | B10: BL Companies | C10: Project Manager | D10: Jason | E10: Monthly | F10: Discount Tire | G10: =IF(D10="Jason",1,0) -> 1 | H10: =IF($D10="Jordan",1,0) -> 0 | I10: =IF($D10="John",1,0) -> 0 | J10: =IF($D10="Yigit",1,0) -> 0 | K10: =IF($D10="Cagla",1,0) -> 0 | L10: =IF($D10="Berkay",1,0) -> 0 | M10: =IF($D10="Gozde",1,0) -> 0 | N10: =IF($D10="Mertcan",1,0) -> 0 | O10: =IF($D10="Amy",1,0) -> 0 | P10: =IF($D10="Jason / Derya",1,0) -> 0 | Q10: =IF($D10="Jason / Basak",1,0) -> 0 | R10: =IF($D10="Jason / Cagla",1,0) -> 0 | S10: TRUE | T10: TRUE | U10: TRUE
A11: Barbara Joslin | B11: BL Companies | C11: Director Project Development, Principal | D11: Jordan | E11: Bi-weekly | F11: AMZN | G11: =IF(D11="Jason",1,0) -> 0 | H11: =IF($D11="Jordan",1,0) -> 1 | I11: =IF($D11="John",1,0) -> 0 | J11: =IF($D11="Yigit",1,0) -> 0 | K11: =IF($D11="Cagla",1,0) -> 0 | L11: =IF($D11="Berkay",1,0) -> 0 | M11: =IF($D11="Gozde",1,0) -> 0 | N11: =IF($D11="Mertcan",1,0) -> 0 | O11: =IF($D11="Amy",1,0) -> 0 | P11: =IF($D11="Jason / Derya",1,0) -> 0 | Q11: =IF($D11="Jason / Basak",1,0) -> 0 | R11: =IF($D11="Jason / Cagla",1,0) -> 0 | S11: TRUE | T11: TRUE | U11: TRUE
A12: Daniel Wenzel | B12: BL Companies | C12: Senior Project Manager | D12: Jordan | G12: =IF(D12="Jason",1,0) -> 0 | H12: =IF($D12="Jordan",1,0) -> 1 | I12: =IF($D12="John",1,0) -> 0 | J12: =IF($D12="Yigit",1,0) -> 0 | K12: =IF($D12="Cagla",1,0) -> 0 | L12: =IF($D12="Berkay",1,0) -> 0 | M12: =IF($D12="Gozde",1,0) -> 0 | N12: =IF($D12="Mertcan",1,0) -> 0 | O12: =IF($D12="Amy",1,0) -> 0 | P12: =IF($D12="Jason / Derya",1,0) -> 0 | Q12: =IF($D12="Jason / Basak",1,0) -> 0 | R12: =IF($D12="Jason / Cagla",1,0) -> 0 | S12: TRUE | T12: FALSE | U12: FALSE
A13: Christine Peterson | B13: BL Companies | C13: Project Manager | D13: Jordan | G13: =IF(D13="Jason",1,0) -> 0 | H13: =IF($D13="Jordan",1,0) -> 1 | I13: =IF($D13="John",1,0) -> 0 | J13: =IF($D13="Yigit",1,0) -> 0 | K13: =IF($D13="Cagla",1,0) -> 0 | L13: =IF($D13="Berkay",1,0) -> 0 | M13: =IF($D13="Gozde",1,0) -> 0 | N13: =IF($D13="Mertcan",1,0) -> 0 | O13: =IF($D13="Amy",1,0) -> 0 | P13: =IF($D13="Jason / Derya",1,0) -> 0 | Q13: =IF($D13="Jason / Basak",1,0) -> 0 | R13: =IF($D13="Jason / Cagla",1,0) -> 0 | S13: TRUE | T13: FALSE | U13: FALSE
A14: J.D. Damrath | B14: CESO - Auto & C-Store | C14: Fueling/C-Store Market Leader | D14: Jason | F14: C-store and Car wash | G14: =IF(D14="Jason",1,0) -> 1 | H14: =IF($D14="Jordan",1,0) -> 0 | I14: =IF($D14="John",1,0) -> 0 | J14: =IF($D14="Yigit",1,0) -> 0 | K14: =IF($D14="Cagla",1,0) -> 0 | L14: =IF($D14="Berkay",1,0) -> 0 | M14: =IF($D14="Gozde",1,0) -> 0 | N14: =IF($D14="Mertcan",1,0) -> 0 | O14: =IF($D14="Amy",1,0) -> 0 | P14: =IF($D14="Jason / Derya",1,0) -> 0 | Q14: =IF($D14="Jason / Basak",1,0) -> 0 | R14: =IF($D14="Jason / Cagla",1,0) -> 0 | S14: FALSE | T14: TRUE | U14: FALSE
A15: Ben Reale | B15: CESO - Civil | C15: Project Manager | D15: Jason | E15: Weekly | F15: Albertsons ADA | G15: =IF(D15="Jason",1,0) -> 1 | H15: =IF($D15="Jordan",1,0) -> 0 | I15: =IF($D15="John",1,0) -> 0 | J15: =IF($D15="Yigit",1,0) -> 0 | K15: =IF($D15="Cagla",1,0) -> 0 | L15: =IF($D15="Berkay",1,0) -> 0 | M15: =IF($D15="Gozde",1,0) -> 0 | N15: =IF($D15="Mertcan",1,0) -> 0 | O15: =IF($D15="Amy",1,0) -> 0 | P15: =IF($D15="Jason / Derya",1,0) -> 0 | Q15: =IF($D15="Jason / Basak",1,0) -> 0 | R15: =IF($D15="Jason / Cagla",1,0) -> 0 | S15: TRUE | T15: TRUE | U15: FALSE
A16: Jeffery Lonchor | B16: CESO - Civil | C16: Project Manager | D16: Yigit | F16: Cracker Barrel ADA | G16: =IF(D16="Jason",1,0) -> 0 | H16: =IF($D16="Jordan",1,0) -> 0 | I16: =IF($D16="John",1,0) -> 0 | J16: =IF($D16="Yigit",1,0) -> 1 | K16: =IF($D16="Cagla",1,0) -> 0 | L16: =IF($D16="Berkay",1,0) -> 0 | M16: =IF($D16="Gozde",1,0) -> 0 | N16: =IF($D16="Mertcan",1,0) -> 0 | O16: =IF($D16="Amy",1,0) -> 0 | P16: =IF($D16="Jason / Derya",1,0) -> 0 | Q16: =IF($D16="Jason / Basak",1,0) -> 0 | R16: =IF($D16="Jason / Cagla",1,0) -> 0 | S16: FALSE | T16: TRUE | U16: FALSE
A17: Nick Hershberger | B17: CESO - Commercial | C17: Vice President | D17: John | E17: Quarterly | F17: All | G17: =IF(D17="Jason",1,0) -> 0 | H17: =IF($D17="Jordan",1,0) -> 0 | I17: =IF($D17="John",1,0) -> 1 | J17: =IF($D17="Yigit",1,0) -> 0 | K17: =IF($D17="Cagla",1,0) -> 0 | L17: =IF($D17="Berkay",1,0) -> 0 | M17: =IF($D17="Gozde",1,0) -> 0 | N17: =IF($D17="Mertcan",1,0) -> 0 | O17: =IF($D17="Amy",1,0) -> 0 | P17: =IF($D17="Jason / Derya",1,0) -> 0 | Q17: =IF($D17="Jason / Basak",1,0) -> 0 | R17: =IF($D17="Jason / Cagla",1,0) -> 0 | S17: TRUE | T17: FALSE | U17: FALSE
A18: Chris Westbrook | B18: CESO - Industrial | C18: Senior Program Director | D18: Jason | F18: R+L Carriers | G18: =IF(D18="Jason",1,0) -> 1 | H18: =IF($D18="Jordan",1,0) -> 0 | I18: =IF($D18="John",1,0) -> 0 | J18: =IF($D18="Yigit",1,0) -> 0 | K18: =IF($D18="Cagla",1,0) -> 0 | L18: =IF($D18="Berkay",1,0) -> 0 | M18: =IF($D18="Gozde",1,0) -> 0 | N18: =IF($D18="Mertcan",1,0) -> 0 | O18: =IF($D18="Amy",1,0) -> 0 | P18: =IF($D18="Jason / Derya",1,0) -> 0 | Q18: =IF($D18="Jason / Basak",1,0) -> 0 | R18: =IF($D18="Jason / Cagla",1,0) -> 0 | S18: FALSE | T18: FALSE | U18: FALSE
A19: Elizabeth Cole | B19: CESO - Industrial | C19: Senior Project Manager | D19: Jason | F19: AMZN | G19: =IF(D19="Jason",1,0) -> 1 | H19: =IF($D19="Jordan",1,0) -> 0 | I19: =IF($D19="John",1,0) -> 0 | J19: =IF($D19="Yigit",1,0) -> 0 | K19: =IF($D19="Cagla",1,0) -> 0 | L19: =IF($D19="Berkay",1,0) -> 0 | M19: =IF($D19="Gozde",1,0) -> 0 | N19: =IF($D19="Mertcan",1,0) -> 0 | O19: =IF($D19="Amy",1,0) -> 0 | P19: =IF($D19="Jason / Derya",1,0) -> 0 | Q19: =IF($D19="Jason / Basak",1,0) -> 0 | R19: =IF($D19="Jason / Cagla",1,0) -> 0 | S19: TRUE | T19: TRUE | U19: TRUE
A20: Micheal Allen | B20: CESO - Industrial | D20: Jason | F20: AMZN | G20: =IF(D20="Jason",1,0) -> 1 | H20: =IF($D20="Jordan",1,0) -> 0 | I20: =IF($D20="John",1,0) -> 0 | J20: =IF($D20="Yigit",1,0) -> 0 | K20: =IF($D20="Cagla",1,0) -> 0 | L20: =IF($D20="Berkay",1,0) -> 0 | M20: =IF($D20="Gozde",1,0) -> 0 | N20: =IF($D20="Mertcan",1,0) -> 0 | O20: =IF($D20="Amy",1,0) -> 0 | P20: =IF($D20="Jason / Derya",1,0) -> 0 | Q20: =IF($D20="Jason / Basak",1,0) -> 0 | R20: =IF($D20="Jason / Cagla",1,0) -> 0 | S20: TRUE | T20: TRUE | U20: FALSE
A21: Robert Malone | B21: CESO - Industrial | C21: Program Director | D21: Jason | F21: AMZN SSD | G21: =IF(D21="Jason",1,0) -> 1 | H21: =IF($D21="Jordan",1,0) -> 0 | I21: =IF($D21="John",1,0) -> 0 | J21: =IF($D21="Yigit",1,0) -> 0 | K21: =IF($D21="Cagla",1,0) -> 0 | L21: =IF($D21="Berkay",1,0) -> 0 | M21: =IF($D21="Gozde",1,0) -> 0 | N21: =IF($D21="Mertcan",1,0) -> 0 | O21: =IF($D21="Amy",1,0) -> 0 | P21: =IF($D21="Jason / Derya",1,0) -> 0 | Q21: =IF($D21="Jason / Basak",1,0) -> 0 | R21: =IF($D21="Jason / Cagla",1,0) -> 0 | S21: TRUE | T21: FALSE | U21: FALSE
A22: Jake Bush | B22: CESO - Industrial | C22: Vice President | D22: John | F22: All | G22: =IF(D22="Jason",1,0) -> 0 | H22: =IF($D22="Jordan",1,0) -> 0 | I22: =IF($D22="John",1,0) -> 1 | J22: =IF($D22="Yigit",1,0) -> 0 | K22: =IF($D22="Cagla",1,0) -> 0 | L22: =IF($D22="Berkay",1,0) -> 0 | M22: =IF($D22="Gozde",1,0) -> 0 | N22: =IF($D22="Mertcan",1,0) -> 0 | O22: =IF($D22="Amy",1,0) -> 0 | P22: =IF($D22="Jason / Derya",1,0) -> 0 | Q22: =IF($D22="Jason / Basak",1,0) -> 0 | R22: =IF($D22="Jason / Cagla",1,0) -> 0 | S22: FALSE | T22: TRUE | U22: FALSE
A23: Mike Bless | B23: CESO - Industrial | C23: Team Lead (Architecture) | D23: Yigit | F23: R+L Carriers | G23: =IF(D23="Jason",1,0) -> 0 | H23: =IF($D23="Jordan",1,0) -> 0 | I23: =IF($D23="John",1,0) -> 0 | J23: =IF($D23="Yigit",1,0) -> 1 | K23: =IF($D23="Cagla",1,0) -> 0 | L23: =IF($D23="Berkay",1,0) -> 0 | M23: =IF($D23="Gozde",1,0) -> 0 | N23: =IF($D23="Mertcan",1,0) -> 0 | O23: =IF($D23="Amy",1,0) -> 0 | P23: =IF($D23="Jason / Derya",1,0) -> 0 | Q23: =IF($D23="Jason / Basak",1,0) -> 0 | R23: =IF($D23="Jason / Cagla",1,0) -> 0 | S23: FALSE | T23: FALSE | U23: FALSE
A24: Cory Risola | B24: CESO - Industrial | C24: Project Manager | D24: Yigit | F24: AMZN BIG STORES (~1mil sft) | G24: =IF(D24="Jason",1,0) -> 0 | H24: =IF($D24="Jordan",1,0) -> 0 | I24: =IF($D24="John",1,0) -> 0 | J24: =IF($D24="Yigit",1,0) -> 1 | K24: =IF($D24="Cagla",1,0) -> 0 | L24: =IF($D24="Berkay",1,0) -> 0 | M24: =IF($D24="Gozde",1,0) -> 0 | N24: =IF($D24="Mertcan",1,0) -> 0 | O24: =IF($D24="Amy",1,0) -> 0 | P24: =IF($D24="Jason / Derya",1,0) -> 0 | Q24: =IF($D24="Jason / Basak",1,0) -> 0 | R24: =IF($D24="Jason / Cagla",1,0) -> 0 | S24: TRUE | T24: TRUE | U24: FALSE
A25: Ricky Williams | B25: CESO - Industrial | C25: Team Lead | D25: Yigit | F25: AMZN SSD | G25: =IF(D25="Jason",1,0) -> 0 | H25: =IF($D25="Jordan",1,0) -> 0 | I25: =IF($D25="John",1,0) -> 0 | J25: =IF($D25="Yigit",1,0) -> 1 | K25: =IF($D25="Cagla",1,0) -> 0 | L25: =IF($D25="Berkay",1,0) -> 0 | M25: =IF($D25="Gozde",1,0) -> 0 | N25: =IF($D25="Mertcan",1,0) -> 0 | O25: =IF($D25="Amy",1,0) -> 0 | P25: =IF($D25="Jason / Derya",1,0) -> 0 | Q25: =IF($D25="Jason / Basak",1,0) -> 0 | R25: =IF($D25="Jason / Cagla",1,0) -> 0 | S25: TRUE | T25: FALSE | U25: TRUE
A26: Terry Bilderbeck | B26: CESO - Industrial | D26: Yigit | F26: AMZN RSR | S26: TRUE | T26: TRUE | U26: TRUE
A27: Jordan Flischman | B27: CESO - Industrial (Civil) | C27: Engineering Manager | D27: Jason | F27: RSR Civil STF | G27: =IF(D27="Jason",1,0) -> 1 | H27: =IF($D27="Jordan",1,0) -> 0 | I27: =IF($D27="John",1,0) -> 0 | J27: =IF($D27="Yigit",1,0) -> 0 | K27: =IF($D27="Cagla",1,0) -> 0 | L27: =IF($D27="Berkay",1,0) -> 0 | M27: =IF($D27="Gozde",1,0) -> 0 | N27: =IF($D27="Mertcan",1,0) -> 0 | O27: =IF($D27="Amy",1,0) -> 0 | P27: =IF($D27="Jason / Derya",1,0) -> 0 | Q27: =IF($D27="Jason / Basak",1,0) -> 0 | R27: =IF($D27="Jason / Cagla",1,0) -> 0 | S27: TRUE | T27: TRUE | U27: TRUE
A28: Ricardo Chambers | B28: CESO - Industrial (Civil) | C28: Program Director | D28: Jason | F28: SSD Civil SEP | G28: =IF(D28="Jason",1,0) -> 1 | H28: =IF($D28="Jordan",1,0) -> 0 | I28: =IF($D28="John",1,0) -> 0 | J28: =IF($D28="Yigit",1,0) -> 0 | K28: =IF($D28="Cagla",1,0) -> 0 | L28: =IF($D28="Berkay",1,0) -> 0 | M28: =IF($D28="Gozde",1,0) -> 0 | N28: =IF($D28="Mertcan",1,0) -> 0 | O28: =IF($D28="Amy",1,0) -> 0 | P28: =IF($D28="Jason / Derya",1,0) -> 0 | Q28: =IF($D28="Jason / Basak",1,0) -> 0 | R28: =IF($D28="Jason / Cagla",1,0) -> 0 | S28: TRUE | T28: TRUE | U28: FALSE
A29: Julia Chen | B29: CESO - Industrial (Civil) | C29: Project Engineer II | D29: Yigit | F29: RSR Civil STF | G29: =IF(D29="Jason",1,0) -> 0 | H29: =IF($D29="Jordan",1,0) -> 0 | I29: =IF($D29="John",1,0) -> 0 | J29: =IF($D29="Yigit",1,0) -> 1 | K29: =IF($D29="Cagla",1,0) -> 0 | L29: =IF($D29="Berkay",1,0) -> 0 | M29: =IF($D29="Gozde",1,0) -> 0 | N29: =IF($D29="Mertcan",1,0) -> 0 | O29: =IF($D29="Amy",1,0) -> 0 | P29: =IF($D29="Jason / Derya",1,0) -> 0 | Q29: =IF($D29="Jason / Basak",1,0) -> 0 | R29: =IF($D29="Jason / Cagla",1,0) -> 0 | S29: TRUE | T29: TRUE | U29: TRUE
A30: Tyler Youler | B30: CESO - Industrial (Civil) | C30: Assistant Project Manager | D30: Yigit | F30: SSD Civil SEP | G30: =IF(D30="Jason",1,0) -> 0 | H30: =IF($D30="Jordan",1,0) -> 0 | I30: =IF($D30="John",1,0) -> 0 | J30: =IF($D30="Yigit",1,0) -> 1 | K30: =IF($D30="Cagla",1,0) -> 0 | L30: =IF($D30="Berkay",1,0) -> 0 | M30: =IF($D30="Gozde",1,0) -> 0 | N30: =IF($D30="Mertcan",1,0) -> 0 | O30: =IF($D30="Amy",1,0) -> 0 | P30: =IF($D30="Jason / Derya",1,0) -> 0 | Q30: =IF($D30="Jason / Basak",1,0) -> 0 | R30: =IF($D30="Jason / Cagla",1,0) -> 0 | S30: TRUE | T30: TRUE | U30: FALSE
A31: Bryan Hall | B31: CESO - Leadership | C31: Civil Business Unit Manager | D31: Jason | G31: =IF(D31="Jason",1,0) -> 1 | H31: =IF($D31="Jordan",1,0) -> 0 | I31: =IF($D31="John",1,0) -> 0 | J31: =IF($D31="Yigit",1,0) -> 0 | K31: =IF($D31="Cagla",1,0) -> 0 | L31: =IF($D31="Berkay",1,0) -> 0 | M31: =IF($D31="Gozde",1,0) -> 0 | N31: =IF($D31="Mertcan",1,0) -> 0 | O31: =IF($D31="Amy",1,0) -> 0 | P31: =IF($D31="Jason / Derya",1,0) -> 0 | Q31: =IF($D31="Jason / Basak",1,0) -> 0 | R31: =IF($D31="Jason / Cagla",1,0) -> 0 | S31: TRUE | T31: FALSE | U31: FALSE
A32: Ashley Lyons | B32: CESO - Leadership | C32: Architecture Manager | D32: Jason | G32: =IF(D32="Jason",1,0) -> 1 | H32: =IF($D32="Jordan",1,0) -> 0 | I32: =IF($D32="John",1,0) -> 0 | J32: =IF($D32="Yigit",1,0) -> 0 | K32: =IF($D32="Cagla",1,0) -> 0 | L32: =IF($D32="Berkay",1,0) -> 0 | M32: =IF($D32="Gozde",1,0) -> 0 | N32: =IF($D32="Mertcan",1,0) -> 0 | O32: =IF($D32="Amy",1,0) -> 0 | P32: =IF($D32="Jason / Derya",1,0) -> 0 | Q32: =IF($D32="Jason / Basak",1,0) -> 0 | R32: =IF($D32="Jason / Cagla",1,0) -> 0 | S32: TRUE | T32: FALSE | U32: FALSE
A33: Lennie Arnold | B33: CESO - Leadership | C33: Vice President | D33: John | G33: =IF(D33="Jason",1,0) -> 0 | H33: =IF($D33="Jordan",1,0) -> 0 | I33: =IF($D33="John",1,0) -> 1 | J33: =IF($D33="Yigit",1,0) -> 0 | K33: =IF($D33="Cagla",1,0) -> 0 | L33: =IF($D33="Berkay",1,0) -> 0 | M33: =IF($D33="Gozde",1,0) -> 0 | N33: =IF($D33="Mertcan",1,0) -> 0 | O33: =IF($D33="Amy",1,0) -> 0 | P33: =IF($D33="Jason / Derya",1,0) -> 0 | Q33: =IF($D33="Jason / Basak",1,0) -> 0 | R33: =IF($D33="Jason / Cagla",1,0) -> 0 | S33: FALSE | T33: FALSE | U33: FALSE
A34: Pat MacNabb | B34: CESO - Leadership | C34: Program Director | D34: John | F34: Sams Club | G34: =IF(D34="Jason",1,0) -> 0 | H34: =IF($D34="Jordan",1,0) -> 0 | I34: =IF($D34="John",1,0) -> 1 | J34: =IF($D34="Yigit",1,0) -> 0 | K34: =IF($D34="Cagla",1,0) -> 0 | L34: =IF($D34="Berkay",1,0) -> 0 | M34: =IF($D34="Gozde",1,0) -> 0 | N34: =IF($D34="Mertcan",1,0) -> 0 | O34: =IF($D34="Amy",1,0) -> 0 | P34: =IF($D34="Jason / Derya",1,0) -> 0 | Q34: =IF($D34="Jason / Basak",1,0) -> 0 | R34: =IF($D34="Jason / Cagla",1,0) -> 0 | S34: TRUE | T34: FALSE | U34: FALSE
A35: Lindsay Meranda | B35: CESO - Restaurant & Grocery | C35: Senior Designer | D35: Berkay | E35: once a month | F35: CAVA | G35: =IF(D35="Jason",1,0) -> 0 | H35: =IF($D35="Jordan",1,0) -> 0 | I35: =IF($D35="John",1,0) -> 0 | J35: =IF($D35="Yigit",1,0) -> 0 | K35: =IF($D35="Cagla",1,0) -> 0 | L35: =IF($D35="Berkay",1,0) -> 1 | M35: =IF($D35="Gozde",1,0) -> 0 | N35: =IF($D35="Mertcan",1,0) -> 0 | O35: =IF($D35="Amy",1,0) -> 0 | P35: =IF($D35="Jason / Derya",1,0) -> 0 | Q35: =IF($D35="Jason / Basak",1,0) -> 0 | R35: =IF($D35="Jason / Cagla",1,0) -> 0 | S35: TRUE | T35: TRUE | U35: TRUE
A36: Katie Papin | B36: CESO - Restaurant & Grocery | C36: Senior Project Manager | D36: Berkay | F36: Sprouts | G36: =IF(D36="Jason",1,0) -> 0 | H36: =IF($D36="Jordan",1,0) -> 0 | I36: =IF($D36="John",1,0) -> 0 | J36: =IF($D36="Yigit",1,0) -> 0 | K36: =IF($D36="Cagla",1,0) -> 0 | L36: =IF($D36="Berkay",1,0) -> 1 | M36: =IF($D36="Gozde",1,0) -> 0 | N36: =IF($D36="Mertcan",1,0) -> 0 | O36: =IF($D36="Amy",1,0) -> 0 | P36: =IF($D36="Jason / Derya",1,0) -> 0 | Q36: =IF($D36="Jason / Basak",1,0) -> 0 | R36: =IF($D36="Jason / Cagla",1,0) -> 0 | S36: FALSE | T36: FALSE | U36: FALSE
A37: Jason Longbrake | B37: CESO - Restaurant & Grocery | C37: Restaurant and Grocery Market Leader | D37: Jason | F37: Cracker Barrel ADA, CAVA | G37: =IF(D37="Jason",1,0) -> 1 | H37: =IF($D37="Jordan",1,0) -> 0 | I37: =IF($D37="John",1,0) -> 0 | J37: =IF($D37="Yigit",1,0) -> 0 | K37: =IF($D37="Cagla",1,0) -> 0 | L37: =IF($D37="Berkay",1,0) -> 0 | M37: =IF($D37="Gozde",1,0) -> 0 | N37: =IF($D37="Mertcan",1,0) -> 0 | O37: =IF($D37="Amy",1,0) -> 0 | P37: =IF($D37="Jason / Derya",1,0) -> 0 | Q37: =IF($D37="Jason / Basak",1,0) -> 0 | R37: =IF($D37="Jason / Cagla",1,0) -> 0 | S37: TRUE | T37: TRUE | U37: FALSE
A38: Laura Smith | B38: CESO - Retail | C38: Retail Market Leader | D38: Jason | F38: Albertsons ADA | G38: =IF(D38="Jason",1,0) -> 1 | H38: =IF($D38="Jordan",1,0) -> 0 | I38: =IF($D38="John",1,0) -> 0 | J38: =IF($D38="Yigit",1,0) -> 0 | K38: =IF($D38="Cagla",1,0) -> 0 | L38: =IF($D38="Berkay",1,0) -> 0 | M38: =IF($D38="Gozde",1,0) -> 0 | N38: =IF($D38="Mertcan",1,0) -> 0 | O38: =IF($D38="Amy",1,0) -> 0 | P38: =IF($D38="Jason / Derya",1,0) -> 0 | Q38: =IF($D38="Jason / Basak",1,0) -> 0 | R38: =IF($D38="Jason / Cagla",1,0) -> 0 | S38: TRUE | T38: TRUE | U38: FALSE
A39: Dee Mock | B39: CESO - Sams Club | C39: Project Manager | D39: Berkay | F39: Sams Club | S39: TRUE | T39: TRUE | U39: TRUE
A40: Caitlyn McCausland | B40: CESO - Sams Club | C40: Senior Architectural Designer | D40: Berkay | F40: Sams Club | S40: TRUE | T40: TRUE | U40: TRUE
A41: Eric Eberhardt | B41: CESO - Walmart | C41: Senior Program Director | D41: Jason | F41: Walmart Remodel | G41: =IF(D41="Jason",1,0) -> 1 | H41: =IF($D41="Jordan",1,0) -> 0 | I41: =IF($D41="John",1,0) -> 0 | J41: =IF($D41="Yigit",1,0) -> 0 | K41: =IF($D41="Cagla",1,0) -> 0 | L41: =IF($D41="Berkay",1,0) -> 0 | M41: =IF($D41="Gozde",1,0) -> 0 | N41: =IF($D41="Mertcan",1,0) -> 0 | O41: =IF($D41="Amy",1,0) -> 0 | P41: =IF($D41="Jason / Derya",1,0) -> 0 | Q41: =IF($D41="Jason / Basak",1,0) -> 0 | R41: =IF($D41="Jason / Cagla",1,0) -> 0 | S41: TRUE | T41: FALSE | U41: FALSE
A42: Bob Morrison | B42: CESO - Walmart | C42: Retail Market Leader | D42: John | F42: Walmart & Sams Club | G42: =IF(D42="Jason",1,0) -> 0 | H42: =IF($D42="Jordan",1,0) -> 0 | I42: =IF($D42="John",1,0) -> 1 | J42: =IF($D42="Yigit",1,0) -> 0 | K42: =IF($D42="Cagla",1,0) -> 0 | L42: =IF($D42="Berkay",1,0) -> 0 | M42: =IF($D42="Gozde",1,0) -> 0 | N42: =IF($D42="Mertcan",1,0) -> 0 | O42: =IF($D42="Amy",1,0) -> 0 | P42: =IF($D42="Jason / Derya",1,0) -> 0 | Q42: =IF($D42="Jason / Basak",1,0) -> 0 | R42: =IF($D42="Jason / Cagla",1,0) -> 0 | S42: TRUE | T42: TRUE | U42: FALSE
A43: Dana Reeves | B43: Collier Eng. & Design | C43: Commercial Market & Discipline Leader | D43: Amy | G43: =IF(D43="Jason",1,0) -> 0 | H43: =IF($D43="Jordan",1,0) -> 0 | I43: =IF($D43="John",1,0) -> 0 | J43: =IF($D43="Yigit",1,0) -> 0 | K43: =IF($D43="Cagla",1,0) -> 0 | L43: =IF($D43="Berkay",1,0) -> 0 | M43: =IF($D43="Gozde",1,0) -> 0 | N43: =IF($D43="Mertcan",1,0) -> 0 | O43: =IF($D43="Amy",1,0) -> 1 | P43: =IF($D43="Jason / Derya",1,0) -> 0 | Q43: =IF($D43="Jason / Basak",1,0) -> 0 | R43: =IF($D43="Jason / Cagla",1,0) -> 0 | S43: TRUE | T43: FALSE | U43: FALSE
A44: Jason Boris | B44: Collier Eng. & Design | C44: Design Director | D44: Jason | S44: FALSE | T44: FALSE | U44: TRUE
A45: Casey Whiteman | B45: Collier Eng. & Design | C45: Principal/Manager Site Development | D45: Jason | F45: Data Centers / Distribution Centers | G45: =IF(D45="Jason",1,0) -> 1 | H45: =IF($D45="Jordan",1,0) -> 0 | I45: =IF($D45="John",1,0) -> 0 | J45: =IF($D45="Yigit",1,0) -> 0 | K45: =IF($D45="Cagla",1,0) -> 0 | L45: =IF($D45="Berkay",1,0) -> 0 | M45: =IF($D45="Gozde",1,0) -> 0 | N45: =IF($D45="Mertcan",1,0) -> 0 | O45: =IF($D45="Amy",1,0) -> 0 | P45: =IF($D45="Jason / Derya",1,0) -> 0 | Q45: =IF($D45="Jason / Basak",1,0) -> 0 | R45: =IF($D45="Jason / Cagla",1,0) -> 0 | S45: FALSE | T45: FALSE | U45: FALSE
A46: Justin Mihalik | B46: Collier Eng. & Design | C46: Principal | D46: Jason | F46: Wendy's, Light Bridge Academy | G46: =IF(D46="Jason",1,0) -> 1 | H46: =IF($D46="Jordan",1,0) -> 0 | I46: =IF($D46="John",1,0) -> 0 | J46: =IF($D46="Yigit",1,0) -> 0 | K46: =IF($D46="Cagla",1,0) -> 0 | L46: =IF($D46="Berkay",1,0) -> 0 | M46: =IF($D46="Gozde",1,0) -> 0 | N46: =IF($D46="Mertcan",1,0) -> 0 | O46: =IF($D46="Amy",1,0) -> 0 | P46: =IF($D46="Jason / Derya",1,0) -> 0 | Q46: =IF($D46="Jason / Basak",1,0) -> 0 | R46: =IF($D46="Jason / Cagla",1,0) -> 0 | S46: TRUE | T46: FALSE | U46: TRUE
A47: Mike Yao | B47: Core States | C47: Program Manager | D47: Jason | F47: CFA | G47: =IF(D47="Jason",1,0) -> 1 | H47: =IF($D47="Jordan",1,0) -> 0 | I47: =IF($D47="John",1,0) -> 0 | J47: =IF($D47="Yigit",1,0) -> 0 | K47: =IF($D47="Cagla",1,0) -> 0 | L47: =IF($D47="Berkay",1,0) -> 0 | M47: =IF($D47="Gozde",1,0) -> 0 | N47: =IF($D47="Mertcan",1,0) -> 0 | O47: =IF($D47="Amy",1,0) -> 0 | P47: =IF($D47="Jason / Derya",1,0) -> 0 | Q47: =IF($D47="Jason / Basak",1,0) -> 0 | R47: =IF($D47="Jason / Cagla",1,0) -> 0 | S47: FALSE | T47: FALSE | U47: FALSE
A48: Ruben Alonso | B48: Core States | C48: Operations Director | D48: Jason | E48: Bi-weekly | G48: =IF(D48="Jason",1,0) -> 1 | H48: =IF($D48="Jordan",1,0) -> 0 | I48: =IF($D48="John",1,0) -> 0 | J48: =IF($D48="Yigit",1,0) -> 0 | K48: =IF($D48="Cagla",1,0) -> 0 | L48: =IF($D48="Berkay",1,0) -> 0 | M48: =IF($D48="Gozde",1,0) -> 0 | N48: =IF($D48="Mertcan",1,0) -> 0 | O48: =IF($D48="Amy",1,0) -> 0 | P48: =IF($D48="Jason / Derya",1,0) -> 0 | Q48: =IF($D48="Jason / Basak",1,0) -> 0 | R48: =IF($D48="Jason / Cagla",1,0) -> 0 | S48: TRUE | T48: TRUE | U48: TRUE
A49: Kelley Teska | B49: Core States | C49: Project Manager | D49: Yigit | E49: Bi-weekly | F49: BWW, Arby's, Zaxby's | G49: =IF(D49="Jason",1,0) -> 0 | H49: =IF($D49="Jordan",1,0) -> 0 | I49: =IF($D49="John",1,0) -> 0 | J49: =IF($D49="Yigit",1,0) -> 1 | K49: =IF($D49="Cagla",1,0) -> 0 | L49: =IF($D49="Berkay",1,0) -> 0 | M49: =IF($D49="Gozde",1,0) -> 0 | N49: =IF($D49="Mertcan",1,0) -> 0 | O49: =IF($D49="Amy",1,0) -> 0 | P49: =IF($D49="Jason / Derya",1,0) -> 0 | Q49: =IF($D49="Jason / Basak",1,0) -> 0 | R49: =IF($D49="Jason / Cagla",1,0) -> 0 | S49: TRUE | T49: TRUE | U49: TRUE
A50: Keri Budzyn | B50: Core States | C50: Organizational Effectiveness Manager | D50: Yigit | E50: Bi-weekly | G50: =IF(D50="Jason",1,0) -> 0 | H50: =IF($D50="Jordan",1,0) -> 0 | I50: =IF($D50="John",1,0) -> 0 | J50: =IF($D50="Yigit",1,0) -> 1 | K50: =IF($D50="Cagla",1,0) -> 0 | L50: =IF($D50="Berkay",1,0) -> 0 | M50: =IF($D50="Gozde",1,0) -> 0 | N50: =IF($D50="Mertcan",1,0) -> 0 | O50: =IF($D50="Amy",1,0) -> 0 | P50: =IF($D50="Jason / Derya",1,0) -> 0 | Q50: =IF($D50="Jason / Basak",1,0) -> 0 | R50: =IF($D50="Jason / Cagla",1,0) -> 0 | S50: TRUE | T50: FALSE | U50: FALSE
A51: Kate Sabol | B51: Core States | C51: Senior Project Manager | D51: Yigit | F51: Starbucks | G51: =IF(D51="Jason",1,0) -> 0 | H51: =IF($D51="Jordan",1,0) -> 0 | I51: =IF($D51="John",1,0) -> 0 | J51: =IF($D51="Yigit",1,0) -> 1 | K51: =IF($D51="Cagla",1,0) -> 0 | L51: =IF($D51="Berkay",1,0) -> 0 | M51: =IF($D51="Gozde",1,0) -> 0 | N51: =IF($D51="Mertcan",1,0) -> 0 | O51: =IF($D51="Amy",1,0) -> 0 | P51: =IF($D51="Jason / Derya",1,0) -> 0 | Q51: =IF($D51="Jason / Basak",1,0) -> 0 | R51: =IF($D51="Jason / Cagla",1,0) -> 0 | S51: FALSE | T51: FALSE | U51: FALSE
A52: Daniel Blohowiak | B52: Core States - C-Store | C52: Senior Project Architect | D52: Jason | F52: Family Express | G52: =IF(D52="Jason",1,0) -> 1 | H52: =IF($D52="Jordan",1,0) -> 0 | I52: =IF($D52="John",1,0) -> 0 | J52: =IF($D52="Yigit",1,0) -> 0 | K52: =IF($D52="Cagla",1,0) -> 0 | L52: =IF($D52="Berkay",1,0) -> 0 | M52: =IF($D52="Gozde",1,0) -> 0 | N52: =IF($D52="Mertcan",1,0) -> 0 | O52: =IF($D52="Amy",1,0) -> 0 | P52: =IF($D52="Jason / Derya",1,0) -> 0 | Q52: =IF($D52="Jason / Basak",1,0) -> 0 | R52: =IF($D52="Jason / Cagla",1,0) -> 0 | S52: TRUE | T52: TRUE | U52: TRUE
A53: Keyanna Yerry | B53: Core States - C-Store | C53: Senior Project Manager | D53: Yigit | F53: Circle K, Travel Center, Dash-in | G53: =IF(D53="Jason",1,0) -> 0 | H53: =IF($D53="Jordan",1,0) -> 0 | I53: =IF($D53="John",1,0) -> 0 | J53: =IF($D53="Yigit",1,0) -> 1 | K53: =IF($D53="Cagla",1,0) -> 0 | L53: =IF($D53="Berkay",1,0) -> 0 | M53: =IF($D53="Gozde",1,0) -> 0 | N53: =IF($D53="Mertcan",1,0) -> 0 | O53: =IF($D53="Amy",1,0) -> 0 | P53: =IF($D53="Jason / Derya",1,0) -> 0 | Q53: =IF($D53="Jason / Basak",1,0) -> 0 | R53: =IF($D53="Jason / Cagla",1,0) -> 0 | S53: TRUE | T53: TRUE | U53: TRUE
A54: Mark Bernet | B54: Core States - Energy | C54: Project Manager | D54: Jason | F54: EVGo | G54: =IF(D54="Jason",1,0) -> 1 | H54: =IF($D54="Jordan",1,0) -> 0 | I54: =IF($D54="John",1,0) -> 0 | J54: =IF($D54="Yigit",1,0) -> 0 | K54: =IF($D54="Cagla",1,0) -> 0 | L54: =IF($D54="Berkay",1,0) -> 0 | M54: =IF($D54="Gozde",1,0) -> 0 | N54: =IF($D54="Mertcan",1,0) -> 0 | O54: =IF($D54="Amy",1,0) -> 0 | P54: =IF($D54="Jason / Derya",1,0) -> 0 | Q54: =IF($D54="Jason / Basak",1,0) -> 0 | R54: =IF($D54="Jason / Cagla",1,0) -> 0 | S54: FALSE | T54: FALSE | U54: FALSE
A55: Clay Gallagher | B55: Core States - Energy | C55: Project Manager | D55: Jordan | E55: Monthly | F55: EVGo | G55: =IF(D55="Jason",1,0) -> 0 | H55: =IF($D55="Jordan",1,0) -> 1 | I55: =IF($D55="John",1,0) -> 0 | J55: =IF($D55="Yigit",1,0) -> 0 | K55: =IF($D55="Cagla",1,0) -> 0 | L55: =IF($D55="Berkay",1,0) -> 0 | M55: =IF($D55="Gozde",1,0) -> 0 | N55: =IF($D55="Mertcan",1,0) -> 0 | O55: =IF($D55="Amy",1,0) -> 0 | P55: =IF($D55="Jason / Derya",1,0) -> 0 | Q55: =IF($D55="Jason / Basak",1,0) -> 0 | R55: =IF($D55="Jason / Cagla",1,0) -> 0 | S55: TRUE | T55: TRUE | U55: FALSE
A56: Omar Tun | B56: Core States - Energy | C56: Senior Project Designer | D56: Yigit | F56: EVGo | G56: =IF(D56="Jason",1,0) -> 0 | H56: =IF($D56="Jordan",1,0) -> 0 | I56: =IF($D56="John",1,0) -> 0 | J56: =IF($D56="Yigit",1,0) -> 1 | K56: =IF($D56="Cagla",1,0) -> 0 | L56: =IF($D56="Berkay",1,0) -> 0 | M56: =IF($D56="Gozde",1,0) -> 0 | N56: =IF($D56="Mertcan",1,0) -> 0 | O56: =IF($D56="Amy",1,0) -> 0 | P56: =IF($D56="Jason / Derya",1,0) -> 0 | Q56: =IF($D56="Jason / Basak",1,0) -> 0 | R56: =IF($D56="Jason / Cagla",1,0) -> 0 | S56: TRUE | T56: FALSE | U56: FALSE
A57: John Ferguson | B57: Core States - Engineering | C57: Sr. Director of Engineering | D57: Jason | G57: =IF(D57="Jason",1,0) -> 1 | H57: =IF($D57="Jordan",1,0) -> 0 | I57: =IF($D57="John",1,0) -> 0 | J57: =IF($D57="Yigit",1,0) -> 0 | K57: =IF($D57="Cagla",1,0) -> 0 | L57: =IF($D57="Berkay",1,0) -> 0 | M57: =IF($D57="Gozde",1,0) -> 0 | N57: =IF($D57="Mertcan",1,0) -> 0 | O57: =IF($D57="Amy",1,0) -> 0 | P57: =IF($D57="Jason / Derya",1,0) -> 0 | Q57: =IF($D57="Jason / Basak",1,0) -> 0 | R57: =IF($D57="Jason / Cagla",1,0) -> 0 | S57: FALSE | T57: TRUE | U57: FALSE
A58: Kent Craig | B58: Core States - Engineering | C58: Senior Electrical Project Manager | D58: Yigit | G58: =IF(D58="Jason",1,0) -> 0 | H58: =IF($D58="Jordan",1,0) -> 0 | I58: =IF($D58="John",1,0) -> 0 | J58: =IF($D58="Yigit",1,0) -> 1 | K58: =IF($D58="Cagla",1,0) -> 0 | L58: =IF($D58="Berkay",1,0) -> 0 | M58: =IF($D58="Gozde",1,0) -> 0 | N58: =IF($D58="Mertcan",1,0) -> 0 | O58: =IF($D58="Amy",1,0) -> 0 | P58: =IF($D58="Jason / Derya",1,0) -> 0 | Q58: =IF($D58="Jason / Basak",1,0) -> 0 | R58: =IF($D58="Jason / Cagla",1,0) -> 0 | S58: FALSE | T58: TRUE | U58: TRUE
A59: Tyler Starr | B59: Core States - Engineering | C59: Mechanical Project Engineer | D59: Yigit | E59: Weekly | G59: =IF(D59="Jason",1,0) -> 0 | H59: =IF($D59="Jordan",1,0) -> 0 | I59: =IF($D59="John",1,0) -> 0 | J59: =IF($D59="Yigit",1,0) -> 1 | K59: =IF($D59="Cagla",1,0) -> 0 | L59: =IF($D59="Berkay",1,0) -> 0 | M59: =IF($D59="Gozde",1,0) -> 0 | N59: =IF($D59="Mertcan",1,0) -> 0 | O59: =IF($D59="Amy",1,0) -> 0 | P59: =IF($D59="Jason / Derya",1,0) -> 0 | Q59: =IF($D59="Jason / Basak",1,0) -> 0 | R59: =IF($D59="Jason / Cagla",1,0) -> 0 | S59: TRUE | T59: FALSE | U59: TRUE
A60: Brad Myers | B60: Core States - Engineering | C60: Senior Project Manager - Electrical | D60: Yigit | F60: Oil Changers | G60: =IF(D60="Jason",1,0) -> 0 | H60: =IF($D60="Jordan",1,0) -> 0 | I60: =IF($D60="John",1,0) -> 0 | J60: =IF($D60="Yigit",1,0) -> 1 | K60: =IF($D60="Cagla",1,0) -> 0 | L60: =IF($D60="Berkay",1,0) -> 0 | M60: =IF($D60="Gozde",1,0) -> 0 | N60: =IF($D60="Mertcan",1,0) -> 0 | O60: =IF($D60="Amy",1,0) -> 0 | P60: =IF($D60="Jason / Derya",1,0) -> 0 | Q60: =IF($D60="Jason / Basak",1,0) -> 0 | R60: =IF($D60="Jason / Cagla",1,0) -> 0 | S60: TRUE | T60: TRUE | U60: TRUE
A61: Fredwin Molina | B61: Core States - Finance | C61: Senior Project Architect | D61: Cagla | E61: Weekly | F61: Wells Fargo | G61: =IF(D61="Jason",1,0) -> 0 | H61: =IF($D61="Jordan",1,0) -> 0 | I61: =IF($D61="John",1,0) -> 0 | J61: =IF($D61="Yigit",1,0) -> 0 | K61: =IF($D61="Cagla",1,0) -> 1 | L61: =IF($D61="Berkay",1,0) -> 0 | M61: =IF($D61="Gozde",1,0) -> 0 | N61: =IF($D61="Mertcan",1,0) -> 0 | O61: =IF($D61="Amy",1,0) -> 0 | P61: =IF($D61="Jason / Derya",1,0) -> 0 | Q61: =IF($D61="Jason / Basak",1,0) -> 0 | R61: =IF($D61="Jason / Cagla",1,0) -> 0 | S61: TRUE | T61: TRUE | U61: TRUE
A62: Virginia Alvarez | B62: Core States - Finance | C62: Project Manager | D62: Jason | E62: Weekly | F62: Wells Fargo | G62: =IF(D62="Jason",1,0) -> 1 | H62: =IF($D62="Jordan",1,0) -> 0 | I62: =IF($D62="John",1,0) -> 0 | J62: =IF($D62="Yigit",1,0) -> 0 | K62: =IF($D62="Cagla",1,0) -> 0 | L62: =IF($D62="Berkay",1,0) -> 0 | M62: =IF($D62="Gozde",1,0) -> 0 | N62: =IF($D62="Mertcan",1,0) -> 0 | O62: =IF($D62="Amy",1,0) -> 0 | P62: =IF($D62="Jason / Derya",1,0) -> 0 | Q62: =IF($D62="Jason / Basak",1,0) -> 0 | R62: =IF($D62="Jason / Cagla",1,0) -> 0 | S62: TRUE | T62: TRUE | U62: TRUE
A63: James Lalli | B63: Core States - Finance | C63: Director of Architecture, Financial | D63: John | F63: Wells Fargo | G63: =IF(D63="Jason",1,0) -> 0 | H63: =IF($D63="Jordan",1,0) -> 0 | I63: =IF($D63="John",1,0) -> 1 | J63: =IF($D63="Yigit",1,0) -> 0 | K63: =IF($D63="Cagla",1,0) -> 0 | L63: =IF($D63="Berkay",1,0) -> 0 | M63: =IF($D63="Gozde",1,0) -> 0 | N63: =IF($D63="Mertcan",1,0) -> 0 | O63: =IF($D63="Amy",1,0) -> 0 | P63: =IF($D63="Jason / Derya",1,0) -> 0 | Q63: =IF($D63="Jason / Basak",1,0) -> 0 | R63: =IF($D63="Jason / Cagla",1,0) -> 0 | S63: FALSE | T63: TRUE | U63: TRUE
A64: Bryan Grabon | B64: Core States - Leadership | C64: Director of Construction Programs | D64: John | G64: =IF(D64="Jason",1,0) -> 0 | H64: =IF($D64="Jordan",1,0) -> 0 | I64: =IF($D64="John",1,0) -> 1 | J64: =IF($D64="Yigit",1,0) -> 0 | K64: =IF($D64="Cagla",1,0) -> 0 | L64: =IF($D64="Berkay",1,0) -> 0 | M64: =IF($D64="Gozde",1,0) -> 0 | N64: =IF($D64="Mertcan",1,0) -> 0 | O64: =IF($D64="Amy",1,0) -> 0 | P64: =IF($D64="Jason / Derya",1,0) -> 0 | Q64: =IF($D64="Jason / Basak",1,0) -> 0 | R64: =IF($D64="Jason / Cagla",1,0) -> 0 | S64: FALSE | T64: FALSE | U64: FALSE
A65: Austin Stone | B65: Core States - Leadership | C65: Director of Design Efficiency + Analytics | D65: John | G65: =IF(D65="Jason",1,0) -> 0 | H65: =IF($D65="Jordan",1,0) -> 0 | I65: =IF($D65="John",1,0) -> 1 | J65: =IF($D65="Yigit",1,0) -> 0 | K65: =IF($D65="Cagla",1,0) -> 0 | L65: =IF($D65="Berkay",1,0) -> 0 | M65: =IF($D65="Gozde",1,0) -> 0 | N65: =IF($D65="Mertcan",1,0) -> 0 | O65: =IF($D65="Amy",1,0) -> 0 | P65: =IF($D65="Jason / Derya",1,0) -> 0 | Q65: =IF($D65="Jason / Basak",1,0) -> 0 | R65: =IF($D65="Jason / Cagla",1,0) -> 0 | S65: FALSE | T65: FALSE | U65: FALSE
A66: Angie Feulner | B66: Core States - Retail | C66: Senior Project Architect | D66: Berkay | E66: Every Other Month | F66: Total Wine & More | G66: =IF(D66="Jason",1,0) -> 0 | H66: =IF($D66="Jordan",1,0) -> 0 | I66: =IF($D66="John",1,0) -> 0 | J66: =IF($D66="Yigit",1,0) -> 0 | K66: =IF($D66="Cagla",1,0) -> 0 | L66: =IF($D66="Berkay",1,0) -> 1 | M66: =IF($D66="Gozde",1,0) -> 0 | N66: =IF($D66="Mertcan",1,0) -> 0 | O66: =IF($D66="Amy",1,0) -> 0 | P66: =IF($D66="Jason / Derya",1,0) -> 0 | Q66: =IF($D66="Jason / Basak",1,0) -> 0 | R66: =IF($D66="Jason / Cagla",1,0) -> 0 | S66: FALSE | T66: FALSE | U66: FALSE
A67: Brody Peterson | B67: Core States - Retail | C67: Senior Project Manager | D67: Berkay | F67: Dollar Tree, Pep Boys, Lowes | G67: =IF(D67="Jason",1,0) -> 0 | H67: =IF($D67="Jordan",1,0) -> 0 | I67: =IF($D67="John",1,0) -> 0 | J67: =IF($D67="Yigit",1,0) -> 0 | K67: =IF($D67="Cagla",1,0) -> 0 | L67: =IF($D67="Berkay",1,0) -> 1 | M67: =IF($D67="Gozde",1,0) -> 0 | N67: =IF($D67="Mertcan",1,0) -> 0 | O67: =IF($D67="Amy",1,0) -> 0 | P67: =IF($D67="Jason / Derya",1,0) -> 0 | Q67: =IF($D67="Jason / Basak",1,0) -> 0 | R67: =IF($D67="Jason / Cagla",1,0) -> 0 | S67: TRUE | T67: FALSE | U67: FALSE
A68: Brad Hamilton | B68: Core States - Retail | C68: Director of Architecture | D68: Jason | E68: Every Other Month | G68: =IF(D68="Jason",1,0) -> 1 | H68: =IF($D68="Jordan",1,0) -> 0 | I68: =IF($D68="John",1,0) -> 0 | J68: =IF($D68="Yigit",1,0) -> 0 | K68: =IF($D68="Cagla",1,0) -> 0 | L68: =IF($D68="Berkay",1,0) -> 0 | M68: =IF($D68="Gozde",1,0) -> 0 | N68: =IF($D68="Mertcan",1,0) -> 0 | O68: =IF($D68="Amy",1,0) -> 0 | P68: =IF($D68="Jason / Derya",1,0) -> 0 | Q68: =IF($D68="Jason / Basak",1,0) -> 0 | R68: =IF($D68="Jason / Cagla",1,0) -> 0 | S68: TRUE | T68: TRUE | U68: TRUE
A69: Joshua Sleeter | B69: CPH | C69: Program Manager | D69: Berkay | F69: Walmart FV Shells | G69: =IF(D69="Jason",1,0) -> 0 | H69: =IF($D69="Jordan",1,0) -> 0 | I69: =IF($D69="John",1,0) -> 0 | J69: =IF($D69="Yigit",1,0) -> 0 | K69: =IF($D69="Cagla",1,0) -> 0 | L69: =IF($D69="Berkay",1,0) -> 1 | M69: =IF($D69="Gozde",1,0) -> 0 | N69: =IF($D69="Mertcan",1,0) -> 0 | O69: =IF($D69="Amy",1,0) -> 0 | P69: =IF($D69="Jason / Derya",1,0) -> 0 | Q69: =IF($D69="Jason / Basak",1,0) -> 0 | R69: =IF($D69="Jason / Cagla",1,0) -> 0 | S69: TRUE | T69: TRUE | U69: TRUE
A70: Ilker Uzun | B70: CPH | C70: Retail Studio Principal | D70: John | F70: Walmart FV Shells | G70: =IF(D70="Jason",1,0) -> 0 | H70: =IF($D70="Jordan",1,0) -> 0 | I70: =IF($D70="John",1,0) -> 1 | J70: =IF($D70="Yigit",1,0) -> 0 | K70: =IF($D70="Cagla",1,0) -> 0 | L70: =IF($D70="Berkay",1,0) -> 0 | M70: =IF($D70="Gozde",1,0) -> 0 | N70: =IF($D70="Mertcan",1,0) -> 0 | O70: =IF($D70="Amy",1,0) -> 0 | P70: =IF($D70="Jason / Derya",1,0) -> 0 | Q70: =IF($D70="Jason / Basak",1,0) -> 0 | R70: =IF($D70="Jason / Cagla",1,0) -> 0 | S70: FALSE | T70: TRUE | U70: TRUE
A71: Kaylee Kaufman | B71: DXU | C71: Sr Project Manager | D71: Berkay | F71: Panera | G71: =IF(D71="Jason",1,0) -> 0 | H71: =IF($D71="Jordan",1,0) -> 0 | I71: =IF($D71="John",1,0) -> 0 | J71: =IF($D71="Yigit",1,0) -> 0 | K71: =IF($D71="Cagla",1,0) -> 0 | L71: =IF($D71="Berkay",1,0) -> 1 | M71: =IF($D71="Gozde",1,0) -> 0 | N71: =IF($D71="Mertcan",1,0) -> 0 | O71: =IF($D71="Amy",1,0) -> 0 | P71: =IF($D71="Jason / Derya",1,0) -> 0 | Q71: =IF($D71="Jason / Basak",1,0) -> 0 | R71: =IF($D71="Jason / Cagla",1,0) -> 0 | S71: TRUE | T71: FALSE | U71: FALSE
A72: Austin Register | B72: DXU | C72: Project Designer | D72: Berkay | F72: Glowbar, Pickler | G72: =IF(D72="Jason",1,0) -> 0 | H72: =IF($D72="Jordan",1,0) -> 0 | I72: =IF($D72="John",1,0) -> 0 | J72: =IF($D72="Yigit",1,0) -> 0 | K72: =IF($D72="Cagla",1,0) -> 0 | L72: =IF($D72="Berkay",1,0) -> 1 | M72: =IF($D72="Gozde",1,0) -> 0 | N72: =IF($D72="Mertcan",1,0) -> 0 | O72: =IF($D72="Amy",1,0) -> 0 | P72: =IF($D72="Jason / Derya",1,0) -> 0 | Q72: =IF($D72="Jason / Basak",1,0) -> 0 | R72: =IF($D72="Jason / Cagla",1,0) -> 0 | S72: TRUE | T72: FALSE | U72: TRUE
A73: Alex Karshis | B73: DXU | C73: Design Manager | D73: Berkay | F73: Glowbar, Pickler | G73: =IF(D73="Jason",1,0) -> 0 | H73: =IF($D73="Jordan",1,0) -> 0 | I73: =IF($D73="John",1,0) -> 0 | J73: =IF($D73="Yigit",1,0) -> 0 | K73: =IF($D73="Cagla",1,0) -> 0 | L73: =IF($D73="Berkay",1,0) -> 1 | M73: =IF($D73="Gozde",1,0) -> 0 | N73: =IF($D73="Mertcan",1,0) -> 0 | O73: =IF($D73="Amy",1,0) -> 0 | P73: =IF($D73="Jason / Derya",1,0) -> 0 | Q73: =IF($D73="Jason / Basak",1,0) -> 0 | R73: =IF($D73="Jason / Cagla",1,0) -> 0 | S73: FALSE | T73: FALSE | U73: FALSE
A74: Sean Jackson | B74: DXU | C74: Project Manager | D74: Cagla | F74: Solidcore | G74: =IF(D74="Jason",1,0) -> 0 | H74: =IF($D74="Jordan",1,0) -> 0 | I74: =IF($D74="John",1,0) -> 0 | J74: =IF($D74="Yigit",1,0) -> 0 | K74: =IF($D74="Cagla",1,0) -> 1 | L74: =IF($D74="Berkay",1,0) -> 0 | M74: =IF($D74="Gozde",1,0) -> 0 | N74: =IF($D74="Mertcan",1,0) -> 0 | O74: =IF($D74="Amy",1,0) -> 0 | P74: =IF($D74="Jason / Derya",1,0) -> 0 | Q74: =IF($D74="Jason / Basak",1,0) -> 0 | R74: =IF($D74="Jason / Cagla",1,0) -> 0 | S74: TRUE | T74: FALSE | U74: FALSE
A75: Anthony Volpe | B75: DXU | C75: Managing Principal | D75: Jason | F75: Big Blue | G75: =IF(D75="Jason",1,0) -> 1 | H75: =IF($D75="Jordan",1,0) -> 0 | I75: =IF($D75="John",1,0) -> 0 | J75: =IF($D75="Yigit",1,0) -> 0 | K75: =IF($D75="Cagla",1,0) -> 0 | L75: =IF($D75="Berkay",1,0) -> 0 | M75: =IF($D75="Gozde",1,0) -> 0 | N75: =IF($D75="Mertcan",1,0) -> 0 | O75: =IF($D75="Amy",1,0) -> 0 | P75: =IF($D75="Jason / Derya",1,0) -> 0 | Q75: =IF($D75="Jason / Basak",1,0) -> 0 | R75: =IF($D75="Jason / Cagla",1,0) -> 0 | S75: FALSE | T75: FALSE | U75: FALSE
A76: Emily Lindsay | B76: DXU | C76: Director | D76: Jason | F76: SolidCore / Big Blue | G76: =IF(D76="Jason",1,0) -> 1 | H76: =IF($D76="Jordan",1,0) -> 0 | I76: =IF($D76="John",1,0) -> 0 | J76: =IF($D76="Yigit",1,0) -> 0 | K76: =IF($D76="Cagla",1,0) -> 0 | L76: =IF($D76="Berkay",1,0) -> 0 | M76: =IF($D76="Gozde",1,0) -> 0 | N76: =IF($D76="Mertcan",1,0) -> 0 | O76: =IF($D76="Amy",1,0) -> 0 | P76: =IF($D76="Jason / Derya",1,0) -> 0 | Q76: =IF($D76="Jason / Basak",1,0) -> 0 | R76: =IF($D76="Jason / Cagla",1,0) -> 0 | S76: TRUE | T76: FALSE | U76: FALSE
A77: Kevin Bromenshenk | B77: Flintco | C77: VDC Director | D77: Jordan | G77: =IF(D77="Jason",1,0) -> 0 | H77: =IF($D77="Jordan",1,0) -> 1 | I77: =IF($D77="John",1,0) -> 0 | J77: =IF($D77="Yigit",1,0) -> 0 | K77: =IF($D77="Cagla",1,0) -> 0 | L77: =IF($D77="Berkay",1,0) -> 0 | M77: =IF($D77="Gozde",1,0) -> 0 | N77: =IF($D77="Mertcan",1,0) -> 0 | O77: =IF($D77="Amy",1,0) -> 0 | P77: =IF($D77="Jason / Derya",1,0) -> 0 | Q77: =IF($D77="Jason / Basak",1,0) -> 0 | R77: =IF($D77="Jason / Cagla",1,0) -> 0 | S77: TRUE | T77: TRUE | U77: TRUE
A78: Aaron Downing | B78: Flintco | C78: VDC Coordinator | D78: Mertcan | F78: Izzio Bakery | G78: =IF(D78="Jason",1,0) -> 0 | H78: =IF($D78="Jordan",1,0) -> 0 | I78: =IF($D78="John",1,0) -> 0 | J78: =IF($D78="Yigit",1,0) -> 0 | K78: =IF($D78="Cagla",1,0) -> 0 | L78: =IF($D78="Berkay",1,0) -> 0 | M78: =IF($D78="Gozde",1,0) -> 0 | N78: =IF($D78="Mertcan",1,0) -> 1 | O78: =IF($D78="Amy",1,0) -> 0 | P78: =IF($D78="Jason / Derya",1,0) -> 0 | Q78: =IF($D78="Jason / Basak",1,0) -> 0 | R78: =IF($D78="Jason / Cagla",1,0) -> 0 | S78: TRUE | T78: TRUE | U78: FALSE
A79: Chris Martin | B79: Flintco | C79: VDC Senior Coordinator | D79: Mertcan | F79: JeffCo Library | G79: =IF(D79="Jason",1,0) -> 0 | H79: =IF($D79="Jordan",1,0) -> 0 | I79: =IF($D79="John",1,0) -> 0 | J79: =IF($D79="Yigit",1,0) -> 0 | K79: =IF($D79="Cagla",1,0) -> 0 | L79: =IF($D79="Berkay",1,0) -> 0 | M79: =IF($D79="Gozde",1,0) -> 0 | N79: =IF($D79="Mertcan",1,0) -> 1 | O79: =IF($D79="Amy",1,0) -> 0 | P79: =IF($D79="Jason / Derya",1,0) -> 0 | Q79: =IF($D79="Jason / Basak",1,0) -> 0 | R79: =IF($D79="Jason / Cagla",1,0) -> 0 | S79: TRUE | T79: TRUE | U79: TRUE
A80: Dave Garbaz | B80: Flintco | C80: VDC Manager | D80: Mertcan | F80: JeffCo Library | S80: TRUE | T80: TRUE | U80: TRUE
A81: Emilia Gosiewska | B81: Hitachi Energy | C81: Application Manager | D81: Berkay | G81: =IF(D81="Jason",1,0) -> 0 | H81: =IF($D81="Jordan",1,0) -> 0 | I81: =IF($D81="John",1,0) -> 0 | J81: =IF($D81="Yigit",1,0) -> 0 | K81: =IF($D81="Cagla",1,0) -> 0 | L81: =IF($D81="Berkay",1,0) -> 1 | M81: =IF($D81="Gozde",1,0) -> 0 | N81: =IF($D81="Mertcan",1,0) -> 0 | O81: =IF($D81="Amy",1,0) -> 0 | P81: =IF($D81="Jason / Derya",1,0) -> 0 | Q81: =IF($D81="Jason / Basak",1,0) -> 0 | R81: =IF($D81="Jason / Cagla",1,0) -> 0 | S81: TRUE | T81: TRUE | U81: TRUE
A82: Kevin Clark | B82: Novilla RNG | C82: Director of Engineering | D82: Jason | F82: Sporatic projects | G82: =IF(D82="Jason",1,0) -> 1 | H82: =IF($D82="Jordan",1,0) -> 0 | I82: =IF($D82="John",1,0) -> 0 | J82: =IF($D82="Yigit",1,0) -> 0 | K82: =IF($D82="Cagla",1,0) -> 0 | L82: =IF($D82="Berkay",1,0) -> 0 | M82: =IF($D82="Gozde",1,0) -> 0 | N82: =IF($D82="Mertcan",1,0) -> 0 | O82: =IF($D82="Amy",1,0) -> 0 | P82: =IF($D82="Jason / Derya",1,0) -> 0 | Q82: =IF($D82="Jason / Basak",1,0) -> 0 | R82: =IF($D82="Jason / Cagla",1,0) -> 0 | S82: TRUE | T82: FALSE | U82: FALSE
A83: Cory Eberly | B83: Novilla RNG | C83: Sr. Project Designer | D83: Yigit | F83: Sporatic projects | G83: =IF(D83="Jason",1,0) -> 0 | H83: =IF($D83="Jordan",1,0) -> 0 | I83: =IF($D83="John",1,0) -> 0 | J83: =IF($D83="Yigit",1,0) -> 1 | K83: =IF($D83="Cagla",1,0) -> 0 | L83: =IF($D83="Berkay",1,0) -> 0 | M83: =IF($D83="Gozde",1,0) -> 0 | N83: =IF($D83="Mertcan",1,0) -> 0 | O83: =IF($D83="Amy",1,0) -> 0 | P83: =IF($D83="Jason / Derya",1,0) -> 0 | Q83: =IF($D83="Jason / Basak",1,0) -> 0 | R83: =IF($D83="Jason / Cagla",1,0) -> 0 | S83: TRUE | T83: FALSE | U83: FALSE
A84: Wash Givings | B84: SGA Design Group | C84: Program Manager | D84: Cagla | E84: Bi-weekly | G84: =IF(D84="Jason",1,0) -> 0 | H84: =IF($D84="Jordan",1,0) -> 0 | I84: =IF($D84="John",1,0) -> 0 | J84: =IF($D84="Yigit",1,0) -> 0 | K84: =IF($D84="Cagla",1,0) -> 1 | L84: =IF($D84="Berkay",1,0) -> 0 | M84: =IF($D84="Gozde",1,0) -> 0 | N84: =IF($D84="Mertcan",1,0) -> 0 | O84: =IF($D84="Amy",1,0) -> 0 | P84: =IF($D84="Jason / Derya",1,0) -> 0 | Q84: =IF($D84="Jason / Basak",1,0) -> 0 | R84: =IF($D84="Jason / Cagla",1,0) -> 0 | S84: TRUE | T84: TRUE | U84: TRUE
A85: Chris Young | B85: SGA Design Group | C85: VP, Principal | D85: Jason | F85: Walmart | G85: =IF(D85="Jason",1,0) -> 1 | H85: =IF($D85="Jordan",1,0) -> 0 | I85: =IF($D85="John",1,0) -> 0 | J85: =IF($D85="Yigit",1,0) -> 0 | K85: =IF($D85="Cagla",1,0) -> 0 | L85: =IF($D85="Berkay",1,0) -> 0 | M85: =IF($D85="Gozde",1,0) -> 0 | N85: =IF($D85="Mertcan",1,0) -> 0 | O85: =IF($D85="Amy",1,0) -> 0 | P85: =IF($D85="Jason / Derya",1,0) -> 0 | Q85: =IF($D85="Jason / Basak",1,0) -> 0 | R85: =IF($D85="Jason / Cagla",1,0) -> 0 | S85: FALSE | T85: TRUE | U85: TRUE
A86: Heath Minyard | B86: SGA Design Group | C86: Program Manager | D86: Jason | F86: Walmart (new stores) | G86: =IF(D86="Jason",1,0) -> 1 | H86: =IF($D86="Jordan",1,0) -> 0 | I86: =IF($D86="John",1,0) -> 0 | J86: =IF($D86="Yigit",1,0) -> 0 | K86: =IF($D86="Cagla",1,0) -> 0 | L86: =IF($D86="Berkay",1,0) -> 0 | M86: =IF($D86="Gozde",1,0) -> 0 | N86: =IF($D86="Mertcan",1,0) -> 0 | O86: =IF($D86="Amy",1,0) -> 0 | P86: =IF($D86="Jason / Derya",1,0) -> 0 | Q86: =IF($D86="Jason / Basak",1,0) -> 0 | R86: =IF($D86="Jason / Cagla",1,0) -> 0 | S86: TRUE | T86: TRUE | U86: TRUE
A87: Virginia Hart | B87: SGA Design Group | C87: Principal | D87: Jason | F87: Panda Express, Aldi Revit Conversion | G87: =IF(D87="Jason",1,0) -> 1 | H87: =IF($D87="Jordan",1,0) -> 0 | I87: =IF($D87="John",1,0) -> 0 | J87: =IF($D87="Yigit",1,0) -> 0 | K87: =IF($D87="Cagla",1,0) -> 0 | L87: =IF($D87="Berkay",1,0) -> 0 | M87: =IF($D87="Gozde",1,0) -> 0 | N87: =IF($D87="Mertcan",1,0) -> 0 | O87: =IF($D87="Amy",1,0) -> 0 | P87: =IF($D87="Jason / Derya",1,0) -> 0 | Q87: =IF($D87="Jason / Basak",1,0) -> 0 | R87: =IF($D87="Jason / Cagla",1,0) -> 0 | S87: TRUE | T87: TRUE | U87: TRUE
A88: Hal Staples | B88: SGA Design Group | C88: Principal | D88: Jordan | G88: =IF(D88="Jason",1,0) -> 0 | H88: =IF($D88="Jordan",1,0) -> 1 | I88: =IF($D88="John",1,0) -> 0 | J88: =IF($D88="Yigit",1,0) -> 0 | K88: =IF($D88="Cagla",1,0) -> 0 | L88: =IF($D88="Berkay",1,0) -> 0 | M88: =IF($D88="Gozde",1,0) -> 0 | N88: =IF($D88="Mertcan",1,0) -> 0 | O88: =IF($D88="Amy",1,0) -> 0 | P88: =IF($D88="Jason / Derya",1,0) -> 0 | Q88: =IF($D88="Jason / Basak",1,0) -> 0 | R88: =IF($D88="Jason / Cagla",1,0) -> 0 | S88: TRUE | T88: TRUE | U88: TRUE
A89: Blake Collier | B89: SGA Design Group | C89: Project Manager | D89: Yigit | F89: Panda Express | G89: =IF(D85="Jason",1,0) -> 1 | H89: =IF($D85="Jordan",1,0) -> 0 | I89: =IF($D85="John",1,0) -> 0 | J89: =IF($D85="Yigit",1,0) -> 0 | K89: =IF($D85="Cagla",1,0) -> 0 | L89: =IF($D85="Berkay",1,0) -> 0 | M89: =IF($D85="Gozde",1,0) -> 0 | N89: =IF($D85="Mertcan",1,0) -> 0 | O89: =IF($D85="Amy",1,0) -> 0 | P89: =IF($D85="Jason / Derya",1,0) -> 0 | Q89: =IF($D85="Jason / Basak",1,0) -> 0 | R89: =IF($D85="Jason / Cagla",1,0) -> 0 | S89: FALSE | T89: TRUE | U89: TRUE
A90: Grace Williams | B90: SGA Design Group | C90: Project Manager | D90: Yigit | E90: Weekly | F90: Walmart New Builds | G90: =IF(D86="Jason",1,0) -> 1 | H90: =IF($D86="Jordan",1,0) -> 0 | I90: =IF($D86="John",1,0) -> 0 | J90: =IF($D86="Yigit",1,0) -> 0 | K90: =IF($D86="Cagla",1,0) -> 0 | L90: =IF($D86="Berkay",1,0) -> 0 | M90: =IF($D86="Gozde",1,0) -> 0 | N90: =IF($D86="Mertcan",1,0) -> 0 | O90: =IF($D86="Amy",1,0) -> 0 | P90: =IF($D86="Jason / Derya",1,0) -> 0 | Q90: =IF($D86="Jason / Basak",1,0) -> 0 | R90: =IF($D86="Jason / Cagla",1,0) -> 0 | S90: TRUE | T90: TRUE | U90: TRUE
A91: Jeff Dalton | B91: SGA Design Group | C91: Principal | D91: Yigit | F91: BSFRO | G91: =IF(D87="Jason",1,0) -> 1 | H91: =IF($D87="Jordan",1,0) -> 0 | I91: =IF($D87="John",1,0) -> 0 | J91: =IF($D87="Yigit",1,0) -> 0 | K91: =IF($D87="Cagla",1,0) -> 0 | L91: =IF($D87="Berkay",1,0) -> 0 | M91: =IF($D87="Gozde",1,0) -> 0 | N91: =IF($D87="Mertcan",1,0) -> 0 | O91: =IF($D87="Amy",1,0) -> 0 | P91: =IF($D87="Jason / Derya",1,0) -> 0 | Q91: =IF($D87="Jason / Basak",1,0) -> 0 | R91: =IF($D87="Jason / Cagla",1,0) -> 0 | S91: TRUE | T91: TRUE | U91: TRUE
A92: Scott Carter | B92: TWM Inc. | C92: Project Manager | D92: Berkay | F92: SWARCO Renovation & Expansion Project | G92: =IF(D88="Jason",1,0) -> 0 | H92: =IF($D88="Jordan",1,0) -> 1 | I92: =IF($D88="John",1,0) -> 0 | J92: =IF($D88="Yigit",1,0) -> 0 | K92: =IF($D88="Cagla",1,0) -> 0 | L92: =IF($D88="Berkay",1,0) -> 0 | M92: =IF($D88="Gozde",1,0) -> 0 | N92: =IF($D88="Mertcan",1,0) -> 0 | O92: =IF($D88="Amy",1,0) -> 0 | P92: =IF($D88="Jason / Derya",1,0) -> 0 | Q92: =IF($D88="Jason / Basak",1,0) -> 0 | R92: =IF($D88="Jason / Cagla",1,0) -> 0 | S92: FALSE | T92: TRUE | U92: FALSE
G93: =SUM(G2:G92) -> 35 | H93: =SUM(H2:H92) -> 7 | I93: =SUM(I2:I92) -> 10 | J93: =SUM(J2:J92) -> 15 | K93: =SUM(K2:K92) -> 3 | L93: =SUM(L2:L92) -> 10 | M93: =SUM(M2:M92) -> 2 | N93: =SUM(N2:N92) -> 3 | ... R93: =SUM(R2:R92) -> 0
B95: Total # of Contacts: | C95: =COUNTA(A2:A92) -> 91 | E95: sum = | F95: =SUM(E2:E88) -> 0 | S95: =COUNTIF(S2:S92, TRUE) -> 64 | T95: =COUNTIF(T2:T92, TRUE) -> 55 | U95: =COUNTIF(U2:U92, TRUE) -> 45
S96: =S95/C95 -> 0.7032967 | T96: =T95/C95 -> 0.6043956 | U96: =U95/C95 -> 0.49450549
B99: Number of Clients Per TL & Manager
B100: John | C100: =I93 -> 10
B101: Jason | C101: =G93+Q93+R93+P93 -> 35 | F101: market leaders / VPs (phone calls / teams calls)
B102: Jordan | C102: =H93 -> 7 | F102: project managers
B103: Amy | C103: =O93 -> 1
...

Sheet 2026 BD Categories
A1: BD Approach Summary
A2: Target
A3: Meet (They have not hear of us before) | B3: Met (Introduced but interst in unclear) | C3: Get Pilot (They showed interest) | D3: Develop (1st project done, Get repeat work) | E3: Expand (Find other Divisions/PMs/Sectors) | F3: Maintain (Keep them happy)
A4: Top 50 Firms | B4: Bohler Engineering (Warren, NJ) | C4: Cyntergy (Tulsa, OK) | D4: BL Companies | E4: CESO | F4: DxU
B5: NORR (Detroit, MI) | C5: Benchmark (Rogers, AR) | D5: Atlantic AE | E5: Core States | F5: APEX/FM Group
B6: CECI (Nashville, TN) | C6: Galloway (Witicha, KS) | D6: Flintco | E6: SGA Design Group | F6: Novilla RNG
B7: Kimley Horn | C7: TPG Architects (FL and NY city) | D7: CPH | E7: Adrenaline | F7: TWM
B8: Little (Charlotte, NC) | C8: BRP Arch [hospitality] (Springfield, MO) | D8: Sargent & Lundy | F8: Hitachi Energy
B9: HFA (Bentonville, AR) | C9: Tricarico Architecture (Wayne, NJ) | D9: Silver Studio Architects
B10: bdg Architects | C10: Onyx (Cleveland, OH) | D10: ADA Architects | F10: APS
B11: KTGY (Irvine, CA) | C11: MJM (Nashville, TN) | F11: MG2
B12: API | C12: Zelus (VDC) (Pheonix, AZ)
C13: Colliers Eng. and Design | F13: HLVG
C14: Cooper Carry [hospitality] (Atlanta, GA)
C15: JDA Arch [hospitality] (Woodinville, WA)
C16: Clayco [mutli family] (Chicago, IL)
C17: Crenshaw Consulting (MEP) (Raleigh, NC)
C18: GPRS
C19: Coast 2 Coast
C20: BRR
C21: JCJ
A25: Number of Firms = | B25: =COUNTA(B4:B24) -> 9 | C25: =COUNTA(C4:C24) -> 18 | D25: =COUNTA(D4:D24) -> 7 | E25: =COUNTA(E4:E24) -> 4 | F25: =COUNTA(F4:F24) -> 8
B27: Contact | C27: Address
A28: Cyntergy | B28: Michael Hicks | C28: 810 S Cincinnati Ave # 200, Tulsa, OK 74119
B29: Steve Ryals
B30: Seth Hildebrandt
A32: Benchmark | B32: Jason Adams | C32: 1805 N 2nd St, Rogers, AR 72756
B33: Jason Dodson
B34: Stephanie Whorton
A36: Galloway | B36: Chris Carlson | C36: 400 S Emporia St Suite 300, Wichita, KS 67202
B37: (Caty) Catherine Gaboian
B38: Lexi Bauer
A40: Onyx Creative | B40: Don Alexander | C40: 25001 Emery Rd # 400, Cleveland, OH 44128
A42: Zelus (VDC) | B42: David McDonald | C42: 5013 E. Washington Street, Suite 150, Phoenix, Arizona 85034
A44: TPG Architects | B44: Hernan Graziano | C44: 500 Winderley Place, Suite 218, Maitland, FL, 32751
A46: HFA
A48: Cooper Carry | B48: Dots Colley | C48: 191 Peachtree St #2400, Atlanta, GA 30303
B49: Manny Dominguez
B50: T. Jack Bagby
A52: MJM | B52: Derron Sluser | C52: 2948 Sidco Dr #206, Nashville, TN 37204
B53: Gretchen Baker
A55: ADA Architects | B55: Brian Quinn
B56: James Kassay
B57: Dustin johnston
B58: Lindsay Scott
B59: Jeff Poutney

Sheet 2026 BD Next Steps
A1: BD Approach Summary
A3: Meet (They have not hear of us before) | B3: Status / Next Steps
A4: =IF('2026 BD Categories'!A4=0,"",'2026 BD Categories'!A4) -> Top 50 Firms | B4: Review list from Retail / Multi-site roll out perspective
A5: =IF('2026 BD Categories'!A5=0,"",'2026 BD Categories'!A5) | B5: Create list of top hospitality / multi-family firms
A6: =IF('2026 BD Categories'!A6=0,"",'2026 BD Categories'!A6) | B6: Create list of top engineering firms (SMEP + Civil)
A7: =IF('2026 BD Categories'!A7=0,"",'2026 BD Categories'!A7) | B7: Create list of firms focused on Data Centers
A8: =IF('2026 BD Categories'!A8=0,"",'2026 BD Categories'!A8) | B8: Create list of firms using VDC
A9: =IF('2026 BD Categories'!A9=0,"",'2026 BD Categories'!A9)
A10: =IF('2026 BD Categories'!A10=0,"",'2026 BD Categories'!A10)
A11: =IF('2026 BD Categories'!A11=0,"",'2026 BD Categories'!A11)
A12: =IF('2026 BD Categories'!A12=0,"",'2026 BD Categories'!A12)
A13: =IF('2026 BD Categories'!A13=0,"",'2026 BD Categories'!A13)
A14: =IF('2026 BD Categories'!A14=0,"",'2026 BD Categories'!A14)
A15: =IF('2026 BD Categories'!#REF!=0,"",'2026 BD Categories'!#REF!) -> #REF!
A16: =IF('2026 BD Categories'!#REF!=0,"",'2026 BD Categories'!#REF!) -> #REF!
A17: =IF('2026 BD Categories'!#REF!=0,"",'2026 BD Categories'!#REF!) -> #REF!
A18: =IF('2026 BD Categories'!#REF!=0,"",'2026 BD Categories'!#REF!) -> #REF!
A19: =IF('2026 BD Categories'!#REF!=0,"",'2026 BD Categories'!#REF!) -> #REF!
A20: =IF('2026 BD Categories'!#REF!=0,"",'2026 BD Categories'!#REF!) -> #REF!
A21: =IF('2026 BD Categories'!A21=0,"",'2026 BD Categories'!A21)
A22: =IF('2026 BD Categories'!A22=0,"",'2026 BD Categories'!A22)
A23: =IF('2026 BD Categories'!A23=0,"",'2026 BD Categories'!A23)
A24: =IF('2026 BD Categories'!A24=0,"",'2026 BD Categories'!A24)
A28: Met (Introduced but interst in unclear) | B28: Status / Next Steps
A29: =IF('2026 BD Categories'!B7=0,"",'2026 BD Categories'!B7) -> Kimley Horn
A30: =IF('2026 BD Categories'!B8=0,"",'2026 BD Categories'!B8) -> Little (Charlotte, NC)
A31: =IF('2026 BD Categories'!B9=0,"",'2026 BD Categories'!B9) -> HFA (Bentonville, AR)
A32: =IF('2026 BD Categories'!B4=0,"",'2026 BD Categories'!B4) -> Bohler Engineering (Warren, NJ) | B32: Send case study in Jan.
A33: =IF('2026 BD Categories'!B5=0,"",'2026 BD Categories'!B5) -> NORR (Detroit, MI) | B33: Set up meeting in Jan. with others in office
A34: =IF('2026 BD Categories'!B6=0,"",'2026 BD Categories'!B6) -> CECI (Nashville, TN) | B34: Send case study in Jan.
A35: =IF('2026 BD Categories'!#REF!=0,"",'2026 BD Categories'!#REF!) -> #REF!
A36: =IF('2026 BD Categories'!#REF!=0,"",'2026 BD Categories'!#REF!) -> #REF!
A37: =IF('2026 BD Categories'!B10=0,"",'2026 BD Categories'!B10) -> bdg Architects | B37: holly .... ?
A39: =IF('2026 BD Categories'!B11=0,"",'2026 BD Categories'!B11) -> KTGY (Irvine, CA)
A40: =IF('2026 BD Categories'!B12=0,"",'2026 BD Categories'!B12) -> API
A41: =IF('2026 BD Categories'!A16=0,"",'2026 BD Categories'!A16)
A42: =IF('2026 BD Categories'!A17=0,"",'2026 BD Categories'!A17)
A43: =IF('2026 BD Categories'!A18=0,"",'2026 BD Categories'!A18)
A44: =IF('2026 BD Categories'!A19=0,"",'2026 BD Categories'!A19)
A45: =IF('2026 BD Categories'!B15=0,"",'2026 BD Categories'!B15)
A46: =IF('2026 BD Categories'!A20=0,"",'2026 BD Categories'!A20)
A47: =IF('2026 BD Categories'!B22=0,"",'2026 BD Categories'!B22)
A48: =IF('2026 BD Categories'!B23=0,"",'2026 BD Categories'!B23)
A49: =IF('2026 BD Categories'!B24=0,"",'2026 BD Categories'!B24)
A51: Get Pilot (They showed interest) | B51: Status / Next Steps
A52: =IF('2026 BD Categories'!C4=0,"",'2026 BD Categories'!C4) -> Cyntergy (Tulsa, OK) | B52: Meeting this afternoon 01/13
A53: =IF('2026 BD Categories'!C5=0,"",'2026 BD Categories'!C5) -> Benchmark (Rogers, AR) | B53: Need to reach out Re NDA
A54: =IF('2026 BD Categories'!C6=0,"",'2026 BD Categories'!C6) -> Galloway (Witicha, KS) | B54: Waiting on documents for pricing
A55: =IF('2026 BD Categories'!C10=0,"",'2026 BD Categories'!C10) -> Onyx (Cleveland, OH) | B55: Meeting next week.
A56: =IF('2026 BD Categories'!C12=0,"",'2026 BD Categories'!C12) -> Zelus (VDC) (Pheonix, AZ) | B56: I need to send pricing to him...
A57: =IF('2026 BD Categories'!C7=0,"",'2026 BD Categories'!C7) -> TPG Architects (FL and NY city) | B57: combined proposal sent. Call next week
A58: =IF('2026 BD Categories'!#REF!=0,"",'2026 BD Categories'!#REF!) -> #REF!
A59: =IF('2026 BD Categories'!#REF!=0,"",'2026 BD Categories'!#REF!) -> #REF!
A60: =IF('2026 BD Categories'!C11=0,"",'2026 BD Categories'!C11) -> MJM (Nashville, TN)
A61: =IF('2026 BD Categories'!C22=0,"",'2026 BD Categories'!C22) | B61: Reach back out to ____
A62: =IF('2026 BD Categories'!C14=0,"",'2026 BD Categories'!C14) -> Cooper Carry [hospitality] (Atlanta, GA)
A63: =IF('2026 BD Categories'!C8=0,"",'2026 BD Categories'!C8) -> BRP Arch [hospitality] (Springfield, MO) | B63: Follow up again in March?? (new baby for george, slower start to year)
A64: =IF('2026 BD Categories'!C15=0,"",'2026 BD Categories'!C15) -> JDA Arch [hospitality] (Woodinville, WA) | B64: Reach back out to set up time to chat
A65: =IF('2026 BD Categories'!C16=0,"",'2026 BD Categories'!C16) -> Clayco [mutli family] (Chicago, IL) | B65: reach back out about february
A66: =IF('2026 BD Categories'!D9=0,"",'2026 BD Categories'!D9) -> Silver Studio Architects | B66: by AMY
A67: =IF('2026 BD Categories'!#REF!=0,"",'2026 BD Categories'!#REF!) -> #REF!
A68: =IF('2026 BD Categories'!C17=0,"",'2026 BD Categories'!C17) -> Crenshaw Consulting (MEP) (Raleigh, NC) | B68: Set up meeting
A69: ADA Architects | B69: Get NDA and docs for pricing
A70: Tricarico Architects | B70: Follow up in February. They plan to attend AI webinar
A71: =IF('2026 BD Categories'!#REF!=0,"",'2026 BD Categories'!#REF!) -> #REF!
A72: =IF('2026 BD Categories'!C24=0,"",'2026 BD Categories'!C24)
A74: Develop (1st project done, Get repeat work) | B74: Status / Next Steps
A75: =IF('2026 BD Categories'!D4=0,"",'2026 BD Categories'!D4) -> BL Companies | B75: Barbara - AI + Guardhouses, visit in Feb Maite - Discount Tire
A76: =IF('2026 BD Categories'!D5=0,"",'2026 BD Categories'!D5) -> Atlantic AE | B76: Patrick Gaither - SSDs
A77: =IF('2026 BD Categories'!D7=0,"",'2026 BD Categories'!D7) -> CPH | B77: Joshua Sleeter - AI
A78: =IF('2026 BD Categories'!D8=0,"",'2026 BD Categories'!D8) -> Sargent & Lundy | B78: Justin M. - reach back out mid feb. Dana Reeves - visit in February
A79: =IF('2026 BD Categories'!D6=0,"",'2026 BD Categories'!D6) -> Flintco | B79: Kevin B. - follow up after projects.
A80: =IF('2026 BD Categories'!#REF!=0,"",'2026 BD Categories'!#REF!) -> #REF!
A81: =IF('2026 BD Categories'!#REF!=0,"",'2026 BD Categories'!#REF!) -> #REF!
A82: =IF('2026 BD Categories'!D11=0,"",'2026 BD Categories'!D11)
A83: =IF('2026 BD Categories'!D12=0,"",'2026 BD Categories'!D12)
A84: =IF('2026 BD Categories'!D13=0,"",'2026 BD Categories'!D13)
A85: =IF('2026 BD Categories'!D14=0,"",'2026 BD Categories'!D14)
A86: =IF('2026 BD Categories'!D15=0,"",'2026 BD Categories'!D15)
A87: =IF('2026 BD Categories'!D16=0,"",'2026 BD Categories'!D16)
A88: =IF('2026 BD Categories'!D17=0,"",'2026 BD Categories'!D17)
A89: =IF('2026 BD Categories'!D18=0,"",'2026 BD Categories'!D18)
A90: =IF('2026 BD Categories'!D19=0,"",'2026 BD Categories'!D19)
A91: =IF('2026 BD Categories'!D20=0,"",'2026 BD Categories'!D20)
A92: =IF('2026 BD Categories'!D21=0,"",'2026 BD Categories'!D21)
A93: =IF('2026 BD Categories'!D22=0,"",'2026 BD Categories'!D22)
... A95: =IF('2026 BD Categories'!D24=0,"",'2026 BD Categories'!D24)
A97: Expand (Find other Divisions/PMs/Sectors)
A98: CESO | B98: Expand within Walmart and Auto/Conv.
A99: Core States | B99: Retail, Resturants, Walmart(?), Sams (?), Target Convienece and Auto
A100: SGA Design Group | B100: Target Walmart New Stores, Add AMZON SSD and RSR, target Sams Club Remodels
A101: Adrenaline | B101: Add Kim Beardsworth's group, target construction group?
A120: Maintain (Keep them happy)
A121: DxU | B121: Picklr, Solidcore, Glowbar, ????
A122: APEX/FM Group
A123: Novilla RNG
A124: TWM
A125: Hitachi Energy
A127: APS
A128: MG2
